Workbook
Name Slicer_Error_Type: #N/A
Name Slicer_Lead_Registration_Date: #N/A
Name Slicer_Project_Name: #N/A
Name Slicer_Severity: #N/A
Name Slicer_Telecaller_Name: #N/A

Sheet Cover
A1: Guru Punvaanii – Telecalling Quality Audit
A2: Reusable daily audit workbook • paste CRM data into Raw Data
A4: CONTENTS
A5: Raw Data | B5: Paste or replace the daily CRM export; audit formulas extend with the table.
A6: Executive Dashboard | B6: Management KPIs, reporting period, and headline audit story.
A7: Telecaller Performance | B7: Ranked accuracy scorecard with ratings and severity counts.
A8: Graphical Dashboard | B8: Five visual summaries of accuracy, errors, projects, and severity.
A9: Detailed Error Report | B9: Filterable record-level exceptions with actions and audit status.

Sheet Raw Data
A1: Project Name | B1: Mobile | C1: Telecaller Name | D1: Lead Registration Date | E1: Lead Status | F1: Comments | G1: Next Followup Date | H1: Location | I1: Overdue Days | J1: Status | K1: Analysis Parameter | L1: Customer Requirement | M1: Source | N1: Source Name | O1: Totals | P1: Error Type | Q1: Error Details | R1: Recommended Action | S1: Severity | T1: Audit Status | U1: Error Flag | V1: Accuracy | W1: Telecaller | X1: Accuracy | Z1: Telecaller | AA1: Errors | AC1: Error Type | AD1: Count | AF1: Project | AG1: Errors | AI1: Severity | AJ1: Count
A2: Guru Punvaanii EKA | B2: 7899415022 | C2: Vinutha M1 | D2: 46254 | E2: warm | F2: Seeing for 1200-1500sqft , located at uttarahalli , seeing for self use , said budget is fine , asked me to share details they will check and get back | G2: 46256.458 | I2: -1 | J2: Interested | K2: In Progress | L2: Seeing for 1200-1500sqft , located at uttarahalli , seeing for self use , said budget is fine | M2: Digital Marketing | N2: Meta_StaticAds_Aug2026 | O2: 1 | P2: =IF(RawData[[#This Row],[Mobile]]="","",_xlfn.TEXTJOIN(" | ",TRUE,IF(AND(OR(LOWER(TRIM(RawData[[#This Row],[Lead Status]]))="cold",LOWER(TRIM(RawData[[#This Row],[Lead Status]]))="lost"),OR(ISNUMBER(SEARCH("visit",LOWER(TRIM(RawData[[#This Row],[Comments]])))),ISNUMBER(SEARCH("brochure",LOWER(TRIM(RawData[[#This Row],[Comments]])))),ISNUMBER(SEARCH("pricing",LOWER(TRIM(RawData[[#This Row],[Comments]])))),ISNUMBER(SEARCH("price",LOWER(TRIM(RawData[[#This Row],[Comments]])))),ISNUMBER(SEARCH("budget",LOWER(TRIM(RawData[[#This Row],[Comments]])))))),"Wrong Lead Status",""),IF(AND(LOWER(TRIM(RawData[[#This Row],[Lead Status]]))="cold",OR(LOWER(TRIM(RawData[[#This Row],[Comments]]))="rnr",LOWER(TRIM(RawData[[#This Row],[Comments]]))="busy",LOWER(TRIM(RawData[[#This Row],[Comments]]))="out of network",LOWER(TRIM(RawData[[#This Row],[Comments]]))="outoff network",LOWER(TRIM(RawData[[#This Row],[Comments]]))="voice mail",LOWER(TRIM(RawData[[#This Row],[Comments]]))="voicemail")),"RNR Classification Error",""),IF(AND(LOWER(TRIM(RawData[[#This Row],[Lead Status]]))="warm",OR(LOWER(TRIM(RawData[[#This Row],[Comments]]))="busy",LOWER(TRIM(RawData[[#This Row],[Comments]]))="voice mail",LOWER(TRIM(RawData[[#This Row],[Comments]]))="voicemail",LOWER(TRIM(RawData[[#This Row],[Comments]]))="call back later")),"Warm Status Mismatch",""),IF(AND(LOWER(TRIM(RawData[[#This Row],[Status]]))="rnr",OR(ISNUMBER(SEARCH("requirement",LOWER(RawData[[#This Row],[Comments]]&" "&RawData[[#This Row],[Customer Requirement]]))),ISNUMBER(SEARCH("budget",LOWER(RawData[[#This Row],[Comments]]&" "&RawData[[#This Row],[Customer Requirement]]))),ISNUMBER(SEARCH("location",LOWER(RawData[[#This Row],[Comments]]&" "&RawData[[#This Row],[Customer Requirement]]))),ISNUMBER(SEARCH("purpose",LOWER(RawData[[#This Row],[Comments]]&" "&RawData[[#This Row],[Customer Requirement]]))),ISNUMBER(SEARCH("dimension",LOWER(RawData[[#This Row],[Comments]]&" "&RawData[[#This Row],[Customer Requirement]]))),ISNUMBER(SEARCH("sqft",LOWER(RawData[[#This Row],[Comments]]&" "&RawData[[#This Row],[Customer Requirement]]))))),"CRM Status Mismatch",""),IF(AND(ISNUMBER(RawData[[#This Row],[Next Followup Date]]),RawData[[#This Row],[Next Followup Date]]<NOW(),OR(LOWER(TRIM(RawData[[#This Row],[Lead Status]]))="hot",LOWER(TRIM(RawData[[#This Row],[Lead Status]]))="prospect",LOWER(TRIM(RawData[[#This Row],[Lead Status]]))="warm")),"Follow-up Error",""),IF(AND(LOWER(TRIM(RawData[[#This Row],[Location]]))="anekal",OR(ISNUMBER(SEARCH("ernika",LOWER(RawData[[#This Row],[Project Name]]))),ISNUMBER(SEARCH("enrika",LOWER(RawData[[#This Row],[Project Name]]))),ISNUMBER(SEARCH("exotica",LOWER(RawData[[#This Row],[Project Name]]))),ISNUMBER(SEARCH(" eka",LOWER(RawData[[#This Row],[Project Name]]))))),"Customer Location Not Captured",""))) | Q2: =IF(RawData[[#This Row],[Mobile]]="","",_xlfn.TEXTJOIN(CHAR(10),TRUE,IF(AND(OR(LOWER(TRIM(RawData[[#This Row],[Lead Status]]))="cold",LOWER(TRIM(RawData[[#This Row],[Lead Status]]))="lost"),OR(ISNUMBER(SEARCH("visit",LOWER(TRIM(RawData[[#This Row],[Comments]])))),ISNUMBER(SEARCH("brochure",LOWER(TRIM(RawData[[#This Row],[Comments]])))),ISNUMBER(SEARCH("pricing",LOWER(TRIM(RawData[[#This Row],[Comments]])))),ISNUMBER(SEARCH("price",LOWER(TRIM(RawData[[#This Row],[Comments]])))),ISNUMBER(SEARCH("budget",LOWER(TRIM(RawData[[#This Row],[Comments]])))))),"Engagement intent conflicts with Cold/Lost status",""),IF(AND(LOWER(TRIM(RawData[[#This Row],[Lead Status]]))="cold",OR(LOWER(TRIM(RawData[[#This Row],[Comments]]))="rnr",LOWER(TRIM(RawData[[#This Row],[Comments]]))="busy",LOWER(TRIM(RawData[[#This Row],[Comments]]))="out of network",LOWER(TRIM(RawData[[#This Row],[Comments]]))="outoff network",LOWER(TRIM(RawData[[#This Row],[Comments]]))="voice mail",LOWER(TRIM(RawData[[#This Row],[Comments]]))="voicemail")),"Contact outcome should remain RNR rather than Cold",""),IF(AND(LOWER(TRIM(RawData[[#This Row],[Lead Status]]))="warm",OR(LOWER(TRIM(RawData[[#This Row],[Comments]]))="busy",LOWER(TRIM(RawData[[#This Row],[Comments]]))="voice mail",LOWER(TRIM(RawData[[#This Row],[Comments]]))="voicemail",LOWER(TRIM(RawData[[#This Row],[Comments]]))="call back later")),"Contact-only outcome does not support Warm status",""),IF(AND(LOWER(TRIM(RawData[[#This Row],[Status]]))="rnr",OR(ISNUMBER(SEARCH("requirement",LOWER(RawData[[#This Row],[Comments]]&" "&RawData[[#This Row],[Customer Requirement]]))),ISNUMBER(SEARCH("budget",LOWER(RawData[[#This Row],[Comments]]&" "&RawData[[#This Row],[Customer Requirement]]))),ISNUMBER(SEARCH("location",LOWER(RawData[[#This Row],[Comments]]&" "&RawData[[#This Row],[Customer Requirement]]))),ISNUMBER(SEARCH("purpose",LOWER(RawData[[#This Row],[Comments]]&" "&RawData[[#This Row],[Customer Requirement]]))),ISNUMBER(SEARCH("dimension",LOWER(RawData[[#This Row],[Comments]]&" "&RawData[[#This Row],[Customer Requirement]]))),ISNUMBER(SEARCH("sqft",LOWER(RawData[[#This Row],[Comments]]&" "&RawData[[#This Row],[Customer Requirement]]))))),"Requirements were captured while CRM status remains RNR",""),IF(AND(ISNUMBER(RawData[[#This Row],[Next Followup Date]]),RawData[[#This Row],[Next Followup Date]]<NOW(),OR(LOWER(TRIM(RawData[[#This Row],[Lead Status]]))="hot",LOWER(TRIM(RawData[[#This Row],[Lead Status]]))="prospect",LOWER(TRIM(RawData[[#This Row],[Lead Status]]))="warm")),"Follow-up date/time has passed for an active lead",""),IF(AND(LOWER(TRIM(RawData[[#This Row],[Location]]))="anekal",OR(ISNUMBER(SEARCH("ernika",LOWER(RawData[[#This Row],[Project Name]]))),ISNUMBER(SEARCH("enrika",LOWER(RawData[[#This Row],[Project Name]]))),ISNUMBER(SEARCH("exotica",LOWER(RawData[[#This Row],[Project Name]]))),ISNUMBER(SEARCH(" eka",LOWER(RawData[[#This Row],[Project Name]]))))),"Anekal is the project default; customer location was not captured",""))) | R2: =IF(RawData[[#This Row],[Mobile]]="","",_xlfn.TEXTJOIN(CHAR(10),TRUE,IF(AND(OR(LOWER(TRIM(RawData[[#This Row],[Lead Status]]))="cold",LOWER(TRIM(RawData[[#This Row],[Lead Status]]))="lost"),OR(ISNUMBER(SEARCH("visit",LOWER(TRIM(RawData[[#This Row],[Comments]])))),ISNUMBER(SEARCH("brochure",LOWER(TRIM(RawData[[#This Row],[Comments]])))),ISNUMBER(SEARCH("pricing",LOWER(TRIM(RawData[[#This Row],[Comments]])))),ISNUMBER(SEARCH("price",LOWER(TRIM(RawData[[#This Row],[Comments]])))),ISNUMBER(SEARCH("budget",LOWER(TRIM(RawData[[#This Row],[Comments]])))))),"Reclassify lead and schedule a documented follow-up",""),IF(AND(LOWER(TRIM(RawData[[#This Row],[Lead Status]]))="cold",OR(LOWER(TRIM(RawData[[#This Row],[Comments]]))="rnr",LOWER(TRIM(RawData[[#This Row],[Comments]]))="busy",LOWER(TRIM(RawData[[#This Row],[Comments]]))="out of network",LOWER(TRIM(RawData[[#This Row],[Comments]]))="outoff network",LOWER(TRIM(RawData[[#This Row],[Comments]]))="voice mail",LOWER(TRIM(RawData[[#This Row],[Comments]]))="voicemail")),"Change lead classification to RNR and retry contact",""),IF(AND(LOWER(TRIM(RawData[[#This Row],[Lead Status]]))="warm",OR(LOWER(TRIM(RawData[[#This Row],[Comments]]))="busy",LOWER(TRIM(RawData[[#This Row],[Comments]]))="voice mail",LOWER(TRIM(RawData[[#This Row],[Comments]]))="voicemail",LOWER(TRIM(RawData[[#This Row],[Comments]]))="call back later")),"Validate engagement before retaining Warm status",""),IF(AND(LOWER(TRIM(RawData[[#This Row],[Status]]))="rnr",OR(ISNUMBER(SEARCH("requirement",LOWER(RawData[[#This Row],[Comments]]&" "&RawData[[#This Row],[Customer Requirement]]))),ISNUMBER(SEARCH("budget",LOWER(RawData[[#This Row],[Comments]]&" "&RawData[[#This Row],[Customer Requirement]]))),ISNUMBER(SEARCH("location",LOWER(RawData[[#This Row],[Comments]]&" "&RawData[[#This Row],[Customer Requirement]]))),ISNUMBER(SEARCH("purpose",LOWER(RawData[[#This Row],[Comments]]&" "&RawData[[#This Row],[Customer Requirement]]))),ISNUMBER(SEARCH("dimension",LOWER(RawData[[#This Row],[Comments]]&" "&RawData[[#This Row],[Customer Requirement]]))),ISNUMBER(SEARCH("sqft",LOWER(RawData[[#This Row],[Comments]]&" "&RawData[[#This Row],[Customer Requirement]]))))),"Update CRM status to reflect the collected requirement",""),IF(AND(ISNUMBER(RawData[[#This Row],[Next Followup Date]]),RawData[[#This Row],[Next Followup Date]]<NOW(),OR(LOWER(TRIM(RawData[[#This Row],[Lead Status]]))="hot",LOWER(TRIM(RawData[[#This Row],[Lead Status]]))="prospect",LOWER(TRIM(RawData[[#This Row],[Lead Status]]))="warm")),"Contact immediately and set the next follow-up",""),IF(AND(LOWER(TRIM(RawData[[#This Row],[Location]]))="anekal",OR(ISNUMBER(SEARCH("ernika",LOWER(RawData[[#This Row],[Project Name]]))),ISNUMBER(SEARCH("enrika",LOWER(RawData[[#This Row],[Project Name]]))),ISNUMBER(SEARCH("exotica",LOWER(RawData[[#This Row],[Project Name]]))),ISNUMBER(SEARCH(" eka",LOWER(RawData[[#This Row],[Project Name]]))))),"Contact the customer and record their actual location",""))) | S2: =IF(RawData[[#This Row],[Error Flag]]=0,"",IF(OR(ISNUMBER(SEARCH("Wrong Lead Status",RawData[[#This Row],[Error Type]])),ISNUMBER(SEARCH("RNR Classification Error",RawData[[#This Row],[Error Type]])),ISNUMBER(SEARCH("Follow-up Error",RawData[[#This Row],[Error Type]]))),"Critical","Medium")) | T2: =IF(RawData[[#This Row],[Error Flag]]=0,"Pass","Action Required ("&RawData[[#This Row],[Error Flag]]&IF(RawData[[#This Row],[Error Flag]]=1," error)"," errors)")) -> Pass | U2: =IF(RawData[[#This Row],[Mobile]]="",0,--(AND(OR(LOWER(TRIM(RawData[[#This Row],[Lead Status]]))="cold",LOWER(TRIM(RawData[[#This Row],[Lead Status]]))="lost"),OR(ISNUMBER(SEARCH("visit",LOWER(TRIM(RawData[[#This Row],[Comments]])))),ISNUMBER(SEARCH("brochure",LOWER(TRIM(RawData[[#This Row],[Comments]])))),ISNUMBER(SEARCH("pricing",LOWER(TRIM(RawData[[#This Row],[Comments]])))),ISNUMBER(SEARCH("price",LOWER(TRIM(RawData[[#This Row],[Comments]])))),ISNUMBER(SEARCH("budget",LOWER(TRIM(RawData[[#This Row],[Comments]])))))))+--(AND(LOWER(TRIM(RawData[[#This Row],[Lead Status]]))="cold",OR(LOWER(TRIM(RawData[[#This Row],[Comments]]))="rnr",LOWER(TRIM(RawData[[#This Row],[Comments]]))="busy",LOWER(TRIM(RawData[[#This Row],[Comments]]))="out of network",LOWER(TRIM(RawData[[#This Row],[Comments]]))="outoff network",LOWER(TRIM(RawData[[#This Row],[Comments]]))="voice mail",LOWER(TRIM(RawData[[#This Row],[Comments]]))="voicemail")))+--(AND(LOWER(TRIM(RawData[[#This Row],[Lead Status]]))="warm",OR(LOWER(TRIM(RawData[[#This Row],[Comments]]))="busy",LOWER(TRIM(RawData[[#This Row],[Comments]]))="voice mail",LOWER(TRIM(RawData[[#This Row],[Comments]]))="voicemail",LOWER(TRIM(RawData[[#This Row],[Comments]]))="call back later")))+--(AND(LOWER(TRIM(RawData[[#This Row],[Status]]))="rnr",OR(ISNUMBER(SEARCH("requirement",LOWER(RawData[[#This Row],[Comments]]&" "&RawData[[#This Row],[Customer Requirement]]))),ISNUMBER(SEARCH("budget",LOWER(RawData[[#This Row],[Comments]]&" "&RawData[[#This Row],[Customer Requirement]]))),ISNUMBER(SEARCH("location",LOWER(RawData[[#This Row],[Comments]]&" "&RawData[[#This Row],[Customer Requirement]]))),ISNUMBER(SEARCH("purpose",LOWER(RawData[[#This Row],[Comments]]&" "&RawData[[#This Row],[Customer Requirement]]))),ISNUMBER(SEARCH("dimension",LOWER(RawData[[#This Row],[Comments]]&" "&RawData[[#This Row],[Customer Requirement]]))),ISNUMBER(SEARCH("sqft",LOWER(RawData[[#This Row],[Comments]]&" "&RawData[[#This Row],[Customer Requirement]]))))))+--(AND(ISNUMBER(RawData[[#This Row],[Next Followup Date]]),RawData[[#This Row],[Next Followup Date]]<NOW(),OR(LOWER(TRIM(RawData[[#This Row],[Lead Status]]))="hot",LOWER(TRIM(RawData[[#This Row],[Lead Status]]))="prospect",LOWER(TRIM(RawData[[#This Row],[Lead Status]]))="warm")))+--(AND(LOWER(TRIM(RawData[[#This Row],[Location]]))="anekal",OR(ISNUMBER(SEARCH("ernika",LOWER(RawData[[#This Row],[Project Name]]))),ISNUMBER(SEARCH("enrika",LOWER(RawData[[#This Row],[Project Name]]))),ISNUMBER(SEARCH("exotica",LOWER(RawData[[#This Row],[Project Name]]))),ISNUMBER(SEARCH(" eka",LOWER(RawData[[#This Row],[Project Name]]))))))) -> 0 | W2: ='Telecaller Performance'!A6 -> Prathima Hegde | X2: {=IF(W2="",NA(),_xlfn.LET(_xlpm.v,SUBTOTAL(103,OFFSET(RawData[Mobile],ROW(RawData[Mobile])-MIN(ROW(RawData[Mobile])),0,1)),_xlpm.z,SUMPRODUCT(_xlpm.v,--(RawData[Telecaller Name]=W2)),IF(_xlpm.z=0,NA(),MAX(0,1-SUMPRODUCT(_xlpm.v,--(RawData[Telecaller Name]=W2),RawData[Error Flag])/_xlpm.z))))} -> 1 | Z2: ='Telecaller Performance'!A6 -> Prathima Hegde | AA2: {=IF(Z2="",NA(),_xlfn.LET(_xlpm.v,SUBTOTAL(103,OFFSET(RawData[Mobile],ROW(RawData[Mobile])-MIN(ROW(RawData[Mobile])),0,1)),_xlpm.z,SUMPRODUCT(_xlpm.v,--(RawData[Telecaller Name]=Z2)),IF(_xlpm.z=0,NA(),SUMPRODUCT(_xlpm.v,--(RawData[Telecaller Name]=Z2),RawData[Error Flag]))))} -> 0 | AC2: Wrong Lead Status | AD2: {=_xlfn.LET(_xlpm.v,SUBTOTAL(103,OFFSET(RawData[Mobile],ROW(RawData[Mobile])-MIN(ROW(RawData[Mobile])),0,1)),SUMPRODUCT(_xlpm.v,--ISNUMBER(SEARCH(AC2,RawData[Error Type]))))} -> 3 | AF2: {=IFERROR(INDEX(_xlfn._xlws.SORT(_xlfn.UNIQUE(_xlfn._xlws.FILTER(RawData[Project Name],RawData[Project Name]<>""))),ROWS(AF$2:AF2)),"")} -> Guru Punvaanii EKA | AG2: {=IF(AF2="",NA(),_xlfn.LET(_xlpm.v,SUBTOTAL(103,OFFSET(RawData[Mobile],ROW(RawData[Mobile])-MIN(ROW(RawData[Mobile])),0,1)),_xlpm.z,SUMPRODUCT(_xlpm.v,--(RawData[Project Name]=AF2)),IF(_xlpm.z=0,NA(),SUMPRODUCT(_xlpm.v,--(RawData[Project Name]=AF2),RawData[Error Flag]))))} -> 1 | AI2: Critical | AJ2: {=_xlfn.LET(_xlpm.v,SUBTOTAL(103,OFFSET(RawData[Mobile],ROW(RawData[Mobile])-MIN(ROW(RawData[Mobile])),0,1)),SUMPRODUCT(_xlpm.v,--ISNUMBER(SEARCH("Wrong Lead Status",RawData[Error Type])))+SUMPRODUCT(_xlpm.v,--ISNUMBER(SEARCH("RNR Classification Error",RawData[Error Type])))+SUMPRODUCT(_xlpm.v,--ISNUMBER(SEARCH("Follow-up Error",RawData[Error Type]))))} -> 8
A3: Guru Punvaanii EKA | B3: 8861583888 | C3: Vinutha M1 | D3: 46253 | E3: warm | F3: Txted in whatsapp asked me to share details | G3: 46256.495 | H3: Anekal | I3: -1 | J3: Interested | K3: RNR | L3: . | M3: Digital Marketing | N3: SEO | O3: 1 | P3: =IF(RawData[[#This Row],[Mobile]]="","",_xlfn.TEXTJOIN(" | ",TRUE,IF(AND(OR(LOWER(TRIM(RawData[[#This Row],[Lead Status]]))="cold",LOWER(TRIM(RawData[[#This Row],[Lead Status]]))="lost"),OR(ISNUMBER(SEARCH("visit",LOWER(TRIM(RawData[[#This Row],[Comments]])))),ISNUMBER(SEARCH("brochure",LOWER(TRIM(RawData[[#This Row],[Comments]])))),ISNUMBER(SEARCH("pricing",LOWER(TRIM(RawData[[#This Row],[Comments]])))),ISNUMBER(SEARCH("price",LOWER(TRIM(RawData[[#This Row],[Comments]])))),ISNUMBER(SEARCH("budget",LOWER(TRIM(RawData[[#This Row],[Comments]])))))),"Wrong Lead Status",""),IF(AND(LOWER(TRIM(RawData[[#This Row],[Lead Status]]))="cold",OR(LOWER(TRIM(RawData[[#This Row],[Comments]]))="rnr",LOWER(TRIM(RawData[[#This Row],[Comments]]))="busy",LOWER(TRIM(RawData[[#This Row],[Comments]]))="out of network",LOWER(TRIM(RawData[[#This Row],[Comments]]))="outoff network",LOWER(TRIM(RawData[[#This Row],[Comments]]))="voice mail",LOWER(TRIM(RawData[[#This Row],[Comments]]))="voicemail")),"RNR Classification Error",""),IF(AND(LOWER(TRIM(RawData[[#This Row],[Lead Status]]))="warm",OR(LOWER(TRIM(RawData[[#This Row],[Comments]]))="busy",LOWER(TRIM(RawData[[#This Row],[Comments]]))="voice mail",LOWER(TRIM(RawData[[#This Row],[Comments]]))="voicemail",LOWER(TRIM(RawData[[#This Row],[Comments]]))="call back later")),"Warm Status Mismatch",""),IF(AND(LOWER(TRIM(RawData[[#This Row],[Status]]))="rnr",OR(ISNUMBER(SEARCH("requirement",LOWER(RawData[[#This Row],[Comments]]&" "&RawData[[#This Row],[Customer Requirement]]))),ISNUMBER(SEARCH("budget",LOWER(RawData[[#This Row],[Comments]]&" "&RawData[[#This Row],[Customer Requirement]]))),ISNUMBER(SEARCH("location",LOWER(RawData[[#This Row],[Comments]]&" "&RawData[[#This Row],[Customer Requirement]]))),ISNUMBER(SEARCH("purpose",LOWER(RawData[[#This Row],[Comments]]&" "&RawData[[#This Row],[Customer Requirement]]))),ISNUMBER(SEARCH("dimension",LOWER(RawData[[#This Row],[Comments]]&" "&RawData[[#This Row],[Customer Requirement]]))),ISNUMBER(SEARCH("sqft",LOWER(RawData[[#This Row],[Comments]]&" "&RawData[[#This Row],[Customer Requirement]]))))),"CRM Status Mismatch",""),IF(AND(ISNUMBER(RawData[[#This Row],[Next Followup Date]]),RawData[[#This Row],[Next Followup Date]]<NOW(),OR(LOWER(TRIM(RawData[[#This Row],[Lead Status]]))="hot",LOWER(TRIM(RawData[[#This Row],[Lead Status]]))="prospect",LOWER(TRIM(RawData[[#This Row],[Lead Status]]))="warm")),"Follow-up Error",""),IF(AND(LOWER(TRIM(RawData[[#This Row],[Location]]))="anekal",OR(ISNUMBER(SEARCH("ernika",LOWER(RawData[[#This Row],[Project Name]]))),ISNUMBER(SEARCH("enrika",LOWER(RawData[[#This Row],[Project Name]]))),ISNUMBER(SEARCH("exotica",LOWER(RawData[[#This Row],[Project Name]]))),ISNUMBER(SEARCH(" eka",LOWER(RawData[[#This Row],[Project Name]]))))),"Customer Location Not Captured",""))) -> Customer Location Not Captured | Q3: =IF(RawData[[#This Row],[Mobile]]="","",_xlfn.TEXTJOIN(CHAR(10),TRUE,IF(AND(OR(LOWER(TRIM(RawData[[#This Row],[Lead Status]]))="cold",LOWER(TRIM(RawData[[#This Row],[Lead Status]]))="lost"),OR(ISNUMBER(SEARCH("visit",LOWER(TRIM(RawData[[#This Row],[Comments]])))),ISNUMBER(SEARCH("brochure",LOWER(TRIM(RawData[[#This Row],[Comments]])))),ISNUMBER(SEARCH("pricing",LOWER(TRIM(RawData[[#This Row],[Comments]])))),ISNUMBER(SEARCH("price",LOWER(TRIM(RawData[[#This Row],[Comments]])))),ISNUMBER(SEARCH("budget",LOWER(TRIM(RawData[[#This Row],[Comments]])))))),"Engagement intent conflicts with Cold/Lost status",""),IF(AND(LOWER(TRIM(RawData[[#This Row],[Lead Status]]))="cold",OR(LOWER(TRIM(RawData[[#This Row],[Comments]]))="rnr",LOWER(TRIM(RawData[[#This Row],[Comments]]))="busy",LOWER(TRIM(RawData[[#This Row],[Comments]]))="out of network",LOWER(TRIM(RawData[[#This Row],[Comments]]))="outoff network",LOWER(TRIM(RawData[[#This Row],[Comments]]))="voice mail",LOWER(TRIM(RawData[[#This Row],[Comments]]))="voicemail")),"Contact outcome should remain RNR rather than Cold",""),IF(AND(LOWER(TRIM(RawData[[#This Row],[Lead Status]]))="warm",OR(LOWER(TRIM(RawData[[#This Row],[Comments]]))="busy",LOWER(TRIM(RawData[[#This Row],[Comments]]))="voice mail",LOWER(TRIM(RawData[[#This Row],[Comments]]))="voicemail",LOWER(TRIM(RawData[[#This Row],[Comments]]))="call back later")),"Contact-only outcome does not support Warm status",""),IF(AND(LOWER(TRIM(RawData[[#This Row],[Status]]))="rnr",OR(ISNUMBER(SEARCH("requirement",LOWER(RawData[[#This Row],[Comments]]&" "&RawData[[#This Row],[Customer Requirement]]))),ISNUMBER(SEARCH("budget",LOWER(RawData[[#This Row],[Comments]]&" "&RawData[[#This Row],[Customer Requirement]]))),ISNUMBER(SEARCH("location",LOWER(RawData[[#This Row],[Comments]]&" "&RawData[[#This Row],[Customer Requirement]]))),ISNUMBER(SEARCH("purpose",LOWER(RawData[[#This Row],[Comments]]&" "&RawData[[#This Row],[Customer Requirement]]))),ISNUMBER(SEARCH("dimension",LOWER(RawData[[#This Row],[Comments]]&" "&RawData[[#This Row],[Customer Requirement]]))),ISNUMBER(SEARCH("sqft",LOWER(RawData[[#This Row],[Comments]]&" "&RawData[[#This Row],[Customer Requirement]]))))),"Requirements were captured while CRM status remains RNR",""),IF(AND(ISNUMBER(RawData[[#This Row],[Next Followup Date]]),RawData[[#This Row],[Next Followup Date]]<NOW(),OR(LOWER(TRIM(RawData[[#This Row],[Lead Status]]))="hot",LOWER(TRIM(RawData[[#This Row],[Lead Status]]))="prospect",LOWER(TRIM(RawData[[#This Row],[Lead Status]]))="warm")),"Follow-up date/time has passed for an active lead",""),IF(AND(LOWER(TRIM(RawData[[#This Row],[Location]]))="anekal",OR(ISNUMBER(SEARCH("ernika",LOWER(RawData[[#This Row],[Project Name]]))),ISNUMBER(SEARCH("enrika",LOWER(RawData[[#This Row],[Project Name]]))),ISNUMBER(SEARCH("exotica",LOWER(RawData[[#This Row],[Project Name]]))),ISNUMBER(SEARCH(" eka",LOWER(RawData[[#This Row],[Project Name]]))))),"Anekal is the project default; customer location was not captured",""))) -> Anekal is the project default; customer location was not captured | R3: =IF(RawData[[#This Row],[Mobile]]="","",_xlfn.TEXTJOIN(CHAR(10),TRUE,IF(AND(OR(LOWER(TRIM(RawData[[#This Row],[Lead Status]]))="cold",LOWER(TRIM(RawData[[#This Row],[Lead Status]]))="lost"),OR(ISNUMBER(SEARCH("visit",LOWER(TRIM(RawData[[#This Row],[Comments]])))),ISNUMBER(SEARCH("brochure",LOWER(TRIM(RawData[[#This Row],[Comments]])))),ISNUMBER(SEARCH("pricing",LOWER(TRIM(RawData[[#This Row],[Comments]])))),ISNUMBER(SEARCH("price",LOWER(TRIM(RawData[[#This Row],[Comments]])))),ISNUMBER(SEARCH("budget",LOWER(TRIM(RawData[[#This Row],[Comments]])))))),"Reclassify lead and schedule a documented follow-up",""),IF(AND(LOWER(TRIM(RawData[[#This Row],[Lead Status]]))="cold",OR(LOWER(TRIM(RawData[[#This Row],[Comments]]))="rnr",LOWER(TRIM(RawData[[#This Row],[Comments]]))="busy",LOWER(TRIM(RawData[[#This Row],[Comments]]))="out of network",LOWER(TRIM(RawData[[#This Row],[Comments]]))="outoff network",LOWER(TRIM(RawData[[#This Row],[Comments]]))="voice mail",LOWER(TRIM(RawData[[#This Row],[Comments]]))="voicemail")),"Change lead classification to RNR and retry contact",""),IF(AND(LOWER(TRIM(RawData[[#This Row],[Lead Status]]))="warm",OR(LOWER(TRIM(RawData[[#This Row],[Comments]]))="busy",LOWER(TRIM(RawData[[#This Row],[Comments]]))="voice mail",LOWER(TRIM(RawData[[#This Row],[Comments]]))="voicemail",LOWER(TRIM(RawData[[#This Row],[Comments]]))="call back later")),"Validate engagement before retaining Warm status",""),IF(AND(LOWER(TRIM(RawData[[#This Row],[Status]]))="rnr",OR(ISNUMBER(SEARCH("requirement",LOWER(RawData[[#This Row],[Comments]]&" "&RawData[[#This Row],[Customer Requirement]]))),ISNUMBER(SEARCH("budget",LOWER(RawData[[#This Row],[Comments]]&" "&RawData[[#This Row],[Customer Requirement]]))),ISNUMBER(SEARCH("location",LOWER(RawData[[#This Row],[Comments]]&" "&RawData[[#This Row],[Customer Requirement]]))),ISNUMBER(SEARCH("purpose",LOWER(RawData[[#This Row],[Comments]]&" "&RawData[[#This Row],[Customer Requirement]]))),ISNUMBER(SEARCH("dimension",LOWER(RawData[[#This Row],[Comments]]&" "&RawData[[#This Row],[Customer Requirement]]))),ISNUMBER(SEARCH("sqft",LOWER(RawData[[#This Row],[Comments]]&" "&RawData[[#This Row],[Customer Requirement]]))))),"Update CRM status to reflect the collected requirement",""),IF(AND(ISNUMBER(RawData[[#This Row],[Next Followup Date]]),RawData[[#This Row],[Next Followup Date]]<NOW(),OR(LOWER(TRIM(RawData[[#This Row],[Lead Status]]))="hot",LOWER(TRIM(RawData[[#This Row],[Lead Status]]))="prospect",LOWER(TRIM(RawData[[#This Row],[Lead Status]]))="warm")),"Contact immediately and set the next follow-up",""),IF(AND(LOWER(TRIM(RawData[[#This Row],[Location]]))="anekal",OR(ISNUMBER(SEARCH("ernika",LOWER(RawData[[#This Row],[Project Name]]))),ISNUMBER(SEARCH("enrika",LOWER(RawData[[#This Row],[Project Name]]))),ISNUMBER(SEARCH("exotica",LOWER(RawData[[#This Row],[Project Name]]))),ISNUMBER(SEARCH(" eka",LOWER(RawData[[#This Row],[Project Name]]))))),"Contact the customer and record their actual location",""))) -> Contact the customer and record their actual location | S3: =IF(RawData[[#This Row],[Error Flag]]=0,"",IF(OR(ISNUMBER(SEARCH("Wrong Lead Status",RawData[[#This Row],[Error Type]])),ISNUMBER(SEARCH("RNR Classification Error",RawData[[#This Row],[Error Type]])),ISNUMBER(SEARCH("Follow-up Error",RawData[[#This Row],[Error Type]]))),"Critical","Medium")) -> Medium | T3: =IF(RawData[[#This Row],[Error Flag]]=0,"Pass","Action Required ("&RawData[[#This Row],[Error Flag]]&IF(RawData[[#This Row],[Error Flag]]=1," error)"," errors)")) -> Action Required (1 error) | U3: =IF(RawData[[#This Row],[Mobile]]="",0,--(AND(OR(LOWER(TRIM(RawData[[#This Row],[Lead Status]]))="cold",LOWER(TRIM(RawData[[#This Row],[Lead Status]]))="lost"),OR(ISNUMBER(SEARCH("visit",LOWER(TRIM(RawData[[#This Row],[Comments]])))),ISNUMBER(SEARCH("brochure",LOWER(TRIM(RawData[[#This Row],[Comments]])))),ISNUMBER(SEARCH("pricing",LOWER(TRIM(RawData[[#This Row],[Comments]])))),ISNUMBER(SEARCH("price",LOWER(TRIM(RawData[[#This Row],[Comments]])))),ISNUMBER(SEARCH("budget",LOWER(TRIM(RawData[[#This Row],[Comments]])))))))+--(AND(LOWER(TRIM(RawData[[#This Row],[Lead Status]]))="cold",OR(LOWER(TRIM(RawData[[#This Row],[Comments]]))="rnr",LOWER(TRIM(RawData[[#This Row],[Comments]]))="busy",LOWER(TRIM(RawData[[#This Row],[Comments]]))="out of network",LOWER(TRIM(RawData[[#This Row],[Comments]]))="outoff network",LOWER(TRIM(RawData[[#This Row],[Comments]]))="voice mail",LOWER(TRIM(RawData[[#This Row],[Comments]]))="voicemail")))+--(AND(LOWER(TRIM(RawData[[#This Row],[Lead Status]]))="warm",OR(LOWER(TRIM(RawData[[#This Row],[Comments]]))="busy",LOWER(TRIM(RawData[[#This Row],[Comments]]))="voice mail",LOWER(TRIM(RawData[[#This Row],[Comments]]))="voicemail",LOWER(TRIM(RawData[[#This Row],[Comments]]))="call back later")))+--(AND(LOWER(TRIM(RawData[[#This Row],[Status]]))="rnr",OR(ISNUMBER(SEARCH("requirement",LOWER(RawData[[#This Row],[Comments]]&" "&RawData[[#This Row],[Customer Requirement]]))),ISNUMBER(SEARCH("budget",LOWER(RawData[[#This Row],[Comments]]&" "&RawData[[#This Row],[Customer Requirement]]))),ISNUMBER(SEARCH("location",LOWER(RawData[[#This Row],[Comments]]&" "&RawData[[#This Row],[Customer Requirement]]))),ISNUMBER(SEARCH("purpose",LOWER(RawData[[#This Row],[Comments]]&" "&RawData[[#This Row],[Customer Requirement]]))),ISNUMBER(SEARCH("dimension",LOWER(RawData[[#This Row],[Comments]]&" "&RawData[[#This Row],[Customer Requirement]]))),ISNUMBER(SEARCH("sqft",LOWER(RawData[[#This Row],[Comments]]&" "&RawData[[#This Row],[Customer Requirement]]))))))+--(AND(ISNUMBER(RawData[[#This Row],[Next Followup Date]]),RawData[[#This Row],[Next Followup Date]]<NOW(),OR(LOWER(TRIM(RawData[[#This Row],[Lead Status]]))="hot",LOWER(TRIM(RawData[[#This Row],[Lead Status]]))="prospect",LOWER(TRIM(RawData[[#This Row],[Lead Status]]))="warm")))+--(AND(LOWER(TRIM(RawData[[#This Row],[Location]]))="anekal",OR(ISNUMBER(SEARCH("ernika",LOWER(RawData[[#This Row],[Project Name]]))),ISNUMBER(SEARCH("enrika",LOWER(RawData[[#This Row],[Project Name]]))),ISNUMBER(SEARCH("exotica",LOWER(RawData[[#This Row],[Project Name]]))),ISNUMBER(SEARCH(" eka",LOWER(RawData[[#This Row],[Project Name]]))))))) -> 1 | W3: ='Telecaller Performance'!A7 -> Vinutha M1 | X3: {=IF(W3="",NA(),_xlfn.LET(_xlpm.v,SUBTOTAL(103,OFFSET(RawData[Mobile],ROW(RawData[Mobile])-MIN(ROW(RawData[Mobile])),0,1)),_xlpm.z,SUMPRODUCT(_xlpm.v,--(RawData[Telecaller Name]=W3)),IF(_xlpm.z=0,NA(),MAX(0,1-SUMPRODUCT(_xlpm.v,--(RawData[Telecaller Name]=W3),RawData[Error Flag])/_xlpm.z))))} -> 0.21428571 | Z3: ='Telecaller Performance'!A7 -> Vinutha M1 | AA3: {=IF(Z3="",NA(),_xlfn.LET(_xlpm.v,SUBTOTAL(103,OFFSET(RawData[Mobile],ROW(RawData[Mobile])-MIN(ROW(RawData[Mobile])),0,1)),_xlpm.z,SUMPRODUCT(_xlpm.v,--(RawData[Telecaller Name]=Z3)),IF(_xlpm.z=0,NA(),SUMPRODUCT(_xlpm.v,--(RawData[Telecaller Name]=Z3),RawData[Error Flag]))))} -> 22 | AC3: Cold Status Mismatch | AD3: {=_xlfn.LET(_xlpm.v,SUBTOTAL(103,OFFSET(RawData[Mobile],ROW(RawData[Mobile])-MIN(ROW(RawData[Mobile])),0,1)),SUMPRODUCT(_xlpm.v,--ISNUMBER(SEARCH(AC3,RawData[Error Type]))))} -> 0 | AF3: {=IFERROR(INDEX(_xlfn._xlws.SORT(_xlfn.UNIQUE(_xlfn._xlws.FILTER(RawData[Project Name],RawData[Project Name]<>""))),ROWS(AF$2:AF3)),"")} -> Guru Punvaanii Elegance | AG3: {=IF(AF3="",NA(),_xlfn.LET(_xlpm.v,SUBTOTAL(103,OFFSET(RawData[Mobile],ROW(RawData[Mobile])-MIN(ROW(RawData[Mobile])),0,1)),_xlpm.z,SUMPRODUCT(_xlpm.v,--(RawData[Project Name]=AF3)),IF(_xlpm.z=0,NA(),SUMPRODUCT(_xlpm.v,--(RawData[Project Name]=AF3),RawData[Error Flag]))))} -> 1 | AI3: Medium | AJ3: {=_xlfn.LET(_xlpm.v,SUBTOTAL(103,OFFSET(RawData[Mobile],ROW(RawData[Mobile])-MIN(ROW(RawData[Mobile])),0,1)),SUMPRODUCT(_xlpm.v,--ISNUMBER(SEARCH("Warm Status Mismatch",RawData[Error Type])))+SUMPRODUCT(_xlpm.v,--ISNUMBER(SEARCH("CRM Status Mismatch",RawData[Error Type])))+SUMPRODUCT(_xlpm.v,--ISNUMBER(SEARCH("Customer Location Not Captured",RawData[Error Type]))))} -> 19
A4: Guru Punvaanii EKA | B4: 9513809427 | C4: Vinutha M1 | D4: 46253 | E4: warm | F4: Rnr | G4: 46256.465 | I4: -1 | J4: Interested | K4: RNR | L4: .. | M4: Digital Marketing | N4: Meta_StaticAds_Aug2026 | O4: 1 | P4: =IF(RawData[[#This Row],[Mobile]]="","",_xlfn.TEXTJOIN(" | ",TRUE,IF(AND(OR(LOWER(TRIM(RawData[[#This Row],[Lead Status]]))="cold",LOWER(TRIM(RawData[[#This Row],[Lead Status]]))="lost"),OR(ISNUMBER(SEARCH("visit",LOWER(TRIM(RawData[[#This Row],[Comments]])))),ISNUMBER(SEARCH("brochure",LOWER(TRIM(RawData[[#This Row],[Comments]])))),ISNUMBER(SEARCH("pricing",LOWER(TRIM(RawData[[#This Row],[Comments]])))),ISNUMBER(SEARCH("price",LOWER(TRIM(RawData[[#This Row],[Comments]])))),ISNUMBER(SEARCH("budget",LOWER(TRIM(RawData[[#This Row],[Comments]])))))),"Wrong Lead Status",""),IF(AND(LOWER(TRIM(RawData[[#This Row],[Lead Status]]))="cold",OR(LOWER(TRIM(RawData[[#This Row],[Comments]]))="rnr",LOWER(TRIM(RawData[[#This Row],[Comments]]))="busy",LOWER(TRIM(RawData[[#This Row],[Comments]]))="out of network",LOWER(TRIM(RawData[[#This Row],[Comments]]))="outoff network",LOWER(TRIM(RawData[[#This Row],[Comments]]))="voice mail",LOWER(TRIM(RawData[[#This Row],[Comments]]))="voicemail")),"RNR Classification Error",""),IF(AND(LOWER(TRIM(RawData[[#This Row],[Lead Status]]))="warm",OR(LOWER(TRIM(RawData[[#This Row],[Comments]]))="busy",LOWER(TRIM(RawData[[#This Row],[Comments]]))="voice mail",LOWER(TRIM(RawData[[#This Row],[Comments]]))="voicemail",LOWER(TRIM(RawData[[#This Row],[Comments]]))="call back later")),"Warm Status Mismatch",""),IF(AND(LOWER(TRIM(RawData[[#This Row],[Status]]))="rnr",OR(ISNUMBER(SEARCH("requirement",LOWER(RawData[[#This Row],[Comments]]&" "&RawData[[#This Row],[Customer Requirement]]))),ISNUMBER(SEARCH("budget",LOWER(RawData[[#This Row],[Comments]]&" "&RawData[[#This Row],[Customer Requirement]]))),ISNUMBER(SEARCH("location",LOWER(RawData[[#This Row],[Comments]]&" "&RawData[[#This Row],[Customer Requirement]]))),ISNUMBER(SEARCH("purpose",LOWER(RawData[[#This Row],[Comments]]&" "&RawData[[#This Row],[Customer Requirement]]))),ISNUMBER(SEARCH("dimension",LOWER(RawData[[#This Row],[Comments]]&" "&RawData[[#This Row],[Customer Requirement]]))),ISNUMBER(SEARCH("sqft",LOWER(RawData[[#This Row],[Comments]]&" "&RawData[[#This Row],[Customer Requirement]]))))),"CRM Status Mismatch",""),IF(AND(ISNUMBER(RawData[[#This Row],[Next Followup Date]]),RawData[[#This Row],[Next Followup Date]]<NOW(),OR(LOWER(TRIM(RawData[[#This Row],[Lead Status]]))="hot",LOWER(TRIM(RawData[[#This Row],[Lead Status]]))="prospect",LOWER(TRIM(RawData[[#This Row],[Lead Status]]))="warm")),"Follow-up Error",""),IF(AND(LOWER(TRIM(RawData[[#This Row],[Location]]))="anekal",OR(ISNUMBER(SEARCH("ernika",LOWER(RawData[[#This Row],[Project Name]]))),ISNUMBER(SEARCH("enrika",LOWER(RawData[[#This Row],[Project Name]]))),ISNUMBER(SEARCH("exotica",LOWER(RawData[[#This Row],[Project Name]]))),ISNUMBER(SEARCH(" eka",LOWER(RawData[[#This Row],[Project Name]]))))),"Customer Location Not Captured",""))) | Q4: =IF(RawData[[#This Row],[Mobile]]="","",_xlfn.TEXTJOIN(CHAR(10),TRUE,IF(AND(OR(LOWER(TRIM(RawData[[#This Row],[Lead Status]]))="cold",LOWER(TRIM(RawData[[#This Row],[Lead Status]]))="lost"),OR(ISNUMBER(SEARCH("visit",LOWER(TRIM(RawData[[#This Row],[Comments]])))),ISNUMBER(SEARCH("brochure",LOWER(TRIM(RawData[[#This Row],[Comments]])))),ISNUMBER(SEARCH("pricing",LOWER(TRIM(RawData[[#This Row],[Comments]])))),ISNUMBER(SEARCH("price",LOWER(TRIM(RawData[[#This Row],[Comments]])))),ISNUMBER(SEARCH("budget",LOWER(TRIM(RawData[[#This Row],[Comments]])))))),"Engagement intent conflicts with Cold/Lost status",""),IF(AND(LOWER(TRIM(RawData[[#This Row],[Lead Status]]))="cold",OR(LOWER(TRIM(RawData[[#This Row],[Comments]]))="rnr",LOWER(TRIM(RawData[[#This Row],[Comments]]))="busy",LOWER(TRIM(RawData[[#This Row],[Comments]]))="out of network",LOWER(TRIM(RawData[[#This Row],[Comments]]))="outoff network",LOWER(TRIM(RawData[[#This Row],[Comments]]))="voice mail",LOWER(TRIM(RawData[[#This Row],[Comments]]))="voicemail")),"Contact outcome should remain RNR rather than Cold",""),IF(AND(LOWER(TRIM(RawData[[#This Row],[Lead Status]]))="warm",OR(LOWER(TRIM(RawData[[#This Row],[Comments]]))="busy",LOWER(TRIM(RawData[[#This Row],[Comments]]))="voice mail",LOWER(TRIM(RawData[[#This Row],[Comments]]))="voicemail",LOWER(TRIM(RawData[[#This Row],[Comments]]))="call back later")),"Contact-only outcome does not support Warm status",""),IF(AND(LOWER(TRIM(RawData[[#This Row],[Status]]))="rnr",OR(ISNUMBER(SEARCH("requirement",LOWER(RawData[[#This Row],[Comments]]&" "&RawData[[#This Row],[Customer Requirement]]))),ISNUMBER(SEARCH("budget",LOWER(RawData[[#This Row],[Comments]]&" "&RawData[[#This Row],[Customer Requirement]]))),ISNUMBER(SEARCH("location",LOWER(RawData[[#This Row],[Comments]]&" "&RawData[[#This Row],[Customer Requirement]]))),ISNUMBER(SEARCH("purpose",LOWER(RawData[[#This Row],[Comments]]&" "&RawData[[#This Row],[Customer Requirement]]))),ISNUMBER(SEARCH("dimension",LOWER(RawData[[#This Row],[Comments]]&" "&RawData[[#This Row],[Customer Requirement]]))),ISNUMBER(SEARCH("sqft",LOWER(RawData[[#This Row],[Comments]]&" "&RawData[[#This Row],[Customer Requirement]]))))),"Requirements were captured while CRM status remains RNR",""),IF(AND(ISNUMBER(RawData[[#This Row],[Next Followup Date]]),RawData[[#This Row],[Next Followup Date]]<NOW(),OR(LOWER(TRIM(RawData[[#This Row],[Lead Status]]))="hot",LOWER(TRIM(RawData[[#This Row],[Lead Status]]))="prospect",LOWER(TRIM(RawData[[#This Row],[Lead Status]]))="warm")),"Follow-up date/time has passed for an active lead",""),IF(AND(LOWER(TRIM(RawData[[#This Row],[Location]]))="anekal",OR(ISNUMBER(SEARCH("ernika",LOWER(RawData[[#This Row],[Project Name]]))),ISNUMBER(SEARCH("enrika",LOWER(RawData[[#This Row],[Project Name]]))),ISNUMBER(SEARCH("exotica",LOWER(RawData[[#This Row],[Project Name]]))),ISNUMBER(SEARCH(" eka",LOWER(RawData[[#This Row],[Project Name]]))))),"Anekal is the project default; customer location was not captured",""))) | R4: =IF(RawData[[#This Row],[Mobile]]="","",_xlfn.TEXTJOIN(CHAR(10),TRUE,IF(AND(OR(LOWER(TRIM(RawData[[#This Row],[Lead Status]]))="cold",LOWER(TRIM(RawData[[#This Row],[Lead Status]]))="lost"),OR(ISNUMBER(SEARCH("visit",LOWER(TRIM(RawData[[#This Row],[Comments]])))),ISNUMBER(SEARCH("brochure",LOWER(TRIM(RawData[[#This Row],[Comments]])))),ISNUMBER(SEARCH("pricing",LOWER(TRIM(RawData[[#This Row],[Comments]])))),ISNUMBER(SEARCH("price",LOWER(TRIM(RawData[[#This Row],[Comments]])))),ISNUMBER(SEARCH("budget",LOWER(TRIM(RawData[[#This Row],[Comments]])))))),"Reclassify lead and schedule a documented follow-up",""),IF(AND(LOWER(TRIM(RawData[[#This Row],[Lead Status]]))="cold",OR(LOWER(TRIM(RawData[[#This Row],[Comments]]))="rnr",LOWER(TRIM(RawData[[#This Row],[Comments]]))="busy",LOWER(TRIM(RawData[[#This Row],[Comments]]))="out of network",LOWER(TRIM(RawData[[#This Row],[Comments]]))="outoff network",LOWER(TRIM(RawData[[#This Row],[Comments]]))="voice mail",LOWER(TRIM(RawData[[#This Row],[Comments]]))="voicemail")),"Change lead classification to RNR and retry contact",""),IF(AND(LOWER(TRIM(RawData[[#This Row],[Lead Status]]))="warm",OR(LOWER(TRIM(RawData[[#This Row],[Comments]]))="busy",LOWER(TRIM(RawData[[#This Row],[Comments]]))="voice mail",LOWER(TRIM(RawData[[#This Row],[Comments]]))="voicemail",LOWER(TRIM(RawData[[#This Row],[Comments]]))="call back later")),"Validate engagement before retaining Warm status",""),IF(AND(LOWER(TRIM(RawData[[#This Row],[Status]]))="rnr",OR(ISNUMBER(SEARCH("requirement",LOWER(RawData[[#This Row],[Comments]]&" "&RawData[[#This Row],[Customer Requirement]]))),ISNUMBER(SEARCH("budget",LOWER(RawData[[#This Row],[Comments]]&" "&RawData[[#This Row],[Customer Requirement]]))),ISNUMBER(SEARCH("location",LOWER(RawData[[#This Row],[Comments]]&" "&RawData[[#This Row],[Customer Requirement]]))),ISNUMBER(SEARCH("purpose",LOWER(RawData[[#This Row],[Comments]]&" "&RawData[[#This Row],[Customer Requirement]]))),ISNUMBER(SEARCH("dimension",LOWER(RawData[[#This Row],[Comments]]&" "&RawData[[#This Row],[Customer Requirement]]))),ISNUMBER(SEARCH("sqft",LOWER(RawData[[#This Row],[Comments]]&" "&RawData[[#This Row],[Customer Requirement]]))))),"Update CRM status to reflect the collected requirement",""),IF(AND(ISNUMBER(RawData[[#This Row],[Next Followup Date]]),RawData[[#This Row],[Next Followup Date]]<NOW(),OR(LOWER(TRIM(RawData[[#This Row],[Lead Status]]))="hot",LOWER(TRIM(RawData[[#This Row],[Lead Status]]))="prospect",LOWER(TRIM(RawData[[#This Row],[Lead Status]]))="warm")),"Contact immediately and set the next follow-up",""),IF(AND(LOWER(TRIM(RawData[[#This Row],[Location]]))="anekal",OR(ISNUMBER(SEARCH("ernika",LOWER(RawData[[#This Row],[Project Name]]))),ISNUMBER(SEARCH("enrika",LOWER(RawData[[#This Row],[Project Name]]))),ISNUMBER(SEARCH("exotica",LOWER(RawData[[#This Row],[Project Name]]))),ISNUMBER(SEARCH(" eka",LOWER(RawData[[#This Row],[Project Name]]))))),"Contact the customer and record their actual location",""))) | S4: =IF(RawData[[#This Row],[Error Flag]]=0,"",IF(OR(ISNUMBER(SEARCH("Wrong Lead Status",RawData[[#This Row],[Error Type]])),ISNUMBER(SEARCH("RNR Classification Error",RawData[[#This Row],[Error Type]])),ISNUMBER(SEARCH("Follow-up Error",RawData[[#This Row],[Error Type]]))),"Critical","Medium")) | T4: =IF(RawData[[#This Row],[Error Flag]]=0,"Pass","Action Required ("&RawData[[#This Row],[Error Flag]]&IF(RawData[[#This Row],[Error Flag]]=1," error)"," errors)")) -> Pass | U4: =IF(RawData[[#This Row],[Mobile]]="",0,--(AND(OR(LOWER(TRIM(RawData[[#This Row],[Lead Status]]))="cold",LOWER(TRIM(RawData[[#This Row],[Lead Status]]))="lost"),OR(ISNUMBER(SEARCH("visit",LOWER(TRIM(RawData[[#This Row],[Comments]])))),ISNUMBER(SEARCH("brochure",LOWER(TRIM(RawData[[#This Row],[Comments]])))),ISNUMBER(SEARCH("pricing",LOWER(TRIM(RawData[[#This Row],[Comments]])))),ISNUMBER(SEARCH("price",LOWER(TRIM(RawData[[#This Row],[Comments]])))),ISNUMBER(SEARCH("budget",LOWER(TRIM(RawData[[#This Row],[Comments]])))))))+--(AND(LOWER(TRIM(RawData[[#This Row],[Lead Status]]))="cold",OR(LOWER(TRIM(RawData[[#This Row],[Comments]]))="rnr",LOWER(TRIM(RawData[[#This Row],[Comments]]))="busy",LOWER(TRIM(RawData[[#This Row],[Comments]]))="out of network",LOWER(TRIM(RawData[[#This Row],[Comments]]))="outoff network",LOWER(TRIM(RawData[[#This Row],[Comments]]))="voice mail",LOWER(TRIM(RawData[[#This Row],[Comments]]))="voicemail")))+--(AND(LOWER(TRIM(RawData[[#This Row],[Lead Status]]))="warm",OR(LOWER(TRIM(RawData[[#This Row],[Comments]]))="busy",LOWER(TRIM(RawData[[#This Row],[Comments]]))="voice mail",LOWER(TRIM(RawData[[#This Row],[Comments]]))="voicemail",LOWER(TRIM(RawData[[#This Row],[Comments]]))="call back later")))+--(AND(LOWER(TRIM(RawData[[#This Row],[Status]]))="rnr",OR(ISNUMBER(SEARCH("requirement",LOWER(RawData[[#This Row],[Comments]]&" "&RawData[[#This Row],[Customer Requirement]]))),ISNUMBER(SEARCH("budget",LOWER(RawData[[#This Row],[Comments]]&" "&RawData[[#This Row],[Customer Requirement]]))),ISNUMBER(SEARCH("location",LOWER(RawData[[#This Row],[Comments]]&" "&RawData[[#This Row],[Customer Requirement]]))),ISNUMBER(SEARCH("purpose",LOWER(RawData[[#This Row],[Comments]]&" "&RawData[[#This Row],[Customer Requirement]]))),ISNUMBER(SEARCH("dimension",LOWER(RawData[[#This Row],[Comments]]&" "&RawData[[#This Row],[Customer Requirement]]))),ISNUMBER(SEARCH("sqft",LOWER(RawData[[#This Row],[Comments]]&" "&RawData[[#This Row],[Customer Requirement]]))))))+--(AND(ISNUMBER(RawData[[#This Row],[Next Followup Date]]),RawData[[#This Row],[Next Followup Date]]<NOW(),OR(LOWER(TRIM(RawData[[#This Row],[Lead Status]]))="hot",LOWER(TRIM(RawData[[#This Row],[Lead Status]]))="prospect",LOWER(TRIM(RawData[[#This Row],[Lead Status]]))="warm")))+--(AND(LOWER(TRIM(RawData[[#This Row],[Location]]))="anekal",OR(ISNUMBER(SEARCH("ernika",LOWER(RawData[[#This Row],[Project Name]]))),ISNUMBER(SEARCH("enrika",LOWER(RawData[[#This Row],[Project Name]]))),ISNUMBER(SEARCH("exotica",LOWER(RawData[[#This Row],[Project Name]]))),ISNUMBER(SEARCH(" eka",LOWER(RawData[[#This Row],[Project Name]]))))))) -> 0 | W4: ='Telecaller Performance'!A8 -> Amulya P | X4: {=IF(W4="",NA(),_xlfn.LET(_xlpm.v,SUBTOTAL(103,OFFSET(RawData[Mobile],ROW(RawData[Mobile])-MIN(ROW(RawData[Mobile])),0,1)),_xlpm.z,SUMPRODUCT(_xlpm.v,--(RawData[Telecaller Name]=W4)),IF(_xlpm.z=0,NA(),MAX(0,1-SUMPRODUCT(_xlpm.v,--(RawData[Telecaller Name]=W4),RawData[Error Flag])/_xlpm.z))))} -> 0.5 | Z4: ='Telecaller Performance'!A8 -> Amulya P | AA4: {=IF(Z4="",NA(),_xlfn.LET(_xlpm.v,SUBTOTAL(103,OFFSET(RawData[Mobile],ROW(RawData[Mobile])-MIN(ROW(RawData[Mobile])),0,1)),_xlpm.z,SUMPRODUCT(_xlpm.v,--(RawData[Telecaller Name]=Z4)),IF(_xlpm.z=0,NA(),SUMPRODUCT(_xlpm.v,--(RawData[Telecaller Name]=Z4),RawData[Error Flag]))))} -> 2 | AC4: Warm Status Mismatch | AD4: {=_xlfn.LET(_xlpm.v,SUBTOTAL(103,OFFSET(RawData[Mobile],ROW(RawData[Mobile])-MIN(ROW(RawData[Mobile])),0,1)),SUMPRODUCT(_xlpm.v,--ISNUMBER(SEARCH(AC4,RawData[Error Type]))))} -> 2 | AF4: {=IFERROR(INDEX(_xlfn._xlws.SORT(_xlfn.UNIQUE(_xlfn._xlws.FILTER(RawData[Project Name],RawData[Project Name]<>""))),ROWS(AF$2:AF4)),"")} -> Guru Punvaanii Ernika | AG4: {=IF(AF4="",NA(),_xlfn.LET(_xlpm.v,SUBTOTAL(103,OFFSET(RawData[Mobile],ROW(RawData[Mobile])-MIN(ROW(RawData[Mobile])),0,1)),_xlpm.z,SUMPRODUCT(_xlpm.v,--(RawData[Project Name]=AF4)),IF(_xlpm.z=0,NA(),SUMPRODUCT(_xlpm.v,--(RawData[Project Name]=AF4),RawData[Error Flag]))))} -> 21 | AI4: Low | AJ4: 0
A5: Guru Punvaanii Elegance | B5: 9972515173 | C5: Amulya P | D5: 46254 | E5: warm | F5: details shared in whastapp (from rajini num) due to network issue did collected any details | G5: 46255.484 | H5: Bheemenahalli | I5: 0 | J5: Interested | K5: In Progress | L5: . | M5: MCube | N5: Instagram Ads | O5: 1 | P5: =IF(RawData[[#This Row],[Mobile]]="","",_xlfn.TEXTJOIN(" | ",TRUE,IF(AND(OR(LOWER(TRIM(RawData[[#This Row],[Lead Status]]))="cold",LOWER(TRIM(RawData[[#This Row],[Lead Status]]))="lost"),OR(ISNUMBER(SEARCH("visit",LOWER(TRIM(RawData[[#This Row],[Comments]])))),ISNUMBER(SEARCH("brochure",LOWER(TRIM(RawData[[#This Row],[Comments]])))),ISNUMBER(SEARCH("pricing",LOWER(TRIM(RawData[[#This Row],[Comments]])))),ISNUMBER(SEARCH("price",LOWER(TRIM(RawData[[#This Row],[Comments]])))),ISNUMBER(SEARCH("budget",LOWER(TRIM(RawData[[#This Row],[Comments]])))))),"Wrong Lead Status",""),IF(AND(LOWER(TRIM(RawData[[#This Row],[Lead Status]]))="cold",OR(LOWER(TRIM(RawData[[#This Row],[Comments]]))="rnr",LOWER(TRIM(RawData[[#This Row],[Comments]]))="busy",LOWER(TRIM(RawData[[#This Row],[Comments]]))="out of network",LOWER(TRIM(RawData[[#This Row],[Comments]]))="outoff network",LOWER(TRIM(RawData[[#This Row],[Comments]]))="voice mail",LOWER(TRIM(RawData[[#This Row],[Comments]]))="voicemail")),"RNR Classification Error",""),IF(AND(LOWER(TRIM(RawData[[#This Row],[Lead Status]]))="warm",OR(LOWER(TRIM(RawData[[#This Row],[Comments]]))="busy",LOWER(TRIM(RawData[[#This Row],[Comments]]))="voice mail",LOWER(TRIM(RawData[[#This Row],[Comments]]))="voicemail",LOWER(TRIM(RawData[[#This Row],[Comments]]))="call back later")),"Warm Status Mismatch",""),IF(AND(LOWER(TRIM(RawData[[#This Row],[Status]]))="rnr",OR(ISNUMBER(SEARCH("requirement",LOWER(RawData[[#This Row],[Comments]]&" "&RawData[[#This Row],[Customer Requirement]]))),ISNUMBER(SEARCH("budget",LOWER(RawData[[#This Row],[Comments]]&" "&RawData[[#This Row],[Customer Requirement]]))),ISNUMBER(SEARCH("location",LOWER(RawData[[#This Row],[Comments]]&" "&RawData[[#This Row],[Customer Requirement]]))),ISNUMBER(SEARCH("purpose",LOWER(RawData[[#This Row],[Comments]]&" "&RawData[[#This Row],[Customer Requirement]]))),ISNUMBER(SEARCH("dimension",LOWER(RawData[[#This Row],[Comments]]&" "&RawData[[#This Row],[Customer Requirement]]))),ISNUMBER(SEARCH("sqft",LOWER(RawData[[#This Row],[Comments]]&" "&RawData[[#This Row],[Customer Requirement]]))))),"CRM Status Mismatch",""),IF(AND(ISNUMBER(RawData[[#This Row],[Next Followup Date]]),RawData[[#This Row],[Next Followup Date]]<NOW(),OR(LOWER(TRIM(RawData[[#This Row],[Lead Status]]))="hot",LOWER(TRIM(RawData[[#This Row],[Lead Status]]))="prospect",LOWER(TRIM(RawData[[#This Row],[Lead Status]]))="warm")),"Follow-up Error",""),IF(AND(LOWER(TRIM(RawData[[#This Row],[Location]]))="anekal",OR(ISNUMBER(SEARCH("ernika",LOWER(RawData[[#This Row],[Project Name]]))),ISNUMBER(SEARCH("enrika",LOWER(RawData[[#This Row],[Project Name]]))),ISNUMBER(SEARCH("exotica",LOWER(RawData[[#This Row],[Project Name]]))),ISNUMBER(SEARCH(" eka",LOWER(RawData[[#This Row],[Project Name]]))))),"Customer Location Not Captured",""))) -> Follow-up Error | Q5: =IF(RawData[[#This Row],[Mobile]]="","",_xlfn.TEXTJOIN(CHAR(10),TRUE,IF(AND(OR(LOWER(TRIM(RawData[[#This Row],[Lead Status]]))="cold",LOWER(TRIM(RawData[[#This Row],[Lead Status]]))="lost"),OR(ISNUMBER(SEARCH("visit",LOWER(TRIM(RawData[[#This Row],[Comments]])))),ISNUMBER(SEARCH("brochure",LOWER(TRIM(RawData[[#This Row],[Comments]])))),ISNUMBER(SEARCH("pricing",LOWER(TRIM(RawData[[#This Row],[Comments]])))),ISNUMBER(SEARCH("price",LOWER(TRIM(RawData[[#This Row],[Comments]])))),ISNUMBER(SEARCH("budget",LOWER(TRIM(RawData[[#This Row],[Comments]])))))),"Engagement intent conflicts with Cold/Lost status",""),IF(AND(LOWER(TRIM(RawData[[#This Row],[Lead Status]]))="cold",OR(LOWER(TRIM(RawData[[#This Row],[Comments]]))="rnr",LOWER(TRIM(RawData[[#This Row],[Comments]]))="busy",LOWER(TRIM(RawData[[#This Row],[Comments]]))="out of network",LOWER(TRIM(RawData[[#This Row],[Comments]]))="outoff network",LOWER(TRIM(RawData[[#This Row],[Comments]]))="voice mail",LOWER(TRIM(RawData[[#This Row],[Comments]]))="voicemail")),"Contact outcome should remain RNR rather than Cold",""),IF(AND(LOWER(TRIM(RawData[[#This Row],[Lead Status]]))="warm",OR(LOWER(TRIM(RawData[[#This Row],[Comments]]))="busy",LOWER(TRIM(RawData[[#This Row],[Comments]]))="voice mail",LOWER(TRIM(RawData[[#This Row],[Comments]]))="voicemail",LOWER(TRIM(RawData[[#This Row],[Comments]]))="call back later")),"Contact-only outcome does not support Warm status",""),IF(AND(LOWER(TRIM(RawData[[#This Row],[Status]]))="rnr",OR(ISNUMBER(SEARCH("requirement",LOWER(RawData[[#This Row],[Comments]]&" "&RawData[[#This Row],[Customer Requirement]]))),ISNUMBER(SEARCH("budget",LOWER(RawData[[#This Row],[Comments]]&" "&RawData[[#This Row],[Customer Requirement]]))),ISNUMBER(SEARCH("location",LOWER(RawData[[#This Row],[Comments]]&" "&RawData[[#This Row],[Customer Requirement]]))),ISNUMBER(SEARCH("purpose",LOWER(RawData[[#This Row],[Comments]]&" "&RawData[[#This Row],[Customer Requirement]]))),ISNUMBER(SEARCH("dimension",LOWER(RawData[[#This Row],[Comments]]&" "&RawData[[#This Row],[Customer Requirement]]))),ISNUMBER(SEARCH("sqft",LOWER(RawData[[#This Row],[Comments]]&" "&RawData[[#This Row],[Customer Requirement]]))))),"Requirements were captured while CRM status remains RNR",""),IF(AND(ISNUMBER(RawData[[#This Row],[Next Followup Date]]),RawData[[#This Row],[Next Followup Date]]<NOW(),OR(LOWER(TRIM(RawData[[#This Row],[Lead Status]]))="hot",LOWER(TRIM(RawData[[#This Row],[Lead Status]]))="prospect",LOWER(TRIM(RawData[[#This Row],[Lead Status]]))="warm")),"Follow-up date/time has passed for an active lead",""),IF(AND(LOWER(TRIM(RawData[[#This Row],[Location]]))="anekal",OR(ISNUMBER(SEARCH("ernika",LOWER(RawData[[#This Row],[Project Name]]))),ISNUMBER(SEARCH("enrika",LOWER(RawData[[#This Row],[Project Name]]))),ISNUMBER(SEARCH("exotica",LOWER(RawData[[#This Row],[Project Name]]))),ISNUMBER(SEARCH(" eka",LOWER(RawData[[#This Row],[Project Name]]))))),"Anekal is the project default; customer location was not captured",""))) -> Follow-up date/time has passed for an active lead | R5: =IF(RawData[[#This Row],[Mobile]]="","",_xlfn.TEXTJOIN(CHAR(10),TRUE,IF(AND(OR(LOWER(TRIM(RawData[[#This Row],[Lead Status]]))="cold",LOWER(TRIM(RawData[[#This Row],[Lead Status]]))="lost"),OR(ISNUMBER(SEARCH("visit",LOWER(TRIM(RawData[[#This Row],[Comments]])))),ISNUMBER(SEARCH("brochure",LOWER(TRIM(RawData[[#This Row],[Comments]])))),ISNUMBER(SEARCH("pricing",LOWER(TRIM(RawData[[#This Row],[Comments]])))),ISNUMBER(SEARCH("price",LOWER(TRIM(RawData[[#This Row],[Comments]])))),ISNUMBER(SEARCH("budget",LOWER(TRIM(RawData[[#This Row],[Comments]])))))),"Reclassify lead and schedule a documented follow-up",""),IF(AND(LOWER(TRIM(RawData[[#This Row],[Lead Status]]))="cold",OR(LOWER(TRIM(RawData[[#This Row],[Comments]]))="rnr",LOWER(TRIM(RawData[[#This Row],[Comments]]))="busy",LOWER(TRIM(RawData[[#This Row],[Comments]]))="out of network",LOWER(TRIM(RawData[[#This Row],[Comments]]))="outoff network",LOWER(TRIM(RawData[[#This Row],[Comments]]))="voice mail",LOWER(TRIM(RawData[[#This Row],[Comments]]))="voicemail")),"Change lead classification to RNR and retry contact",""),IF(AND(LOWER(TRIM(RawData[[#This Row],[Lead Status]]))="warm",OR(LOWER(TRIM(RawData[[#This Row],[Comments]]))="busy",LOWER(TRIM(RawData[[#This Row],[Comments]]))="voice mail",LOWER(TRIM(RawData[[#This Row],[Comments]]))="voicemail",LOWER(TRIM(RawData[[#This Row],[Comments]]))="call back later")),"Validate engagement before retaining Warm status",""),IF(AND(LOWER(TRIM(RawData[[#This Row],[Status]]))="rnr",OR(ISNUMBER(SEARCH("requirement",LOWER(RawData[[#This Row],[Comments]]&" "&RawData[[#This Row],[Customer Requirement]]))),ISNUMBER(SEARCH("budget",LOWER(RawData[[#This Row],[Comments]]&" "&RawData[[#This Row],[Customer Requirement]]))),ISNUMBER(SEARCH("location",LOWER(RawData[[#This Row],[Comments]]&" "&RawData[[#This Row],[Customer Requirement]]))),ISNUMBER(SEARCH("purpose",LOWER(RawData[[#This Row],[Comments]]&" "&RawData[[#This Row],[Customer Requirement]]))),ISNUMBER(SEARCH("dimension",LOWER(RawData[[#This Row],[Comments]]&" "&RawData[[#This Row],[Customer Requirement]]))),ISNUMBER(SEARCH("sqft",LOWER(RawData[[#This Row],[Comments]]&" "&RawData[[#This Row],[Customer Requirement]]))))),"Update CRM status to reflect the collected requirement",""),IF(AND(ISNUMBER(RawData[[#This Row],[Next Followup Date]]),RawData[[#This Row],[Next Followup Date]]<NOW(),OR(LOWER(TRIM(RawData[[#This Row],[Lead Status]]))="hot",LOWER(TRIM(RawData[[#This Row],[Lead Status]]))="prospect",LOWER(TRIM(RawData[[#This Row],[Lead Status]]))="warm")),"Contact immediately and set the next follow-up",""),IF(AND(LOWER(TRIM(RawData[[#This Row],[Location]]))="anekal",OR(ISNUMBER(SEARCH("ernika",LOWER(RawData[[#This Row],[Project Name]]))),ISNUMBER(SEARCH("enrika",LOWER(RawData[[#This Row],[Project Name]]))),ISNUMBER(SEARCH("exotica",LOWER(RawData[[#This Row],[Project Name]]))),ISNUMBER(SEARCH(" eka",LOWER(RawData[[#This Row],[Project Name]]))))),"Contact the customer and record their actual location",""))) -> Contact immediately and set the next follow-up | S5: =IF(RawData[[#This Row],[Error Flag]]=0,"",IF(OR(ISNUMBER(SEARCH("Wrong Lead Status",RawData[[#This Row],[Error Type]])),ISNUMBER(SEARCH("RNR Classification Error",RawData[[#This Row],[Error Type]])),ISNUMBER(SEARCH("Follow-up Error",RawData[[#This Row],[Error Type]]))),"Critical","Medium")) -> Critical | T5: =IF(RawData[[#This Row],[Error Flag]]=0,"Pass","Action Required ("&RawData[[#This Row],[Error Flag]]&IF(RawData[[#This Row],[Error Flag]]=1," error)"," errors)")) -> Action Required (1 error) | U5: =IF(RawData[[#This Row],[Mobile]]="",0,--(AND(OR(LOWER(TRIM(RawData[[#This Row],[Lead Status]]))="cold",LOWER(TRIM(RawData[[#This Row],[Lead Status]]))="lost"),OR(ISNUMBER(SEARCH("visit",LOWER(TRIM(RawData[[#This Row],[Comments]])))),ISNUMBER(SEARCH("brochure",LOWER(TRIM(RawData[[#This Row],[Comments]])))),ISNUMBER(SEARCH("pricing",LOWER(TRIM(RawData[[#This Row],[Comments]])))),ISNUMBER(SEARCH("price",LOWER(TRIM(RawData[[#This Row],[Comments]])))),ISNUMBER(SEARCH("budget",LOWER(TRIM(RawData[[#This Row],[Comments]])))))))+--(AND(LOWER(TRIM(RawData[[#This Row],[Lead Status]]))="cold",OR(LOWER(TRIM(RawData[[#This Row],[Comments]]))="rnr",LOWER(TRIM(RawData[[#This Row],[Comments]]))="busy",LOWER(TRIM(RawData[[#This Row],[Comments]]))="out of network",LOWER(TRIM(RawData[[#This Row],[Comments]]))="outoff network",LOWER(TRIM(RawData[[#This Row],[Comments]]))="voice mail",LOWER(TRIM(RawData[[#This Row],[Comments]]))="voicemail")))+--(AND(LOWER(TRIM(RawData[[#This Row],[Lead Status]]))="warm",OR(LOWER(TRIM(RawData[[#This Row],[Comments]]))="busy",LOWER(TRIM(RawData[[#This Row],[Comments]]))="voice mail",LOWER(TRIM(RawData[[#This Row],[Comments]]))="voicemail",LOWER(TRIM(RawData[[#This Row],[Comments]]))="call back later")))+--(AND(LOWER(TRIM(RawData[[#This Row],[Status]]))="rnr",OR(ISNUMBER(SEARCH("requirement",LOWER(RawData[[#This Row],[Comments]]&" "&RawData[[#This Row],[Customer Requirement]]))),ISNUMBER(SEARCH("budget",LOWER(RawData[[#This Row],[Comments]]&" "&RawData[[#This Row],[Customer Requirement]]))),ISNUMBER(SEARCH("location",LOWER(RawData[[#This Row],[Comments]]&" "&RawData[[#This Row],[Customer Requirement]]))),ISNUMBER(SEARCH("purpose",LOWER(RawData[[#This Row],[Comments]]&" "&RawData[[#This Row],[Customer Requirement]]))),ISNUMBER(SEARCH("dimension",LOWER(RawData[[#This Row],[Comments]]&" "&RawData[[#This Row],[Customer Requirement]]))),ISNUMBER(SEARCH("sqft",LOWER(RawData[[#This Row],[Comments]]&" "&RawData[[#This Row],[Customer Requirement]]))))))+--(AND(ISNUMBER(RawData[[#This Row],[Next Followup Date]]),RawData[[#This Row],[Next Followup Date]]<NOW(),OR(LOWER(TRIM(RawData[[#This Row],[Lead Status]]))="hot",LOWER(TRIM(RawData[[#This Row],[Lead Status]]))="prospect",LOWER(TRIM(RawData[[#This Row],[Lead Status]]))="warm")))+--(AND(LOWER(TRIM(RawData[[#This Row],[Location]]))="anekal",OR(ISNUMBER(SEARCH("ernika",LOWER(RawData[[#This Row],[Project Name]]))),ISNUMBER(SEARCH("enrika",LOWER(RawData[[#This Row],[Project Name]]))),ISNUMBER(SEARCH("exotica",LOWER(RawData[[#This Row],[Project Name]]))),ISNUMBER(SEARCH(" eka",LOWER(RawData[[#This Row],[Project Name]]))))))) -> 1 | W5: ='Telecaller Performance'!A9 -> Manoj Vs 1 | X5: {=IF(W5="",NA(),_xlfn.LET(_xlpm.v,SUBTOTAL(103,OFFSET(RawData[Mobile],ROW(RawData[Mobile])-MIN(ROW(RawData[Mobile])),0,1)),_xlpm.z,SUMPRODUCT(_xlpm.v,--(RawData[Telecaller Name]=W5)),IF(_xlpm.z=0,NA(),MAX(0,1-SUMPRODUCT(_xlpm.v,--(RawData[Telecaller Name]=W5),RawData[Error Flag])/_xlpm.z))))} -> 0 | Z5: ='Telecaller Performance'!A9 -> Manoj Vs 1 | AA5: {=IF(Z5="",NA(),_xlfn.LET(_xlpm.v,SUBTOTAL(103,OFFSET(RawData[Mobile],ROW(RawData[Mobile])-MIN(ROW(RawData[Mobile])),0,1)),_xlpm.z,SUMPRODUCT(_xlpm.v,--(RawData[Telecaller Name]=Z5)),IF(_xlpm.z=0,NA(),SUMPRODUCT(_xlpm.v,--(RawData[Telecaller Name]=Z5),RawData[Error Flag]))))} -> 3 | AC5: RNR Classification Error | AD5: {=_xlfn.LET(_xlpm.v,SUBTOTAL(103,OFFSET(RawData[Mobile],ROW(RawData[Mobile])-MIN(ROW(RawData[Mobile])),0,1)),SUMPRODUCT(_xlpm.v,--ISNUMBER(SEARCH(AC5,RawData[Error Type]))))} -> 3 | AF5: {=IFERROR(INDEX(_xlfn._xlws.SORT(_xlfn.UNIQUE(_xlfn._xlws.FILTER(RawData[Project Name],RawData[Project Name]<>""))),ROWS(AF$2:AF5)),"")} -> Guru Punvaanii Eureka | AG5: {=IF(AF5="",NA(),_xlfn.LET(_xlpm.v,SUBTOTAL(103,OFFSET(RawData[Mobile],ROW(RawData[Mobile])-MIN(ROW(RawData[Mobile])),0,1)),_xlpm.z,SUMPRODUCT(_xlpm.v,--(RawData[Project Name]=AF5)),IF(_xlpm.z=0,NA(),SUMPRODUCT(_xlpm.v,--(RawData[Project Name]=AF5),RawData[Error Flag]))))} -> 1
A6: Guru Punvaanii Ernika | B6: 6361095505 | C6: Vinutha M1 | D6: 46254 | E6: warm | F6: Rnr | G6: 46256.494 | H6: Anekal | I6: -1 | J6: Interested | K6: RNR | L6: .. | M6: Online Portal | N6: 99 Acres | O6: 1 | P6: =IF(RawData[[#This Row],[Mobile]]="","",_xlfn.TEXTJOIN(" | ",TRUE,IF(AND(OR(LOWER(TRIM(RawData[[#This Row],[Lead Status]]))="cold",LOWER(TRIM(RawData[[#This Row],[Lead Status]]))="lost"),OR(ISNUMBER(SEARCH("visit",LOWER(TRIM(RawData[[#This Row],[Comments]])))),ISNUMBER(SEARCH("brochure",LOWER(TRIM(RawData[[#This Row],[Comments]])))),ISNUMBER(SEARCH("pricing",LOWER(TRIM(RawData[[#This Row],[Comments]])))),ISNUMBER(SEARCH("price",LOWER(TRIM(RawData[[#This Row],[Comments]])))),ISNUMBER(SEARCH("budget",LOWER(TRIM(RawData[[#This Row],[Comments]])))))),"Wrong Lead Status",""),IF(AND(LOWER(TRIM(RawData[[#This Row],[Lead Status]]))="cold",OR(LOWER(TRIM(RawData[[#This Row],[Comments]]))="rnr",LOWER(TRIM(RawData[[#This Row],[Comments]]))="busy",LOWER(TRIM(RawData[[#This Row],[Comments]]))="out of network",LOWER(TRIM(RawData[[#This Row],[Comments]]))="outoff network",LOWER(TRIM(RawData[[#This Row],[Comments]]))="voice mail",LOWER(TRIM(RawData[[#This Row],[Comments]]))="voicemail")),"RNR Classification Error",""),IF(AND(LOWER(TRIM(RawData[[#This Row],[Lead Status]]))="warm",OR(LOWER(TRIM(RawData[[#This Row],[Comments]]))="busy",LOWER(TRIM(RawData[[#This Row],[Comments]]))="voice mail",LOWER(TRIM(RawData[[#This Row],[Comments]]))="voicemail",LOWER(TRIM(RawData[[#This Row],[Comments]]))="call back later")),"Warm Status Mismatch",""),IF(AND(LOWER(TRIM(RawData[[#This Row],[Status]]))="rnr",OR(ISNUMBER(SEARCH("requirement",LOWER(RawData[[#This Row],[Comments]]&" "&RawData[[#This Row],[Customer Requirement]]))),ISNUMBER(SEARCH("budget",LOWER(RawData[[#This Row],[Comments]]&" "&RawData[[#This Row],[Customer Requirement]]))),ISNUMBER(SEARCH("location",LOWER(RawData[[#This Row],[Comments]]&" "&RawData[[#This Row],[Customer Requirement]]))),ISNUMBER(SEARCH("purpose",LOWER(RawData[[#This Row],[Comments]]&" "&RawData[[#This Row],[Customer Requirement]]))),ISNUMBER(SEARCH("dimension",LOWER(RawData[[#This Row],[Comments]]&" "&RawData[[#This Row],[Customer Requirement]]))),ISNUMBER(SEARCH("sqft",LOWER(RawData[[#This Row],[Comments]]&" "&RawData[[#This Row],[Customer Requirement]]))))),"CRM Status Mismatch",""),IF(AND(ISNUMBER(RawData[[#This Row],[Next Followup Date]]),RawData[[#This Row],[Next Followup Date]]<NOW(),OR(LOWER(TRIM(RawData[[#This Row],[Lead Status]]))="hot",LOWER(TRIM(RawData[[#This Row],[Lead Status]]))="prospect",LOWER(TRIM(RawData[[#This Row],[Lead Status]]))="warm")),"Follow-up Error",""),IF(AND(LOWER(TRIM(RawData[[#This Row],[Location]]))="anekal",OR(ISNUMBER(SEARCH("ernika",LOWER(RawData[[#This Row],[Project Name]]))),ISNUMBER(SEARCH("enrika",LOWER(RawData[[#This Row],[Project Name]]))),ISNUMBER(SEARCH("exotica",LOWER(RawData[[#This Row],[Project Name]]))),ISNUMBER(SEARCH(" eka",LOWER(RawData[[#This Row],[Project Name]]))))),"Customer Location Not Captured",""))) -> Customer Location Not Captured | Q6: =IF(RawData[[#This Row],[Mobile]]="","",_xlfn.TEXTJOIN(CHAR(10),TRUE,IF(AND(OR(LOWER(TRIM(RawData[[#This Row],[Lead Status]]))="cold",LOWER(TRIM(RawData[[#This Row],[Lead Status]]))="lost"),OR(ISNUMBER(SEARCH("visit",LOWER(TRIM(RawData[[#This Row],[Comments]])))),ISNUMBER(SEARCH("brochure",LOWER(TRIM(RawData[[#This Row],[Comments]])))),ISNUMBER(SEARCH("pricing",LOWER(TRIM(RawData[[#This Row],[Comments]])))),ISNUMBER(SEARCH("price",LOWER(TRIM(RawData[[#This Row],[Comments]])))),ISNUMBER(SEARCH("budget",LOWER(TRIM(RawData[[#This Row],[Comments]])))))),"Engagement intent conflicts with Cold/Lost status",""),IF(AND(LOWER(TRIM(RawData[[#This Row],[Lead Status]]))="cold",OR(LOWER(TRIM(RawData[[#This Row],[Comments]]))="rnr",LOWER(TRIM(RawData[[#This Row],[Comments]]))="busy",LOWER(TRIM(RawData[[#This Row],[Comments]]))="out of network",LOWER(TRIM(RawData[[#This Row],[Comments]]))="outoff network",LOWER(TRIM(RawData[[#This Row],[Comments]]))="voice mail",LOWER(TRIM(RawData[[#This Row],[Comments]]))="voicemail")),"Contact outcome should remain RNR rather than Cold",""),IF(AND(LOWER(TRIM(RawData[[#This Row],[Lead Status]]))="warm",OR(LOWER(TRIM(RawData[[#This Row],[Comments]]))="busy",LOWER(TRIM(RawData[[#This Row],[Comments]]))="voice mail",LOWER(TRIM(RawData[[#This Row],[Comments]]))="voicemail",LOWER(TRIM(RawData[[#This Row],[Comments]]))="call back later")),"Contact-only outcome does not support Warm status",""),IF(AND(LOWER(TRIM(RawData[[#This Row],[Status]]))="rnr",OR(ISNUMBER(SEARCH("requirement",LOWER(RawData[[#This Row],[Comments]]&" "&RawData[[#This Row],[Customer Requirement]]))),ISNUMBER(SEARCH("budget",LOWER(RawData[[#This Row],[Comments]]&" "&RawData[[#This Row],[Customer Requirement]]))),ISNUMBER(SEARCH("location",LOWER(RawData[[#This Row],[Comments]]&" "&RawData[[#This Row],[Customer Requirement]]))),ISNUMBER(SEARCH("purpose",LOWER(RawData[[#This Row],[Comments]]&" "&RawData[[#This Row],[Customer Requirement]]))),ISNUMBER(SEARCH("dimension",LOWER(RawData[[#This Row],[Comments]]&" "&RawData[[#This Row],[Customer Requirement]]))),ISNUMBER(SEARCH("sqft",LOWER(RawData[[#This Row],[Comments]]&" "&RawData[[#This Row],[Customer Requirement]]))))),"Requirements were captured while CRM status remains RNR",""),IF(AND(ISNUMBER(RawData[[#This Row],[Next Followup Date]]),RawData[[#This Row],[Next Followup Date]]<NOW(),OR(LOWER(TRIM(RawData[[#This Row],[Lead Status]]))="hot",LOWER(TRIM(RawData[[#This Row],[Lead Status]]))="prospect",LOWER(TRIM(RawData[[#This Row],[Lead Status]]))="warm")),"Follow-up date/time has passed for an active lead",""),IF(AND(LOWER(TRIM(RawData[[#This Row],[Location]]))="anekal",OR(ISNUMBER(SEARCH("ernika",LOWER(RawData[[#This Row],[Project Name]]))),ISNUMBER(SEARCH("enrika",LOWER(RawData[[#This Row],[Project Name]]))),ISNUMBER(SEARCH("exotica",LOWER(RawData[[#This Row],[Project Name]]))),ISNUMBER(SEARCH(" eka",LOWER(RawData[[#This Row],[Project Name]]))))),"Anekal is the project default; customer location was not captured",""))) -> Anekal is the project default; customer location was not captured | R6: =IF(RawData[[#This Row],[Mobile]]="","",_xlfn.TEXTJOIN(CHAR(10),TRUE,IF(AND(OR(LOWER(TRIM(RawData[[#This Row],[Lead Status]]))="cold",LOWER(TRIM(RawData[[#This Row],[Lead Status]]))="lost"),OR(ISNUMBER(SEARCH("visit",LOWER(TRIM(RawData[[#This Row],[Comments]])))),ISNUMBER(SEARCH("brochure",LOWER(TRIM(RawData[[#This Row],[Comments]])))),ISNUMBER(SEARCH("pricing",LOWER(TRIM(RawData[[#This Row],[Comments]])))),ISNUMBER(SEARCH("price",LOWER(TRIM(RawData[[#This Row],[Comments]])))),ISNUMBER(SEARCH("budget",LOWER(TRIM(RawData[[#This Row],[Comments]])))))),"Reclassify lead and schedule a documented follow-up",""),IF(AND(LOWER(TRIM(RawData[[#This Row],[Lead Status]]))="cold",OR(LOWER(TRIM(RawData[[#This Row],[Comments]]))="rnr",LOWER(TRIM(RawData[[#This Row],[Comments]]))="busy",LOWER(TRIM(RawData[[#This Row],[Comments]]))="out of network",LOWER(TRIM(RawData[[#This Row],[Comments]]))="outoff network",LOWER(TRIM(RawData[[#This Row],[Comments]]))="voice mail",LOWER(TRIM(RawData[[#This Row],[Comments]]))="voicemail")),"Change lead classification to RNR and retry contact",""),IF(AND(LOWER(TRIM(RawData[[#This Row],[Lead Status]]))="warm",OR(LOWER(TRIM(RawData[[#This Row],[Comments]]))="busy",LOWER(TRIM(RawData[[#This Row],[Comments]]))="voice mail",LOWER(TRIM(RawData[[#This Row],[Comments]]))="voicemail",LOWER(TRIM(RawData[[#This Row],[Comments]]))="call back later")),"Validate engagement before retaining Warm status",""),IF(AND(LOWER(TRIM(RawData[[#This Row],[Status]]))="rnr",OR(ISNUMBER(SEARCH("requirement",LOWER(RawData[[#This Row],[Comments]]&" "&RawData[[#This Row],[Customer Requirement]]))),ISNUMBER(SEARCH("budget",LOWER(RawData[[#This Row],[Comments]]&" "&RawData[[#This Row],[Customer Requirement]]))),ISNUMBER(SEARCH("location",LOWER(RawData[[#This Row],[Comments]]&" "&RawData[[#This Row],[Customer Requirement]]))),ISNUMBER(SEARCH("purpose",LOWER(RawData[[#This Row],[Comments]]&" "&RawData[[#This Row],[Customer Requirement]]))),ISNUMBER(SEARCH("dimension",LOWER(RawData[[#This Row],[Comments]]&" "&RawData[[#This Row],[Customer Requirement]]))),ISNUMBER(SEARCH("sqft",LOWER(RawData[[#This Row],[Comments]]&" "&RawData[[#This Row],[Customer Requirement]]))))),"Update CRM status to reflect the collected requirement",""),IF(AND(ISNUMBER(RawData[[#This Row],[Next Followup Date]]),RawData[[#This Row],[Next Followup Date]]<NOW(),OR(LOWER(TRIM(RawData[[#This Row],[Lead Status]]))="hot",LOWER(TRIM(RawData[[#This Row],[Lead Status]]))="prospect",LOWER(TRIM(RawData[[#This Row],[Lead Status]]))="warm")),"Contact immediately and set the next follow-up",""),IF(AND(LOWER(TRIM(RawData[[#This Row],[Location]]))="anekal",OR(ISNUMBER(SEARCH("ernika",LOWER(RawData[[#This Row],[Project Name]]))),ISNUMBER(SEARCH("enrika",LOWER(RawData[[#This Row],[Project Name]]))),ISNUMBER(SEARCH("exotica",LOWER(RawData[[#This Row],[Project Name]]))),ISNUMBER(SEARCH(" eka",LOWER(RawData[[#This Row],[Project Name]]))))),"Contact the customer and record their actual location",""))) -> Contact the customer and record their actual location | S6: =IF(RawData[[#This Row],[Error Flag]]=0,"",IF(OR(ISNUMBER(SEARCH("Wrong Lead Status",RawData[[#This Row],[Error Type]])),ISNUMBER(SEARCH("RNR Classification Error",RawData[[#This Row],[Error Type]])),ISNUMBER(SEARCH("Follow-up Error",RawData[[#This Row],[Error Type]]))),"Critical","Medium")) -> Medium | T6: =IF(RawData[[#This Row],[Error Flag]]=0,"Pass","Action Required ("&RawData[[#This Row],[Error Flag]]&IF(RawData[[#This Row],[Error Flag]]=1," error)"," errors)")) -> Action Required (1 error) | U6: =IF(RawData[[#This Row],[Mobile]]="",0,--(AND(OR(LOWER(TRIM(RawData[[#This Row],[Lead Status]]))="cold",LOWER(TRIM(RawData[[#This Row],[Lead Status]]))="lost"),OR(ISNUMBER(SEARCH("visit",LOWER(TRIM(RawData[[#This Row],[Comments]])))),ISNUMBER(SEARCH("brochure",LOWER(TRIM(RawData[[#This Row],[Comments]])))),ISNUMBER(SEARCH("pricing",LOWER(TRIM(RawData[[#This Row],[Comments]])))),ISNUMBER(SEARCH("price",LOWER(TRIM(RawData[[#This Row],[Comments]])))),ISNUMBER(SEARCH("budget",LOWER(TRIM(RawData[[#This Row],[Comments]])))))))+--(AND(LOWER(TRIM(RawData[[#This Row],[Lead Status]]))="cold",OR(LOWER(TRIM(RawData[[#This Row],[Comments]]))="rnr",LOWER(TRIM(RawData[[#This Row],[Comments]]))="busy",LOWER(TRIM(RawData[[#This Row],[Comments]]))="out of network",LOWER(TRIM(RawData[[#This Row],[Comments]]))="outoff network",LOWER(TRIM(RawData[[#This Row],[Comments]]))="voice mail",LOWER(TRIM(RawData[[#This Row],[Comments]]))="voicemail")))+--(AND(LOWER(TRIM(RawData[[#This Row],[Lead Status]]))="warm",OR(LOWER(TRIM(RawData[[#This Row],[Comments]]))="busy",LOWER(TRIM(RawData[[#This Row],[Comments]]))="voice mail",LOWER(TRIM(RawData[[#This Row],[Comments]]))="voicemail",LOWER(TRIM(RawData[[#This Row],[Comments]]))="call back later")))+--(AND(LOWER(TRIM(RawData[[#This Row],[Status]]))="rnr",OR(ISNUMBER(SEARCH("requirement",LOWER(RawData[[#This Row],[Comments]]&" "&RawData[[#This Row],[Customer Requirement]]))),ISNUMBER(SEARCH("budget",LOWER(RawData[[#This Row],[Comments]]&" "&RawData[[#This Row],[Customer Requirement]]))),ISNUMBER(SEARCH("location",LOWER(RawData[[#This Row],[Comments]]&" "&RawData[[#This Row],[Customer Requirement]]))),ISNUMBER(SEARCH("purpose",LOWER(RawData[[#This Row],[Comments]]&" "&RawData[[#This Row],[Customer Requirement]]))),ISNUMBER(SEARCH("dimension",LOWER(RawData[[#This Row],[Comments]]&" "&RawData[[#This Row],[Customer Requirement]]))),ISNUMBER(SEARCH("sqft",LOWER(RawData[[#This Row],[Comments]]&" "&RawData[[#This Row],[Customer Requirement]]))))))+--(AND(ISNUMBER(RawData[[#This Row],[Next Followup Date]]),RawData[[#This Row],[Next Followup Date]]<NOW(),OR(LOWER(TRIM(RawData[[#This Row],[Lead Status]]))="hot",LOWER(TRIM(RawData[[#This Row],[Lead Status]]))="prospect",LOWER(TRIM(RawData[[#This Row],[Lead Status]]))="warm")))+--(AND(LOWER(TRIM(RawData[[#This Row],[Location]]))="anekal",OR(ISNUMBER(SEARCH("ernika",LOWER(RawData[[#This Row],[Project Name]]))),ISNUMBER(SEARCH("enrika",LOWER(RawData[[#This Row],[Project Name]]))),ISNUMBER(SEARCH("exotica",LOWER(RawData[[#This Row],[Project Name]]))),ISNUMBER(SEARCH(" eka",LOWER(RawData[[#This Row],[Project Name]]))))))) -> 1 | W6: ='Telecaller Performance'!A10 | X6: {=IF(W6="",NA(),_xlfn.LET(_xlpm.v,SUBTOTAL(103,OFFSET(RawData[Mobile],ROW(RawData[Mobile])-MIN(ROW(RawData[Mobile])),0,1)),_xlpm.z,SUMPRODUCT(_xlpm.v,--(RawData[Telecaller Name]=W6)),IF(_xlpm.z=0,NA(),MAX(0,1-SUMPRODUCT(_xlpm.v,--(RawData[Telecaller Name]=W6),RawData[Error Flag])/_xlpm.z))))} -> #N/A | Z6: ='Telecaller Performance'!A10 | AA6: {=IF(Z6="",NA(),_xlfn.LET(_xlpm.v,SUBTOTAL(103,OFFSET(RawData[Mobile],ROW(RawData[Mobile])-MIN(ROW(RawData[Mobile])),0,1)),_xlpm.z,SUMPRODUCT(_xlpm.v,--(RawData[Telecaller Name]=Z6)),IF(_xlpm.z=0,NA(),SUMPRODUCT(_xlpm.v,--(RawData[Telecaller Name]=Z6),RawData[Error Flag]))))} -> #N/A | AC6: Follow-up Error | AD6: {=_xlfn.LET(_xlpm.v,SUBTOTAL(103,OFFSET(RawData[Mobile],ROW(RawData[Mobile])-MIN(ROW(RawData[Mobile])),0,1)),SUMPRODUCT(_xlpm.v,--ISNUMBER(SEARCH(AC6,RawData[Error Type]))))} -> 2 | AF6: {=IFERROR(INDEX(_xlfn._xlws.SORT(_xlfn.UNIQUE(_xlfn._xlws.FILTER(RawData[Project Name],RawData[Project Name]<>""))),ROWS(AF$2:AF6)),"")} -> Guru Punvaanii Shyam Residency | AG6: {=IF(AF6="",NA(),_xlfn.LET(_xlpm.v,SUBTOTAL(103,OFFSET(RawData[Mobile],ROW(RawData[Mobile])-MIN(ROW(RawData[Mobile])),0,1)),_xlpm.z,SUMPRODUCT(_xlpm.v,--(RawData[Project Name]=AF6)),IF(_xlpm.z=0,NA(),SUMPRODUCT(_xlpm.v,--(RawData[Project Name]=AF6),RawData[Error Flag]))))} -> 3
A7: Guru Punvaanii Ernika | B7: 7019359269 | C7: Vinutha M1 | D7: 46253 | E7: warm | F7: Rnr | G7: 46256.427 | H7: Anekal | I7: -1 | J7: Interested | K7: RNR | L7: Rnr | M7: Online Portal | N7: 99 Acres | O7: 1 | P7: =IF(RawData[[#This Row],[Mobile]]="","",_xlfn.TEXTJOIN(" | ",TRUE,IF(AND(OR(LOWER(TRIM(RawData[[#This Row],[Lead Status]]))="cold",LOWER(TRIM(RawData[[#This Row],[Lead Status]]))="lost"),OR(ISNUMBER(SEARCH("visit",LOWER(TRIM(RawData[[#This Row],[Comments]])))),ISNUMBER(SEARCH("brochure",LOWER(TRIM(RawData[[#This Row],[Comments]])))),ISNUMBER(SEARCH("pricing",LOWER(TRIM(RawData[[#This Row],[Comments]])))),ISNUMBER(SEARCH("price",LOWER(TRIM(RawData[[#This Row],[Comments]])))),ISNUMBER(SEARCH("budget",LOWER(TRIM(RawData[[#This Row],[Comments]])))))),"Wrong Lead Status",""),IF(AND(LOWER(TRIM(RawData[[#This Row],[Lead Status]]))="cold",OR(LOWER(TRIM(RawData[[#This Row],[Comments]]))="rnr",LOWER(TRIM(RawData[[#This Row],[Comments]]))="busy",LOWER(TRIM(RawData[[#This Row],[Comments]]))="out of network",LOWER(TRIM(RawData[[#This Row],[Comments]]))="outoff network",LOWER(TRIM(RawData[[#This Row],[Comments]]))="voice mail",LOWER(TRIM(RawData[[#This Row],[Comments]]))="voicemail")),"RNR Classification Error",""),IF(AND(LOWER(TRIM(RawData[[#This Row],[Lead Status]]))="warm",OR(LOWER(TRIM(RawData[[#This Row],[Comments]]))="busy",LOWER(TRIM(RawData[[#This Row],[Comments]]))="voice mail",LOWER(TRIM(RawData[[#This Row],[Comments]]))="voicemail",LOWER(TRIM(RawData[[#This Row],[Comments]]))="call back later")),"Warm Status Mismatch",""),IF(AND(LOWER(TRIM(RawData[[#This Row],[Status]]))="rnr",OR(ISNUMBER(SEARCH("requirement",LOWER(RawData[[#This Row],[Comments]]&" "&RawData[[#This Row],[Customer Requirement]]))),ISNUMBER(SEARCH("budget",LOWER(RawData[[#This Row],[Comments]]&" "&RawData[[#This Row],[Customer Requirement]]))),ISNUMBER(SEARCH("location",LOWER(RawData[[#This Row],[Comments]]&" "&RawData[[#This Row],[Customer Requirement]]))),ISNUMBER(SEARCH("purpose",LOWER(RawData[[#This Row],[Comments]]&" "&RawData[[#This Row],[Customer Requirement]]))),ISNUMBER(SEARCH("dimension",LOWER(RawData[[#This Row],[Comments]]&" "&RawData[[#This Row],[Customer Requirement]]))),ISNUMBER(SEARCH("sqft",LOWER(RawData[[#This Row],[Comments]]&" "&RawData[[#This Row],[Customer Requirement]]))))),"CRM Status Mismatch",""),IF(AND(ISNUMBER(RawData[[#This Row],[Next Followup Date]]),RawData[[#This Row],[Next Followup Date]]<NOW(),OR(LOWER(TRIM(RawData[[#This Row],[Lead Status]]))="hot",LOWER(TRIM(RawData[[#This Row],[Lead Status]]))="prospect",LOWER(TRIM(RawData[[#This Row],[Lead Status]]))="warm")),"Follow-up Error",""),IF(AND(LOWER(TRIM(RawData[[#This Row],[Location]]))="anekal",OR(ISNUMBER(SEARCH("ernika",LOWER(RawData[[#This Row],[Project Name]]))),ISNUMBER(SEARCH("enrika",LOWER(RawData[[#This Row],[Project Name]]))),ISNUMBER(SEARCH("exotica",LOWER(RawData[[#This Row],[Project Name]]))),ISNUMBER(SEARCH(" eka",LOWER(RawData[[#This Row],[Project Name]]))))),"Customer Location Not Captured",""))) -> Customer Location Not Captured | Q7: =IF(RawData[[#This Row],[Mobile]]="","",_xlfn.TEXTJOIN(CHAR(10),TRUE,IF(AND(OR(LOWER(TRIM(RawData[[#This Row],[Lead Status]]))="cold",LOWER(TRIM(RawData[[#This Row],[Lead Status]]))="lost"),OR(ISNUMBER(SEARCH("visit",LOWER(TRIM(RawData[[#This Row],[Comments]])))),ISNUMBER(SEARCH("brochure",LOWER(TRIM(RawData[[#This Row],[Comments]])))),ISNUMBER(SEARCH("pricing",LOWER(TRIM(RawData[[#This Row],[Comments]])))),ISNUMBER(SEARCH("price",LOWER(TRIM(RawData[[#This Row],[Comments]])))),ISNUMBER(SEARCH("budget",LOWER(TRIM(RawData[[#This Row],[Comments]])))))),"Engagement intent conflicts with Cold/Lost status",""),IF(AND(LOWER(TRIM(RawData[[#This Row],[Lead Status]]))="cold",OR(LOWER(TRIM(RawData[[#This Row],[Comments]]))="rnr",LOWER(TRIM(RawData[[#This Row],[Comments]]))="busy",LOWER(TRIM(RawData[[#This Row],[Comments]]))="out of network",LOWER(TRIM(RawData[[#This Row],[Comments]]))="outoff network",LOWER(TRIM(RawData[[#This Row],[Comments]]))="voice mail",LOWER(TRIM(RawData[[#This Row],[Comments]]))="voicemail")),"Contact outcome should remain RNR rather than Cold",""),IF(AND(LOWER(TRIM(RawData[[#This Row],[Lead Status]]))="warm",OR(LOWER(TRIM(RawData[[#This Row],[Comments]]))="busy",LOWER(TRIM(RawData[[#This Row],[Comments]]))="voice mail",LOWER(TRIM(RawData[[#This Row],[Comments]]))="voicemail",LOWER(TRIM(RawData[[#This Row],[Comments]]))="call back later")),"Contact-only outcome does not support Warm status",""),IF(AND(LOWER(TRIM(RawData[[#This Row],[Status]]))="rnr",OR(ISNUMBER(SEARCH("requirement",LOWER(RawData[[#This Row],[Comments]]&" "&RawData[[#This Row],[Customer Requirement]]))),ISNUMBER(SEARCH("budget",LOWER(RawData[[#This Row],[Comments]]&" "&RawData[[#This Row],[Customer Requirement]]))),ISNUMBER(SEARCH("location",LOWER(RawData[[#This Row],[Comments]]&" "&RawData[[#This Row],[Customer Requirement]]))),ISNUMBER(SEARCH("purpose",LOWER(RawData[[#This Row],[Comments]]&" "&RawData[[#This Row],[Customer Requirement]]))),ISNUMBER(SEARCH("dimension",LOWER(RawData[[#This Row],[Comments]]&" "&RawData[[#This Row],[Customer Requirement]]))),ISNUMBER(SEARCH("sqft",LOWER(RawData[[#This Row],[Comments]]&" "&RawData[[#This Row],[Customer Requirement]]))))),"Requirements were captured while CRM status remains RNR",""),IF(AND(ISNUMBER(RawData[[#This Row],[Next Followup Date]]),RawData[[#This Row],[Next Followup Date]]<NOW(),OR(LOWER(TRIM(RawData[[#This Row],[Lead Status]]))="hot",LOWER(TRIM(RawData[[#This Row],[Lead Status]]))="prospect",LOWER(TRIM(RawData[[#This Row],[Lead Status]]))="warm")),"Follow-up date/time has passed for an active lead",""),IF(AND(LOWER(TRIM(RawData[[#This Row],[Location]]))="anekal",OR(ISNUMBER(SEARCH("ernika",LOWER(RawData[[#This Row],[Project Name]]))),ISNUMBER(SEARCH("enrika",LOWER(RawData[[#This Row],[Project Name]]))),ISNUMBER(SEARCH("exotica",LOWER(RawData[[#This Row],[Project Name]]))),ISNUMBER(SEARCH(" eka",LOWER(RawData[[#This Row],[Project Name]]))))),"Anekal is the project default; customer location was not captured",""))) -> Anekal is the project default; customer location was not captured | R7: =IF(RawData[[#This Row],[Mobile]]="","",_xlfn.TEXTJOIN(CHAR(10),TRUE,IF(AND(OR(LOWER(TRIM(RawData[[#This Row],[Lead Status]]))="cold",LOWER(TRIM(RawData[[#This Row],[Lead Status]]))="lost"),OR(ISNUMBER(SEARCH("visit",LOWER(TRIM(RawData[[#This Row],[Comments]])))),ISNUMBER(SEARCH("brochure",LOWER(TRIM(RawData[[#This Row],[Comments]])))),ISNUMBER(SEARCH("pricing",LOWER(TRIM(RawData[[#This Row],[Comments]])))),ISNUMBER(SEARCH("price",LOWER(TRIM(RawData[[#This Row],[Comments]])))),ISNUMBER(SEARCH("budget",LOWER(TRIM(RawData[[#This Row],[Comments]])))))),"Reclassify lead and schedule a documented follow-up",""),IF(AND(LOWER(TRIM(RawData[[#This Row],[Lead Status]]))="cold",OR(LOWER(TRIM(RawData[[#This Row],[Comments]]))="rnr",LOWER(TRIM(RawData[[#This Row],[Comments]]))="busy",LOWER(TRIM(RawData[[#This Row],[Comments]]))="out of network",LOWER(TRIM(RawData[[#This Row],[Comments]]))="outoff network",LOWER(TRIM(RawData[[#This Row],[Comments]]))="voice mail",LOWER(TRIM(RawData[[#This Row],[Comments]]))="voicemail")),"Change lead classification to RNR and retry contact",""),IF(AND(LOWER(TRIM(RawData[[#This Row],[Lead Status]]))="warm",OR(LOWER(TRIM(RawData[[#This Row],[Comments]]))="busy",LOWER(TRIM(RawData[[#This Row],[Comments]]))="voice mail",LOWER(TRIM(RawData[[#This Row],[Comments]]))="voicemail",LOWER(TRIM(RawData[[#This Row],[Comments]]))="call back later")),"Validate engagement before retaining Warm status",""),IF(AND(LOWER(TRIM(RawData[[#This Row],[Status]]))="rnr",OR(ISNUMBER(SEARCH("requirement",LOWER(RawData[[#This Row],[Comments]]&" "&RawData[[#This Row],[Customer Requirement]]))),ISNUMBER(SEARCH("budget",LOWER(RawData[[#This Row],[Comments]]&" "&RawData[[#This Row],[Customer Requirement]]))),ISNUMBER(SEARCH("location",LOWER(RawData[[#This Row],[Comments]]&" "&RawData[[#This Row],[Customer Requirement]]))),ISNUMBER(SEARCH("purpose",LOWER(RawData[[#This Row],[Comments]]&" "&RawData[[#This Row],[Customer Requirement]]))),ISNUMBER(SEARCH("dimension",LOWER(RawData[[#This Row],[Comments]]&" "&RawData[[#This Row],[Customer Requirement]]))),ISNUMBER(SEARCH("sqft",LOWER(RawData[[#This Row],[Comments]]&" "&RawData[[#This Row],[Customer Requirement]]))))),"Update CRM status to reflect the collected requirement",""),IF(AND(ISNUMBER(RawData[[#This Row],[Next Followup Date]]),RawData[[#This Row],[Next Followup Date]]<NOW(),OR(LOWER(TRIM(RawData[[#This Row],[Lead Status]]))="hot",LOWER(TRIM(RawData[[#This Row],[Lead Status]]))="prospect",LOWER(TRIM(RawData[[#This Row],[Lead Status]]))="warm")),"Contact immediately and set the next follow-up",""),IF(AND(LOWER(TRIM(RawData[[#This Row],[Location]]))="anekal",OR(ISNUMBER(SEARCH("ernika",LOWER(RawData[[#This Row],[Project Name]]))),ISNUMBER(SEARCH("enrika",LOWER(RawData[[#This Row],[Project Name]]))),ISNUMBER(SEARCH("exotica",LOWER(RawData[[#This Row],[Project Name]]))),ISNUMBER(SEARCH(" eka",LOWER(RawData[[#This Row],[Project Name]]))))),"Contact the customer and record their actual location",""))) -> Contact the customer and record their actual location | S7: =IF(RawData[[#This Row],[Error Flag]]=0,"",IF(OR(ISNUMBER(SEARCH("Wrong Lead Status",RawData[[#This Row],[Error Type]])),ISNUMBER(SEARCH("RNR Classification Error",RawData[[#This Row],[Error Type]])),ISNUMBER(SEARCH("Follow-up Error",RawData[[#This Row],[Error Type]]))),"Critical","Medium")) -> Medium | T7: =IF(RawData[[#This Row],[Error Flag]]=0,"Pass","Action Required ("&RawData[[#This Row],[Error Flag]]&IF(RawData[[#This Row],[Error Flag]]=1," error)"," errors)")) -> Action Required (1 error) | U7: =IF(RawData[[#This Row],[Mobile]]="",0,--(AND(OR(LOWER(TRIM(RawData[[#This Row],[Lead Status]]))="cold",LOWER(TRIM(RawData[[#This Row],[Lead Status]]))="lost"),OR(ISNUMBER(SEARCH("visit",LOWER(TRIM(RawData[[#This Row],[Comments]])))),ISNUMBER(SEARCH("brochure",LOWER(TRIM(RawData[[#This Row],[Comments]])))),ISNUMBER(SEARCH("pricing",LOWER(TRIM(RawData[[#This Row],[Comments]])))),ISNUMBER(SEARCH("price",LOWER(TRIM(RawData[[#This Row],[Comments]])))),ISNUMBER(SEARCH("budget",LOWER(TRIM(RawData[[#This Row],[Comments]])))))))+--(AND(LOWER(TRIM(RawData[[#This Row],[Lead Status]]))="cold",OR(LOWER(TRIM(RawData[[#This Row],[Comments]]))="rnr",LOWER(TRIM(RawData[[#This Row],[Comments]]))="busy",LOWER(TRIM(RawData[[#This Row],[Comments]]))="out of network",LOWER(TRIM(RawData[[#This Row],[Comments]]))="outoff network",LOWER(TRIM(RawData[[#This Row],[Comments]]))="voice mail",LOWER(TRIM(RawData[[#This Row],[Comments]]))="voicemail")))+--(AND(LOWER(TRIM(RawData[[#This Row],[Lead Status]]))="warm",OR(LOWER(TRIM(RawData[[#This Row],[Comments]]))="busy",LOWER(TRIM(RawData[[#This Row],[Comments]]))="voice mail",LOWER(TRIM(RawData[[#This Row],[Comments]]))="voicemail",LOWER(TRIM(RawData[[#This Row],[Comments]]))="call back later")))+--(AND(LOWER(TRIM(RawData[[#This Row],[Status]]))="rnr",OR(ISNUMBER(SEARCH("requirement",LOWER(RawData[[#This Row],[Comments]]&" "&RawData[[#This Row],[Customer Requirement]]))),ISNUMBER(SEARCH("budget",LOWER(RawData[[#This Row],[Comments]]&" "&RawData[[#This Row],[Customer Requirement]]))),ISNUMBER(SEARCH("location",LOWER(RawData[[#This Row],[Comments]]&" "&RawData[[#This Row],[Customer Requirement]]))),ISNUMBER(SEARCH("purpose",LOWER(RawData[[#This Row],[Comments]]&" "&RawData[[#This Row],[Customer Requirement]]))),ISNUMBER(SEARCH("dimension",LOWER(RawData[[#This Row],[Comments]]&" "&RawData[[#This Row],[Customer Requirement]]))),ISNUMBER(SEARCH("sqft",LOWER(RawData[[#This Row],[Comments]]&" "&RawData[[#This Row],[Customer Requirement]]))))))+--(AND(ISNUMBER(RawData[[#This Row],[Next Followup Date]]),RawData[[#This Row],[Next Followup Date]]<NOW(),OR(LOWER(TRIM(RawData[[#This Row],[Lead Status]]))="hot",LOWER(TRIM(RawData[[#This Row],[Lead Status]]))="prospect",LOWER(TRIM(RawData[[#This Row],[Lead Status]]))="warm")))+--(AND(LOWER(TRIM(RawData[[#This Row],[Location]]))="anekal",OR(ISNUMBER(SEARCH("ernika",LOWER(RawData[[#This Row],[Project Name]]))),ISNUMBER(SEARCH("enrika",LOWER(RawData[[#This Row],[Project Name]]))),ISNUMBER(SEARCH("exotica",LOWER(RawData[[#This Row],[Project Name]]))),ISNUMBER(SEARCH(" eka",LOWER(RawData[[#This Row],[Project Name]]))))))) -> 1 | W7: ='Telecaller Performance'!A11 | X7: {=IF(W7="",NA(),_xlfn.LET(_xlpm.v,SUBTOTAL(103,OFFSET(RawData[Mobile],ROW(RawData[Mobile])-MIN(ROW(RawData[Mobile])),0,1)),_xlpm.z,SUMPRODUCT(_xlpm.v,--(RawData[Telecaller Name]=W7)),IF(_xlpm.z=0,NA(),MAX(0,1-SUMPRODUCT(_xlpm.v,--(RawData[Telecaller Name]=W7),RawData[Error Flag])/_xlpm.z))))} -> #N/A | Z7: ='Telecaller Performance'!A11 | AA7: {=IF(Z7="",NA(),_xlfn.LET(_xlpm.v,SUBTOTAL(103,OFFSET(RawData[Mobile],ROW(RawData[Mobile])-MIN(ROW(RawData[Mobile])),0,1)),_xlpm.z,SUMPRODUCT(_xlpm.v,--(RawData[Telecaller Name]=Z7)),IF(_xlpm.z=0,NA(),SUMPRODUCT(_xlpm.v,--(RawData[Telecaller Name]=Z7),RawData[Error Flag]))))} -> #N/A | AC7: CRM Status Mismatch | AD7: {=_xlfn.LET(_xlpm.v,SUBTOTAL(103,OFFSET(RawData[Mobile],ROW(RawData[Mobile])-MIN(ROW(RawData[Mobile])),0,1)),SUMPRODUCT(_xlpm.v,--ISNUMBER(SEARCH(AC7,RawData[Error Type]))))} -> 0 | AF7: {=IFERROR(INDEX(_xlfn._xlws.SORT(_xlfn.UNIQUE(_xlfn._xlws.FILTER(RawData[Project Name],RawData[Project Name]<>""))),ROWS(AF$2:AF7)),"")} | AG7: {=IF(AF7="",NA(),_xlfn.LET(_xlpm.v,SUBTOTAL(103,OFFSET(RawData[Mobile],ROW(RawData[Mobile])-MIN(ROW(RawData[Mobile])),0,1)),_xlpm.z,SUMPRODUCT(_xlpm.v,--(RawData[Project Name]=AF7)),IF(_xlpm.z=0,NA(),SUMPRODUCT(_xlpm.v,--(RawData[Project Name]=AF7),RawData[Error Flag]))))} -> #N/A
A8: Guru Punvaanii Ernika | B8: 7406119929 | C8: Vinutha M1 | D8: 46253 | E8: warm | F8: Said me to share details and price in whatsapp they will see and tell us | G8: 46256.435 | H8: Anekal | I8: -1 | J8: Interested | K8: In Progress | L8: .. | M8: Online Portal | N8: 99 Acres | O8: 1 | P8: =IF(RawData[[#This Row],[Mobile]]="","",_xlfn.TEXTJOIN(" | ",TRUE,IF(AND(OR(LOWER(TRIM(RawData[[#This Row],[Lead Status]]))="cold",LOWER(TRIM(RawData[[#This Row],[Lead Status]]))="lost"),OR(ISNUMBER(SEARCH("visit",LOWER(TRIM(RawData[[#This Row],[Comments]])))),ISNUMBER(SEARCH("brochure",LOWER(TRIM(RawData[[#This Row],[Comments]])))),ISNUMBER(SEARCH("pricing",LOWER(TRIM(RawData[[#This Row],[Comments]])))),ISNUMBER(SEARCH("price",LOWER(TRIM(RawData[[#This Row],[Comments]])))),ISNUMBER(SEARCH("budget",LOWER(TRIM(RawData[[#This Row],[Comments]])))))),"Wrong Lead Status",""),IF(AND(LOWER(TRIM(RawData[[#This Row],[Lead Status]]))="cold",OR(LOWER(TRIM(RawData[[#This Row],[Comments]]))="rnr",LOWER(TRIM(RawData[[#This Row],[Comments]]))="busy",LOWER(TRIM(RawData[[#This Row],[Comments]]))="out of network",LOWER(TRIM(RawData[[#This Row],[Comments]]))="outoff network",LOWER(TRIM(RawData[[#This Row],[Comments]]))="voice mail",LOWER(TRIM(RawData[[#This Row],[Comments]]))="voicemail")),"RNR Classification Error",""),IF(AND(LOWER(TRIM(RawData[[#This Row],[Lead Status]]))="warm",OR(LOWER(TRIM(RawData[[#This Row],[Comments]]))="busy",LOWER(TRIM(RawData[[#This Row],[Comments]]))="voice mail",LOWER(TRIM(RawData[[#This Row],[Comments]]))="voicemail",LOWER(TRIM(RawData[[#This Row],[Comments]]))="call back later")),"Warm Status Mismatch",""),IF(AND(LOWER(TRIM(RawData[[#This Row],[Status]]))="rnr",OR(ISNUMBER(SEARCH("requirement",LOWER(RawData[[#This Row],[Comments]]&" "&RawData[[#This Row],[Customer Requirement]]))),ISNUMBER(SEARCH("budget",LOWER(RawData[[#This Row],[Comments]]&" "&RawData[[#This Row],[Customer Requirement]]))),ISNUMBER(SEARCH("location",LOWER(RawData[[#This Row],[Comments]]&" "&RawData[[#This Row],[Customer Requirement]]))),ISNUMBER(SEARCH("purpose",LOWER(RawData[[#This Row],[Comments]]&" "&RawData[[#This Row],[Customer Requirement]]))),ISNUMBER(SEARCH("dimension",LOWER(RawData[[#This Row],[Comments]]&" "&RawData[[#This Row],[Customer Requirement]]))),ISNUMBER(SEARCH("sqft",LOWER(RawData[[#This Row],[Comments]]&" "&RawData[[#This Row],[Customer Requirement]]))))),"CRM Status Mismatch",""),IF(AND(ISNUMBER(RawData[[#This Row],[Next Followup Date]]),RawData[[#This Row],[Next Followup Date]]<NOW(),OR(LOWER(TRIM(RawData[[#This Row],[Lead Status]]))="hot",LOWER(TRIM(RawData[[#This Row],[Lead Status]]))="prospect",LOWER(TRIM(RawData[[#This Row],[Lead Status]]))="warm")),"Follow-up Error",""),IF(AND(LOWER(TRIM(RawData[[#This Row],[Location]]))="anekal",OR(ISNUMBER(SEARCH("ernika",LOWER(RawData[[#This Row],[Project Name]]))),ISNUMBER(SEARCH("enrika",LOWER(RawData[[#This Row],[Project Name]]))),ISNUMBER(SEARCH("exotica",LOWER(RawData[[#This Row],[Project Name]]))),ISNUMBER(SEARCH(" eka",LOWER(RawData[[#This Row],[Project Name]]))))),"Customer Location Not Captured",""))) -> Customer Location Not Captured | Q8: =IF(RawData[[#This Row],[Mobile]]="","",_xlfn.TEXTJOIN(CHAR(10),TRUE,IF(AND(OR(LOWER(TRIM(RawData[[#This Row],[Lead Status]]))="cold",LOWER(TRIM(RawData[[#This Row],[Lead Status]]))="lost"),OR(ISNUMBER(SEARCH("visit",LOWER(TRIM(RawData[[#This Row],[Comments]])))),ISNUMBER(SEARCH("brochure",LOWER(TRIM(RawData[[#This Row],[Comments]])))),ISNUMBER(SEARCH("pricing",LOWER(TRIM(RawData[[#This Row],[Comments]])))),ISNUMBER(SEARCH("price",LOWER(TRIM(RawData[[#This Row],[Comments]])))),ISNUMBER(SEARCH("budget",LOWER(TRIM(RawData[[#This Row],[Comments]])))))),"Engagement intent conflicts with Cold/Lost status",""),IF(AND(LOWER(TRIM(RawData[[#This Row],[Lead Status]]))="cold",OR(LOWER(TRIM(RawData[[#This Row],[Comments]]))="rnr",LOWER(TRIM(RawData[[#This Row],[Comments]]))="busy",LOWER(TRIM(RawData[[#This Row],[Comments]]))="out of network",LOWER(TRIM(RawData[[#This Row],[Comments]]))="outoff network",LOWER(TRIM(RawData[[#This Row],[Comments]]))="voice mail",LOWER(TRIM(RawData[[#This Row],[Comments]]))="voicemail")),"Contact outcome should remain RNR rather than Cold",""),IF(AND(LOWER(TRIM(RawData[[#This Row],[Lead Status]]))="warm",OR(LOWER(TRIM(RawData[[#This Row],[Comments]]))="busy",LOWER(TRIM(RawData[[#This Row],[Comments]]))="voice mail",LOWER(TRIM(RawData[[#This Row],[Comments]]))="voicemail",LOWER(TRIM(RawData[[#This Row],[Comments]]))="call back later")),"Contact-only outcome does not support Warm status",""),IF(AND(LOWER(TRIM(RawData[[#This Row],[Status]]))="rnr",OR(ISNUMBER(SEARCH("requirement",LOWER(RawData[[#This Row],[Comments]]&" "&RawData[[#This Row],[Customer Requirement]]))),ISNUMBER(SEARCH("budget",LOWER(RawData[[#This Row],[Comments]]&" "&RawData[[#This Row],[Customer Requirement]]))),ISNUMBER(SEARCH("location",LOWER(RawData[[#This Row],[Comments]]&" "&RawData[[#This Row],[Customer Requirement]]))),ISNUMBER(SEARCH("purpose",LOWER(RawData[[#This Row],[Comments]]&" "&RawData[[#This Row],[Customer Requirement]]))),ISNUMBER(SEARCH("dimension",LOWER(RawData[[#This Row],[Comments]]&" "&RawData[[#This Row],[Customer Requirement]]))),ISNUMBER(SEARCH("sqft",LOWER(RawData[[#This Row],[Comments]]&" "&RawData[[#This Row],[Customer Requirement]]))))),"Requirements were captured while CRM status remains RNR",""),IF(AND(ISNUMBER(RawData[[#This Row],[Next Followup Date]]),RawData[[#This Row],[Next Followup Date]]<NOW(),OR(LOWER(TRIM(RawData[[#This Row],[Lead Status]]))="hot",LOWER(TRIM(RawData[[#This Row],[Lead Status]]))="prospect",LOWER(TRIM(RawData[[#This Row],[Lead Status]]))="warm")),"Follow-up date/time has passed for an active lead",""),IF(AND(LOWER(TRIM(RawData[[#This Row],[Location]]))="anekal",OR(ISNUMBER(SEARCH("ernika",LOWER(RawData[[#This Row],[Project Name]]))),ISNUMBER(SEARCH("enrika",LOWER(RawData[[#This Row],[Project Name]]))),ISNUMBER(SEARCH("exotica",LOWER(RawData[[#This Row],[Project Name]]))),ISNUMBER(SEARCH(" eka",LOWER(RawData[[#This Row],[Project Name]]))))),"Anekal is the project default; customer location was not captured",""))) -> Anekal is the project default; customer location was not captured | R8: =IF(RawData[[#This Row],[Mobile]]="","",_xlfn.TEXTJOIN(CHAR(10),TRUE,IF(AND(OR(LOWER(TRIM(RawData[[#This Row],[Lead Status]]))="cold",LOWER(TRIM(RawData[[#This Row],[Lead Status]]))="lost"),OR(ISNUMBER(SEARCH("visit",LOWER(TRIM(RawData[[#This Row],[Comments]])))),ISNUMBER(SEARCH("brochure",LOWER(TRIM(RawData[[#This Row],[Comments]])))),ISNUMBER(SEARCH("pricing",LOWER(TRIM(RawData[[#This Row],[Comments]])))),ISNUMBER(SEARCH("price",LOWER(TRIM(RawData[[#This Row],[Comments]])))),ISNUMBER(SEARCH("budget",LOWER(TRIM(RawData[[#This Row],[Comments]])))))),"Reclassify lead and schedule a documented follow-up",""),IF(AND(LOWER(TRIM(RawData[[#This Row],[Lead Status]]))="cold",OR(LOWER(TRIM(RawData[[#This Row],[Comments]]))="rnr",LOWER(TRIM(RawData[[#This Row],[Comments]]))="busy",LOWER(TRIM(RawData[[#This Row],[Comments]]))="out of network",LOWER(TRIM(RawData[[#This Row],[Comments]]))="outoff network",LOWER(TRIM(RawData[[#This Row],[Comments]]))="voice mail",LOWER(TRIM(RawData[[#This Row],[Comments]]))="voicemail")),"Change lead classification to RNR and retry contact",""),IF(AND(LOWER(TRIM(RawData[[#This Row],[Lead Status]]))="warm",OR(LOWER(TRIM(RawData[[#This Row],[Comments]]))="busy",LOWER(TRIM(RawData[[#This Row],[Comments]]))="voice mail",LOWER(TRIM(RawData[[#This Row],[Comments]]))="voicemail",LOWER(TRIM(RawData[[#This Row],[Comments]]))="call back later")),"Validate engagement before retaining Warm status",""),IF(AND(LOWER(TRIM(RawData[[#This Row],[Status]]))="rnr",OR(ISNUMBER(SEARCH("requirement",LOWER(RawData[[#This Row],[Comments]]&" "&RawData[[#This Row],[Customer Requirement]]))),ISNUMBER(SEARCH("budget",LOWER(RawData[[#This Row],[Comments]]&" "&RawData[[#This Row],[Customer Requirement]]))),ISNUMBER(SEARCH("location",LOWER(RawData[[#This Row],[Comments]]&" "&RawData[[#This Row],[Customer Requirement]]))),ISNUMBER(SEARCH("purpose",LOWER(RawData[[#This Row],[Comments]]&" "&RawData[[#This Row],[Customer Requirement]]))),ISNUMBER(SEARCH("dimension",LOWER(RawData[[#This Row],[Comments]]&" "&RawData[[#This Row],[Customer Requirement]]))),ISNUMBER(SEARCH("sqft",LOWER(RawData[[#This Row],[Comments]]&" "&RawData[[#This Row],[Customer Requirement]]))))),"Update CRM status to reflect the collected requirement",""),IF(AND(ISNUMBER(RawData[[#This Row],[Next Followup Date]]),RawData[[#This Row],[Next Followup Date]]<NOW(),OR(LOWER(TRIM(RawData[[#This Row],[Lead Status]]))="hot",LOWER(TRIM(RawData[[#This Row],[Lead Status]]))="prospect",LOWER(TRIM(RawData[[#This Row],[Lead Status]]))="warm")),"Contact immediately and set the next follow-up",""),IF(AND(LOWER(TRIM(RawData[[#This Row],[Location]]))="anekal",OR(ISNUMBER(SEARCH("ernika",LOWER(RawData[[#This Row],[Project Name]]))),ISNUMBER(SEARCH("enrika",LOWER(RawData[[#This Row],[Project Name]]))),ISNUMBER(SEARCH("exotica",LOWER(RawData[[#This Row],[Project Name]]))),ISNUMBER(SEARCH(" eka",LOWER(RawData[[#This Row],[Project Name]]))))),"Contact the customer and record their actual location",""))) -> Contact the customer and record their actual location | S8: =IF(RawData[[#This Row],[Error Flag]]=0,"",IF(OR(ISNUMBER(SEARCH("Wrong Lead Status",RawData[[#This Row],[Error Type]])),ISNUMBER(SEARCH("RNR Classification Error",RawData[[#This Row],[Error Type]])),ISNUMBER(SEARCH("Follow-up Error",RawData[[#This Row],[Error Type]]))),"Critical","Medium")) -> Medium | T8: =IF(RawData[[#This Row],[Error Flag]]=0,"Pass","Action Required ("&RawData[[#This Row],[Error Flag]]&IF(RawData[[#This Row],[Error Flag]]=1," error)"," errors)")) -> Action Required (1 error) | U8: =IF(RawData[[#This Row],[Mobile]]="",0,--(AND(OR(LOWER(TRIM(RawData[[#This Row],[Lead Status]]))="cold",LOWER(TRIM(RawData[[#This Row],[Lead Status]]))="lost"),OR(ISNUMBER(SEARCH("visit",LOWER(TRIM(RawData[[#This Row],[Comments]])))),ISNUMBER(SEARCH("brochure",LOWER(TRIM(RawData[[#This Row],[Comments]])))),ISNUMBER(SEARCH("pricing",LOWER(TRIM(RawData[[#This Row],[Comments]])))),ISNUMBER(SEARCH("price",LOWER(TRIM(RawData[[#This Row],[Comments]])))),ISNUMBER(SEARCH("budget",LOWER(TRIM(RawData[[#This Row],[Comments]])))))))+--(AND(LOWER(TRIM(RawData[[#This Row],[Lead Status]]))="cold",OR(LOWER(TRIM(RawData[[#This Row],[Comments]]))="rnr",LOWER(TRIM(RawData[[#This Row],[Comments]]))="busy",LOWER(TRIM(RawData[[#This Row],[Comments]]))="out of network",LOWER(TRIM(RawData[[#This Row],[Comments]]))="outoff network",LOWER(TRIM(RawData[[#This Row],[Comments]]))="voice mail",LOWER(TRIM(RawData[[#This Row],[Comments]]))="voicemail")))+--(AND(LOWER(TRIM(RawData[[#This Row],[Lead Status]]))="warm",OR(LOWER(TRIM(RawData[[#This Row],[Comments]]))="busy",LOWER(TRIM(RawData[[#This Row],[Comments]]))="voice mail",LOWER(TRIM(RawData[[#This Row],[Comments]]))="voicemail",LOWER(TRIM(RawData[[#This Row],[Comments]]))="call back later")))+--(AND(LOWER(TRIM(RawData[[#This Row],[Status]]))="rnr",OR(ISNUMBER(SEARCH("requirement",LOWER(RawData[[#This Row],[Comments]]&" "&RawData[[#This Row],[Customer Requirement]]))),ISNUMBER(SEARCH("budget",LOWER(RawData[[#This Row],[Comments]]&" "&RawData[[#This Row],[Customer Requirement]]))),ISNUMBER(SEARCH("location",LOWER(RawData[[#This Row],[Comments]]&" "&RawData[[#This Row],[Customer Requirement]]))),ISNUMBER(SEARCH("purpose",LOWER(RawData[[#This Row],[Comments]]&" "&RawData[[#This Row],[Customer Requirement]]))),ISNUMBER(SEARCH("dimension",LOWER(RawData[[#This Row],[Comments]]&" "&RawData[[#This Row],[Customer Requirement]]))),ISNUMBER(SEARCH("sqft",LOWER(RawData[[#This Row],[Comments]]&" "&RawData[[#This Row],[Customer Requirement]]))))))+--(AND(ISNUMBER(RawData[[#This Row],[Next Followup Date]]),RawData[[#This Row],[Next Followup Date]]<NOW(),OR(LOWER(TRIM(RawData[[#This Row],[Lead Status]]))="hot",LOWER(TRIM(RawData[[#This Row],[Lead Status]]))="prospect",LOWER(TRIM(RawData[[#This Row],[Lead Status]]))="warm")))+--(AND(LOWER(TRIM(RawData[[#This Row],[Location]]))="anekal",OR(ISNUMBER(SEARCH("ernika",LOWER(RawData[[#This Row],[Project Name]]))),ISNUMBER(SEARCH("enrika",LOWER(RawData[[#This Row],[Project Name]]))),ISNUMBER(SEARCH("exotica",LOWER(RawData[[#This Row],[Project Name]]))),ISNUMBER(SEARCH(" eka",LOWER(RawData[[#This Row],[Project Name]]))))))) -> 1 | W8: ='Telecaller Performance'!A12 | X8: {=IF(W8="",NA(),_xlfn.LET(_xlpm.v,SUBTOTAL(103,OFFSET(RawData[Mobile],ROW(RawData[Mobile])-MIN(ROW(RawData[Mobile])),0,1)),_xlpm.z,SUMPRODUCT(_xlpm.v,--(RawData[Telecaller Name]=W8)),IF(_xlpm.z=0,NA(),MAX(0,1-SUMPRODUCT(_xlpm.v,--(RawData[Telecaller Name]=W8),RawData[Error Flag])/_xlpm.z))))} -> #N/A | Z8: ='Telecaller Performance'!A12 | AA8: {=IF(Z8="",NA(),_xlfn.LET(_xlpm.v,SUBTOTAL(103,OFFSET(RawData[Mobile],ROW(RawData[Mobile])-MIN(ROW(RawData[Mobile])),0,1)),_xlpm.z,SUMPRODUCT(_xlpm.v,--(RawData[Telecaller Name]=Z8)),IF(_xlpm.z=0,NA(),SUMPRODUCT(_xlpm.v,--(RawData[Telecaller Name]=Z8),RawData[Error Flag]))))} -> #N/A | AC8: Customer Location Not Captured | AD8: {=_xlfn.LET(_xlpm.v,SUBTOTAL(103,OFFSET(RawData[Mobile],ROW(RawData[Mobile])-MIN(ROW(RawData[Mobile])),0,1)),SUMPRODUCT(_xlpm.v,--ISNUMBER(SEARCH(AC8,RawData[Error Type]))))} -> 17 | AF8: {=IFERROR(INDEX(_xlfn._xlws.SORT(_xlfn.UNIQUE(_xlfn._xlws.FILTER(RawData[Project Name],RawData[Project Name]<>""))),ROWS(AF$2:AF8)),"")} | AG8: {=IF(AF8="",NA(),_xlfn.LET(_xlpm.v,SUBTOTAL(103,OFFSET(RawData[Mobile],ROW(RawData[Mobile])-MIN(ROW(RawData[Mobile])),0,1)),_xlpm.z,SUMPRODUCT(_xlpm.v,--(RawData[Project Name]=AF8)),IF(_xlpm.z=0,NA(),SUMPRODUCT(_xlpm.v,--(RawData[Project Name]=AF8),RawData[Error Flag]))))} -> #N/A
A9: Guru Punvaanii Ernika | B9: 7795505658 | C9: Vinutha M1 | D9: 46253 | E9: warm | F9: Rnr | G9: 46256.469 | H9: Anekal | I9: -1 | J9: Interested | K9: In Progress | L9: dint disclose , need to take it next call | M9: Online Portal | N9: 99 Acres | O9: 1 | P9: =IF(RawData[[#This Row],[Mobile]]="","",_xlfn.TEXTJOIN(" | ",TRUE,IF(AND(OR(LOWER(TRIM(RawData[[#This Row],[Lead Status]]))="cold",LOWER(TRIM(RawData[[#This Row],[Lead Status]]))="lost"),OR(ISNUMBER(SEARCH("visit",LOWER(TRIM(RawData[[#This Row],[Comments]])))),ISNUMBER(SEARCH("brochure",LOWER(TRIM(RawData[[#This Row],[Comments]])))),ISNUMBER(SEARCH("pricing",LOWER(TRIM(RawData[[#This Row],[Comments]])))),ISNUMBER(SEARCH("price",LOWER(TRIM(RawData[[#This Row],[Comments]])))),ISNUMBER(SEARCH("budget",LOWER(TRIM(RawData[[#This Row],[Comments]])))))),"Wrong Lead Status",""),IF(AND(LOWER(TRIM(RawData[[#This Row],[Lead Status]]))="cold",OR(LOWER(TRIM(RawData[[#This Row],[Comments]]))="rnr",LOWER(TRIM(RawData[[#This Row],[Comments]]))="busy",LOWER(TRIM(RawData[[#This Row],[Comments]]))="out of network",LOWER(TRIM(RawData[[#This Row],[Comments]]))="outoff network",LOWER(TRIM(RawData[[#This Row],[Comments]]))="voice mail",LOWER(TRIM(RawData[[#This Row],[Comments]]))="voicemail")),"RNR Classification Error",""),IF(AND(LOWER(TRIM(RawData[[#This Row],[Lead Status]]))="warm",OR(LOWER(TRIM(RawData[[#This Row],[Comments]]))="busy",LOWER(TRIM(RawData[[#This Row],[Comments]]))="voice mail",LOWER(TRIM(RawData[[#This Row],[Comments]]))="voicemail",LOWER(TRIM(RawData[[#This Row],[Comments]]))="call back later")),"Warm Status Mismatch",""),IF(AND(LOWER(TRIM(RawData[[#This Row],[Status]]))="rnr",OR(ISNUMBER(SEARCH("requirement",LOWER(RawData[[#This Row],[Comments]]&" "&RawData[[#This Row],[Customer Requirement]]))),ISNUMBER(SEARCH("budget",LOWER(RawData[[#This Row],[Comments]]&" "&RawData[[#This Row],[Customer Requirement]]))),ISNUMBER(SEARCH("location",LOWER(RawData[[#This Row],[Comments]]&" "&RawData[[#This Row],[Customer Requirement]]))),ISNUMBER(SEARCH("purpose",LOWER(RawData[[#This Row],[Comments]]&" "&RawData[[#This Row],[Customer Requirement]]))),ISNUMBER(SEARCH("dimension",LOWER(RawData[[#This Row],[Comments]]&" "&RawData[[#This Row],[Customer Requirement]]))),ISNUMBER(SEARCH("sqft",LOWER(RawData[[#This Row],[Comments]]&" "&RawData[[#This Row],[Customer Requirement]]))))),"CRM Status Mismatch",""),IF(AND(ISNUMBER(RawData[[#This Row],[Next Followup Date]]),RawData[[#This Row],[Next Followup Date]]<NOW(),OR(LOWER(TRIM(RawData[[#This Row],[Lead Status]]))="hot",LOWER(TRIM(RawData[[#This Row],[Lead Status]]))="prospect",LOWER(TRIM(RawData[[#This Row],[Lead Status]]))="warm")),"Follow-up Error",""),IF(AND(LOWER(TRIM(RawData[[#This Row],[Location]]))="anekal",OR(ISNUMBER(SEARCH("ernika",LOWER(RawData[[#This Row],[Project Name]]))),ISNUMBER(SEARCH("enrika",LOWER(RawData[[#This Row],[Project Name]]))),ISNUMBER(SEARCH("exotica",LOWER(RawData[[#This Row],[Project Name]]))),ISNUMBER(SEARCH(" eka",LOWER(RawData[[#This Row],[Project Name]]))))),"Customer Location Not Captured",""))) -> Customer Location Not Captured | Q9: =IF(RawData[[#This Row],[Mobile]]="","",_xlfn.TEXTJOIN(CHAR(10),TRUE,IF(AND(OR(LOWER(TRIM(RawData[[#This Row],[Lead Status]]))="cold",LOWER(TRIM(RawData[[#This Row],[Lead Status]]))="lost"),OR(ISNUMBER(SEARCH("visit",LOWER(TRIM(RawData[[#This Row],[Comments]])))),ISNUMBER(SEARCH("brochure",LOWER(TRIM(RawData[[#This Row],[Comments]])))),ISNUMBER(SEARCH("pricing",LOWER(TRIM(RawData[[#This Row],[Comments]])))),ISNUMBER(SEARCH("price",LOWER(TRIM(RawData[[#This Row],[Comments]])))),ISNUMBER(SEARCH("budget",LOWER(TRIM(RawData[[#This Row],[Comments]])))))),"Engagement intent conflicts with Cold/Lost status",""),IF(AND(LOWER(TRIM(RawData[[#This Row],[Lead Status]]))="cold",OR(LOWER(TRIM(RawData[[#This Row],[Comments]]))="rnr",LOWER(TRIM(RawData[[#This Row],[Comments]]))="busy",LOWER(TRIM(RawData[[#This Row],[Comments]]))="out of network",LOWER(TRIM(RawData[[#This Row],[Comments]]))="outoff network",LOWER(TRIM(RawData[[#This Row],[Comments]]))="voice mail",LOWER(TRIM(RawData[[#This Row],[Comments]]))="voicemail")),"Contact outcome should remain RNR rather than Cold",""),IF(AND(LOWER(TRIM(RawData[[#This Row],[Lead Status]]))="warm",OR(LOWER(TRIM(RawData[[#This Row],[Comments]]))="busy",LOWER(TRIM(RawData[[#This Row],[Comments]]))="voice mail",LOWER(TRIM(RawData[[#This Row],[Comments]]))="voicemail",LOWER(TRIM(RawData[[#This Row],[Comments]]))="call back later")),"Contact-only outcome does not support Warm status",""),IF(AND(LOWER(TRIM(RawData[[#This Row],[Status]]))="rnr",OR(ISNUMBER(SEARCH("requirement",LOWER(RawData[[#This Row],[Comments]]&" "&RawData[[#This Row],[Customer Requirement]]))),ISNUMBER(SEARCH("budget",LOWER(RawData[[#This Row],[Comments]]&" "&RawData[[#This Row],[Customer Requirement]]))),ISNUMBER(SEARCH("location",LOWER(RawData[[#This Row],[Comments]]&" "&RawData[[#This Row],[Customer Requirement]]))),ISNUMBER(SEARCH("purpose",LOWER(RawData[[#This Row],[Comments]]&" "&RawData[[#This Row],[Customer Requirement]]))),ISNUMBER(SEARCH("dimension",LOWER(RawData[[#This Row],[Comments]]&" "&RawData[[#This Row],[Customer Requirement]]))),ISNUMBER(SEARCH("sqft",LOWER(RawData[[#This Row],[Comments]]&" "&RawData[[#This Row],[Customer Requirement]]))))),"Requirements were captured while CRM status remains RNR",""),IF(AND(ISNUMBER(RawData[[#This Row],[Next Followup Date]]),RawData[[#This Row],[Next Followup Date]]<NOW(),OR(LOWER(TRIM(RawData[[#This Row],[Lead Status]]))="hot",LOWER(TRIM(RawData[[#This Row],[Lead Status]]))="prospect",LOWER(TRIM(RawData[[#This Row],[Lead Status]]))="warm")),"Follow-up date/time has passed for an active lead",""),IF(AND(LOWER(TRIM(RawData[[#This Row],[Location]]))="anekal",OR(ISNUMBER(SEARCH("ernika",LOWER(RawData[[#This Row],[Project Name]]))),ISNUMBER(SEARCH("enrika",LOWER(RawData[[#This Row],[Project Name]]))),ISNUMBER(SEARCH("exotica",LOWER(RawData[[#This Row],[Project Name]]))),ISNUMBER(SEARCH(" eka",LOWER(RawData[[#This Row],[Project Name]]))))),"Anekal is the project default; customer location was not captured",""))) -> Anekal is the project default; customer location was not captured | R9: =IF(RawData[[#This Row],[Mobile]]="","",_xlfn.TEXTJOIN(CHAR(10),TRUE,IF(AND(OR(LOWER(TRIM(RawData[[#This Row],[Lead Status]]))="cold",LOWER(TRIM(RawData[[#This Row],[Lead Status]]))="lost"),OR(ISNUMBER(SEARCH("visit",LOWER(TRIM(RawData[[#This Row],[Comments]])))),ISNUMBER(SEARCH("brochure",LOWER(TRIM(RawData[[#This Row],[Comments]])))),ISNUMBER(SEARCH("pricing",LOWER(TRIM(RawData[[#This Row],[Comments]])))),ISNUMBER(SEARCH("price",LOWER(TRIM(RawData[[#This Row],[Comments]])))),ISNUMBER(SEARCH("budget",LOWER(TRIM(RawData[[#This Row],[Comments]])))))),"Reclassify lead and schedule a documented follow-up",""),IF(AND(LOWER(TRIM(RawData[[#This Row],[Lead Status]]))="cold",OR(LOWER(TRIM(RawData[[#This Row],[Comments]]))="rnr",LOWER(TRIM(RawData[[#This Row],[Comments]]))="busy",LOWER(TRIM(RawData[[#This Row],[Comments]]))="out of network",LOWER(TRIM(RawData[[#This Row],[Comments]]))="outoff network",LOWER(TRIM(RawData[[#This Row],[Comments]]))="voice mail",LOWER(TRIM(RawData[[#This Row],[Comments]]))="voicemail")),"Change lead classification to RNR and retry contact",""),IF(AND(LOWER(TRIM(RawData[[#This Row],[Lead Status]]))="warm",OR(LOWER(TRIM(RawData[[#This Row],[Comments]]))="busy",LOWER(TRIM(RawData[[#This Row],[Comments]]))="voice mail",LOWER(TRIM(RawData[[#This Row],[Comments]]))="voicemail",LOWER(TRIM(RawData[[#This Row],[Comments]]))="call back later")),"Validate engagement before retaining Warm status",""),IF(AND(LOWER(TRIM(RawData[[#This Row],[Status]]))="rnr",OR(ISNUMBER(SEARCH("requirement",LOWER(RawData[[#This Row],[Comments]]&" "&RawData[[#This Row],[Customer Requirement]]))),ISNUMBER(SEARCH("budget",LOWER(RawData[[#This Row],[Comments]]&" "&RawData[[#This Row],[Customer Requirement]]))),ISNUMBER(SEARCH("location",LOWER(RawData[[#This Row],[Comments]]&" "&RawData[[#This Row],[Customer Requirement]]))),ISNUMBER(SEARCH("purpose",LOWER(RawData[[#This Row],[Comments]]&" "&RawData[[#This Row],[Customer Requirement]]))),ISNUMBER(SEARCH("dimension",LOWER(RawData[[#This Row],[Comments]]&" "&RawData[[#This Row],[Customer Requirement]]))),ISNUMBER(SEARCH("sqft",LOWER(RawData[[#This Row],[Comments]]&" "&RawData[[#This Row],[Customer Requirement]]))))),"Update CRM status to reflect the collected requirement",""),IF(AND(ISNUMBER(RawData[[#This Row],[Next Followup Date]]),RawData[[#This Row],[Next Followup Date]]<NOW(),OR(LOWER(TRIM(RawData[[#This Row],[Lead Status]]))="hot",LOWER(TRIM(RawData[[#This Row],[Lead Status]]))="prospect",LOWER(TRIM(RawData[[#This Row],[Lead Status]]))="warm")),"Contact immediately and set the next follow-up",""),IF(AND(LOWER(TRIM(RawData[[#This Row],[Location]]))="anekal",OR(ISNUMBER(SEARCH("ernika",LOWER(RawData[[#This Row],[Project Name]]))),ISNUMBER(SEARCH("enrika",LOWER(RawData[[#This Row],[Project Name]]))),ISNUMBER(SEARCH("exotica",LOWER(RawData[[#This Row],[Project Name]]))),ISNUMBER(SEARCH(" eka",LOWER(RawData[[#This Row],[Project Name]]))))),"Contact the customer and record their actual location",""))) -> Contact the customer and record their actual location | S9: =IF(RawData[[#This Row],[Error Flag]]=0,"",IF(OR(ISNUMBER(SEARCH("Wrong Lead Status",RawData[[#This Row],[Error Type]])),ISNUMBER(SEARCH("RNR Classification Error",RawData[[#This Row],[Error Type]])),ISNUMBER(SEARCH("Follow-up Error",RawData[[#This Row],[Error Type]]))),"Critical","Medium")) -> Medium | T9: =IF(RawData[[#This Row],[Error Flag]]=0,"Pass","Action Required ("&RawData[[#This Row],[Error Flag]]&IF(RawData[[#This Row],[Error Flag]]=1," error)"," errors)")) -> Action Required (1 error) | U9: =IF(RawData[[#This Row],[Mobile]]="",0,--(AND(OR(LOWER(TRIM(RawData[[#This Row],[Lead Status]]))="cold",LOWER(TRIM(RawData[[#This Row],[Lead Status]]))="lost"),OR(ISNUMBER(SEARCH("visit",LOWER(TRIM(RawData[[#This Row],[Comments]])))),ISNUMBER(SEARCH("brochure",LOWER(TRIM(RawData[[#This Row],[Comments]])))),ISNUMBER(SEARCH("pricing",LOWER(TRIM(RawData[[#This Row],[Comments]])))),ISNUMBER(SEARCH("price",LOWER(TRIM(RawData[[#This Row],[Comments]])))),ISNUMBER(SEARCH("budget",LOWER(TRIM(RawData[[#This Row],[Comments]])))))))+--(AND(LOWER(TRIM(RawData[[#This Row],[Lead Status]]))="cold",OR(LOWER(TRIM(RawData[[#This Row],[Comments]]))="rnr",LOWER(TRIM(RawData[[#This Row],[Comments]]))="busy",LOWER(TRIM(RawData[[#This Row],[Comments]]))="out of network",LOWER(TRIM(RawData[[#This Row],[Comments]]))="outoff network",LOWER(TRIM(RawData[[#This Row],[Comments]]))="voice mail",LOWER(TRIM(RawData[[#This Row],[Comments]]))="voicemail")))+--(AND(LOWER(TRIM(RawData[[#This Row],[Lead Status]]))="warm",OR(LOWER(TRIM(RawData[[#This Row],[Comments]]))="busy",LOWER(TRIM(RawData[[#This Row],[Comments]]))="voice mail",LOWER(TRIM(RawData[[#This Row],[Comments]]))="voicemail",LOWER(TRIM(RawData[[#This Row],[Comments]]))="call back later")))+--(AND(LOWER(TRIM(RawData[[#This Row],[Status]]))="rnr",OR(ISNUMBER(SEARCH("requirement",LOWER(RawData[[#This Row],[Comments]]&" "&RawData[[#This Row],[Customer Requirement]]))),ISNUMBER(SEARCH("budget",LOWER(RawData[[#This Row],[Comments]]&" "&RawData[[#This Row],[Customer Requirement]]))),ISNUMBER(SEARCH("location",LOWER(RawData[[#This Row],[Comments]]&" "&RawData[[#This Row],[Customer Requirement]]))),ISNUMBER(SEARCH("purpose",LOWER(RawData[[#This Row],[Comments]]&" "&RawData[[#This Row],[Customer Requirement]]))),ISNUMBER(SEARCH("dimension",LOWER(RawData[[#This Row],[Comments]]&" "&RawData[[#This Row],[Customer Requirement]]))),ISNUMBER(SEARCH("sqft",LOWER(RawData[[#This Row],[Comments]]&" "&RawData[[#This Row],[Customer Requirement]]))))))+--(AND(ISNUMBER(RawData[[#This Row],[Next Followup Date]]),RawData[[#This Row],[Next Followup Date]]<NOW(),OR(LOWER(TRIM(RawData[[#This Row],[Lead Status]]))="hot",LOWER(TRIM(RawData[[#This Row],[Lead Status]]))="prospect",LOWER(TRIM(RawData[[#This Row],[Lead Status]]))="warm")))+--(AND(LOWER(TRIM(RawData[[#This Row],[Location]]))="anekal",OR(ISNUMBER(SEARCH("ernika",LOWER(RawData[[#This Row],[Project Name]]))),ISNUMBER(SEARCH("enrika",LOWER(RawData[[#This Row],[Project Name]]))),ISNUMBER(SEARCH("exotica",LOWER(RawData[[#This Row],[Project Name]]))),ISNUMBER(SEARCH(" eka",LOWER(RawData[[#This Row],[Project Name]]))))))) -> 1 | W9: ='Telecaller Performance'!A13 | X9: {=IF(W9="",NA(),_xlfn.LET(_xlpm.v,SUBTOTAL(103,OFFSET(RawData[Mobile],ROW(RawData[Mobile])-MIN(ROW(RawData[Mobile])),0,1)),_xlpm.z,SUMPRODUCT(_xlpm.v,--(RawData[Telecaller Name]=W9)),IF(_xlpm.z=0,NA(),MAX(0,1-SUMPRODUCT(_xlpm.v,--(RawData[Telecaller Name]=W9),RawData[Error Flag])/_xlpm.z))))} -> #N/A | Z9: ='Telecaller Performance'!A13 | AA9: {=IF(Z9="",NA(),_xlfn.LET(_xlpm.v,SUBTOTAL(103,OFFSET(RawData[Mobile],ROW(RawData[Mobile])-MIN(ROW(RawData[Mobile])),0,1)),_xlpm.z,SUMPRODUCT(_xlpm.v,--(RawData[Telecaller Name]=Z9)),IF(_xlpm.z=0,NA(),SUMPRODUCT(_xlpm.v,--(RawData[Telecaller Name]=Z9),RawData[Error Flag]))))} -> #N/A | AF9: {=IFERROR(INDEX(_xlfn._xlws.SORT(_xlfn.UNIQUE(_xlfn._xlws.FILTER(RawData[Project Name],RawData[Project Name]<>""))),ROWS(AF$2:AF9)),"")} | AG9: {=IF(AF9="",NA(),_xlfn.LET(_xlpm.v,SUBTOTAL(103,OFFSET(RawData[Mobile],ROW(RawData[Mobile])-MIN(ROW(RawData[Mobile])),0,1)),_xlpm.z,SUMPRODUCT(_xlpm.v,--(RawData[Project Name]=AF9)),IF(_xlpm.z=0,NA(),SUMPRODUCT(_xlpm.v,--(RawData[Project Name]=AF9),RawData[Error Flag]))))} -> #N/A
A10: Guru Punvaanii Ernika | B10: 7975982783 | C10: Vinutha M1 | D10: 46253 | E10: warm | F10: There was a network issue , said i will call in whatsapp , said yes but whatsapp call also not responded | G10: 46256.424 | I10: -1 | J10: Interested | K10: RNR | L10: .. | M10: Digital Marketing | N10: Meta_StaticAds_Aug2026 | O10: 1 | P10: =IF(RawData[[#This Row],[Mobile]]="","",_xlfn.TEXTJOIN(" | ",TRUE,IF(AND(OR(LOWER(TRIM(RawData[[#This Row],[Lead Status]]))="cold",LOWER(TRIM(RawData[[#This Row],[Lead Status]]))="lost"),OR(ISNUMBER(SEARCH("visit",LOWER(TRIM(RawData[[#This Row],[Comments]])))),ISNUMBER(SEARCH("brochure",LOWER(TRIM(RawData[[#This Row],[Comments]])))),ISNUMBER(SEARCH("pricing",LOWER(TRIM(RawData[[#This Row],[Comments]])))),ISNUMBER(SEARCH("price",LOWER(TRIM(RawData[[#This Row],[Comments]])))),ISNUMBER(SEARCH("budget",LOWER(TRIM(RawData[[#This Row],[Comments]])))))),"Wrong Lead Status",""),IF(AND(LOWER(TRIM(RawData[[#This Row],[Lead Status]]))="cold",OR(LOWER(TRIM(RawData[[#This Row],[Comments]]))="rnr",LOWER(TRIM(RawData[[#This Row],[Comments]]))="busy",LOWER(TRIM(RawData[[#This Row],[Comments]]))="out of network",LOWER(TRIM(RawData[[#This Row],[Comments]]))="outoff network",LOWER(TRIM(RawData[[#This Row],[Comments]]))="voice mail",LOWER(TRIM(RawData[[#This Row],[Comments]]))="voicemail")),"RNR Classification Error",""),IF(AND(LOWER(TRIM(RawData[[#This Row],[Lead Status]]))="warm",OR(LOWER(TRIM(RawData[[#This Row],[Comments]]))="busy",LOWER(TRIM(RawData[[#This Row],[Comments]]))="voice mail",LOWER(TRIM(RawData[[#This Row],[Comments]]))="voicemail",LOWER(TRIM(RawData[[#This Row],[Comments]]))="call back later")),"Warm Status Mismatch",""),IF(AND(LOWER(TRIM(RawData[[#This Row],[Status]]))="rnr",OR(ISNUMBER(SEARCH("requirement",LOWER(RawData[[#This Row],[Comments]]&" "&RawData[[#This Row],[Customer Requirement]]))),ISNUMBER(SEARCH("budget",LOWER(RawData[[#This Row],[Comments]]&" "&RawData[[#This Row],[Customer Requirement]]))),ISNUMBER(SEARCH("location",LOWER(RawData[[#This Row],[Comments]]&" "&RawData[[#This Row],[Customer Requirement]]))),ISNUMBER(SEARCH("purpose",LOWER(RawData[[#This Row],[Comments]]&" "&RawData[[#This Row],[Customer Requirement]]))),ISNUMBER(SEARCH("dimension",LOWER(RawData[[#This Row],[Comments]]&" "&RawData[[#This Row],[Customer Requirement]]))),ISNUMBER(SEARCH("sqft",LOWER(RawData[[#This Row],[Comments]]&" "&RawData[[#This Row],[Customer Requirement]]))))),"CRM Status Mismatch",""),IF(AND(ISNUMBER(RawData[[#This Row],[Next Followup Date]]),RawData[[#This Row],[Next Followup Date]]<NOW(),OR(LOWER(TRIM(RawData[[#This Row],[Lead Status]]))="hot",LOWER(TRIM(RawData[[#This Row],[Lead Status]]))="prospect",LOWER(TRIM(RawData[[#This Row],[Lead Status]]))="warm")),"Follow-up Error",""),IF(AND(LOWER(TRIM(RawData[[#This Row],[Location]]))="anekal",OR(ISNUMBER(SEARCH("ernika",LOWER(RawData[[#This Row],[Project Name]]))),ISNUMBER(SEARCH("enrika",LOWER(RawData[[#This Row],[Project Name]]))),ISNUMBER(SEARCH("exotica",LOWER(RawData[[#This Row],[Project Name]]))),ISNUMBER(SEARCH(" eka",LOWER(RawData[[#This Row],[Project Name]]))))),"Customer Location Not Captured",""))) | Q10: =IF(RawData[[#This Row],[Mobile]]="","",_xlfn.TEXTJOIN(CHAR(10),TRUE,IF(AND(OR(LOWER(TRIM(RawData[[#This Row],[Lead Status]]))="cold",LOWER(TRIM(RawData[[#This Row],[Lead Status]]))="lost"),OR(ISNUMBER(SEARCH("visit",LOWER(TRIM(RawData[[#This Row],[Comments]])))),ISNUMBER(SEARCH("brochure",LOWER(TRIM(RawData[[#This Row],[Comments]])))),ISNUMBER(SEARCH("pricing",LOWER(TRIM(RawData[[#This Row],[Comments]])))),ISNUMBER(SEARCH("price",LOWER(TRIM(RawData[[#This Row],[Comments]])))),ISNUMBER(SEARCH("budget",LOWER(TRIM(RawData[[#This Row],[Comments]])))))),"Engagement intent conflicts with Cold/Lost status",""),IF(AND(LOWER(TRIM(RawData[[#This Row],[Lead Status]]))="cold",OR(LOWER(TRIM(RawData[[#This Row],[Comments]]))="rnr",LOWER(TRIM(RawData[[#This Row],[Comments]]))="busy",LOWER(TRIM(RawData[[#This Row],[Comments]]))="out of network",LOWER(TRIM(RawData[[#This Row],[Comments]]))="outoff network",LOWER(TRIM(RawData[[#This Row],[Comments]]))="voice mail",LOWER(TRIM(RawData[[#This Row],[Comments]]))="voicemail")),"Contact outcome should remain RNR rather than Cold",""),IF(AND(LOWER(TRIM(RawData[[#This Row],[Lead Status]]))="warm",OR(LOWER(TRIM(RawData[[#This Row],[Comments]]))="busy",LOWER(TRIM(RawData[[#This Row],[Comments]]))="voice mail",LOWER(TRIM(RawData[[#This Row],[Comments]]))="voicemail",LOWER(TRIM(RawData[[#This Row],[Comments]]))="call back later")),"Contact-only outcome does not support Warm status",""),IF(AND(LOWER(TRIM(RawData[[#This Row],[Status]]))="rnr",OR(ISNUMBER(SEARCH("requirement",LOWER(RawData[[#This Row],[Comments]]&" "&RawData[[#This Row],[Customer Requirement]]))),ISNUMBER(SEARCH("budget",LOWER(RawData[[#This Row],[Comments]]&" "&RawData[[#This Row],[Customer Requirement]]))),ISNUMBER(SEARCH("location",LOWER(RawData[[#This Row],[Comments]]&" "&RawData[[#This Row],[Customer Requirement]]))),ISNUMBER(SEARCH("purpose",LOWER(RawData[[#This Row],[Comments]]&" "&RawData[[#This Row],[Customer Requirement]]))),ISNUMBER(SEARCH("dimension",LOWER(RawData[[#This Row],[Comments]]&" "&RawData[[#This Row],[Customer Requirement]]))),ISNUMBER(SEARCH("sqft",LOWER(RawData[[#This Row],[Comments]]&" "&RawData[[#This Row],[Customer Requirement]]))))),"Requirements were captured while CRM status remains RNR",""),IF(AND(ISNUMBER(RawData[[#This Row],[Next Followup Date]]),RawData[[#This Row],[Next Followup Date]]<NOW(),OR(LOWER(TRIM(RawData[[#This Row],[Lead Status]]))="hot",LOWER(TRIM(RawData[[#This Row],[Lead Status]]))="prospect",LOWER(TRIM(RawData[[#This Row],[Lead Status]]))="warm")),"Follow-up date/time has passed for an active lead",""),IF(AND(LOWER(TRIM(RawData[[#This Row],[Location]]))="anekal",OR(ISNUMBER(SEARCH("ernika",LOWER(RawData[[#This Row],[Project Name]]))),ISNUMBER(SEARCH("enrika",LOWER(RawData[[#This Row],[Project Name]]))),ISNUMBER(SEARCH("exotica",LOWER(RawData[[#This Row],[Project Name]]))),ISNUMBER(SEARCH(" eka",LOWER(RawData[[#This Row],[Project Name]]))))),"Anekal is the project default; customer location was not captured",""))) | R10: =IF(RawData[[#This Row],[Mobile]]="","",_xlfn.TEXTJOIN(CHAR(10),TRUE,IF(AND(OR(LOWER(TRIM(RawData[[#This Row],[Lead Status]]))="cold",LOWER(TRIM(RawData[[#This Row],[Lead Status]]))="lost"),OR(ISNUMBER(SEARCH("visit",LOWER(TRIM(RawData[[#This Row],[Comments]])))),ISNUMBER(SEARCH("brochure",LOWER(TRIM(RawData[[#This Row],[Comments]])))),ISNUMBER(SEARCH("pricing",LOWER(TRIM(RawData[[#This Row],[Comments]])))),ISNUMBER(SEARCH("price",LOWER(TRIM(RawData[[#This Row],[Comments]])))),ISNUMBER(SEARCH("budget",LOWER(TRIM(RawData[[#This Row],[Comments]])))))),"Reclassify lead and schedule a documented follow-up",""),IF(AND(LOWER(TRIM(RawData[[#This Row],[Lead Status]]))="cold",OR(LOWER(TRIM(RawData[[#This Row],[Comments]]))="rnr",LOWER(TRIM(RawData[[#This Row],[Comments]]))="busy",LOWER(TRIM(RawData[[#This Row],[Comments]]))="out of network",LOWER(TRIM(RawData[[#This Row],[Comments]]))="outoff network",LOWER(TRIM(RawData[[#This Row],[Comments]]))="voice mail",LOWER(TRIM(RawData[[#This Row],[Comments]]))="voicemail")),"Change lead classification to RNR and retry contact",""),IF(AND(LOWER(TRIM(RawData[[#This Row],[Lead Status]]))="warm",OR(LOWER(TRIM(RawData[[#This Row],[Comments]]))="busy",LOWER(TRIM(RawData[[#This Row],[Comments]]))="voice mail",LOWER(TRIM(RawData[[#This Row],[Comments]]))="voicemail",LOWER(TRIM(RawData[[#This Row],[Comments]]))="call back later")),"Validate engagement before retaining Warm status",""),IF(AND(LOWER(TRIM(RawData[[#This Row],[Status]]))="rnr",OR(ISNUMBER(SEARCH("requirement",LOWER(RawData[[#This Row],[Comments]]&" "&RawData[[#This Row],[Customer Requirement]]))),ISNUMBER(SEARCH("budget",LOWER(RawData[[#This Row],[Comments]]&" "&RawData[[#This Row],[Customer Requirement]]))),ISNUMBER(SEARCH("location",LOWER(RawData[[#This Row],[Comments]]&" "&RawData[[#This Row],[Customer Requirement]]))),ISNUMBER(SEARCH("purpose",LOWER(RawData[[#This Row],[Comments]]&" "&RawData[[#This Row],[Customer Requirement]]))),ISNUMBER(SEARCH("dimension",LOWER(RawData[[#This Row],[Comments]]&" "&RawData[[#This Row],[Customer Requirement]]))),ISNUMBER(SEARCH("sqft",LOWER(RawData[[#This Row],[Comments]]&" "&RawData[[#This Row],[Customer Requirement]]))))),"Update CRM status to reflect the collected requirement",""),IF(AND(ISNUMBER(RawData[[#This Row],[Next Followup Date]]),RawData[[#This Row],[Next Followup Date]]<NOW(),OR(LOWER(TRIM(RawData[[#This Row],[Lead Status]]))="hot",LOWER(TRIM(RawData[[#This Row],[Lead Status]]))="prospect",LOWER(TRIM(RawData[[#This Row],[Lead Status]]))="warm")),"Contact immediately and set the next follow-up",""),IF(AND(LOWER(TRIM(RawData[[#This Row],[Location]]))="anekal",OR(ISNUMBER(SEARCH("ernika",LOWER(RawData[[#This Row],[Project Name]]))),ISNUMBER(SEARCH("enrika",LOWER(RawData[[#This Row],[Project Name]]))),ISNUMBER(SEARCH("exotica",LOWER(RawData[[#This Row],[Project Name]]))),ISNUMBER(SEARCH(" eka",LOWER(RawData[[#This Row],[Project Name]]))))),"Contact the customer and record their actual location",""))) | S10: =IF(RawData[[#This Row],[Error Flag]]=0,"",IF(OR(ISNUMBER(SEARCH("Wrong Lead Status",RawData[[#This Row],[Error Type]])),ISNUMBER(SEARCH("RNR Classification Error",RawData[[#This Row],[Error Type]])),ISNUMBER(SEARCH("Follow-up Error",RawData[[#This Row],[Error Type]]))),"Critical","Medium")) | T10: =IF(RawData[[#This Row],[Error Flag]]=0,"Pass","Action Required ("&RawData[[#This Row],[Error Flag]]&IF(RawData[[#This Row],[Error Flag]]=1," error)"," errors)")) -> Pass | U10: =IF(RawData[[#This Row],[Mobile]]="",0,--(AND(OR(LOWER(TRIM(RawData[[#This Row],[Lead Status]]))="cold",LOWER(TRIM(RawData[[#This Row],[Lead Status]]))="lost"),OR(ISNUMBER(SEARCH("visit",LOWER(TRIM(RawData[[#This Row],[Comments]])))),ISNUMBER(SEARCH("brochure",LOWER(TRIM(RawData[[#This Row],[Comments]])))),ISNUMBER(SEARCH("pricing",LOWER(TRIM(RawData[[#This Row],[Comments]])))),ISNUMBER(SEARCH("price",LOWER(TRIM(RawData[[#This Row],[Comments]])))),ISNUMBER(SEARCH("budget",LOWER(TRIM(RawData[[#This Row],[Comments]])))))))+--(AND(LOWER(TRIM(RawData[[#This Row],[Lead Status]]))="cold",OR(LOWER(TRIM(RawData[[#This Row],[Comments]]))="rnr",LOWER(TRIM(RawData[[#This Row],[Comments]]))="busy",LOWER(TRIM(RawData[[#This Row],[Comments]]))="out of network",LOWER(TRIM(RawData[[#This Row],[Comments]]))="outoff network",LOWER(TRIM(RawData[[#This Row],[Comments]]))="voice mail",LOWER(TRIM(RawData[[#This Row],[Comments]]))="voicemail")))+--(AND(LOWER(TRIM(RawData[[#This Row],[Lead Status]]))="warm",OR(LOWER(TRIM(RawData[[#This Row],[Comments]]))="busy",LOWER(TRIM(RawData[[#This Row],[Comments]]))="voice mail",LOWER(TRIM(RawData[[#This Row],[Comments]]))="voicemail",LOWER(TRIM(RawData[[#This Row],[Comments]]))="call back later")))+--(AND(LOWER(TRIM(RawData[[#This Row],[Status]]))="rnr",OR(ISNUMBER(SEARCH("requirement",LOWER(RawData[[#This Row],[Comments]]&" "&RawData[[#This Row],[Customer Requirement]]))),ISNUMBER(SEARCH("budget",LOWER(RawData[[#This Row],[Comments]]&" "&RawData[[#This Row],[Customer Requirement]]))),ISNUMBER(SEARCH("location",LOWER(RawData[[#This Row],[Comments]]&" "&RawData[[#This Row],[Customer Requirement]]))),ISNUMBER(SEARCH("purpose",LOWER(RawData[[#This Row],[Comments]]&" "&RawData[[#This Row],[Customer Requirement]]))),ISNUMBER(SEARCH("dimension",LOWER(RawData[[#This Row],[Comments]]&" "&RawData[[#This Row],[Customer Requirement]]))),ISNUMBER(SEARCH("sqft",LOWER(RawData[[#This Row],[Comments]]&" "&RawData[[#This Row],[Customer Requirement]]))))))+--(AND(ISNUMBER(RawData[[#This Row],[Next Followup Date]]),RawData[[#This Row],[Next Followup Date]]<NOW(),OR(LOWER(TRIM(RawData[[#This Row],[Lead Status]]))="hot",LOWER(TRIM(RawData[[#This Row],[Lead Status]]))="prospect",LOWER(TRIM(RawData[[#This Row],[Lead Status]]))="warm")))+--(AND(LOWER(TRIM(RawData[[#This Row],[Location]]))="anekal",OR(ISNUMBER(SEARCH("ernika",LOWER(RawData[[#This Row],[Project Name]]))),ISNUMBER(SEARCH("enrika",LOWER(RawData[[#This Row],[Project Name]]))),ISNUMBER(SEARCH("exotica",LOWER(RawData[[#This Row],[Project Name]]))),ISNUMBER(SEARCH(" eka",LOWER(RawData[[#This Row],[Project Name]]))))))) -> 0 | W10: ='Telecaller Performance'!A14 | X10: {=IF(W10="",NA(),_xlfn.LET(_xlpm.v,SUBTOTAL(103,OFFSET(RawData[Mobile],ROW(RawData[Mobile])-MIN(ROW(RawData[Mobile])),0,1)),_xlpm.z,SUMPRODUCT(_xlpm.v,--(RawData[Telecaller Name]=W10)),IF(_xlpm.z=0,NA(),MAX(0,1-SUMPRODUCT(_xlpm.v,--(RawData[Telecaller Name]=W10),RawData[Error Flag])/_xlpm.z))))} -> #N/A | Z10: ='Telecaller Performance'!A14 | AA10: {=IF(Z10="",NA(),_xlfn.LET(_xlpm.v,SUBTOTAL(103,OFFSET(RawData[Mobile],ROW(RawData[Mobile])-MIN(ROW(RawData[Mobile])),0,1)),_xlpm.z,SUMPRODUCT(_xlpm.v,--(RawData[Telecaller Name]=Z10)),IF(_xlpm.z=0,NA(),SUMPRODUCT(_xlpm.v,--(RawData[Telecaller Name]=Z10),RawData[Error Flag]))))} -> #N/A | AF10: {=IFERROR(INDEX(_xlfn._xlws.SORT(_xlfn.UNIQUE(_xlfn._xlws.FILTER(RawData[Project Name],RawData[Project Name]<>""))),ROWS(AF$2:AF10)),"")} | AG10: {=IF(AF10="",NA(),_xlfn.LET(_xlpm.v,SUBTOTAL(103,OFFSET(RawData[Mobile],ROW(RawData[Mobile])-MIN(ROW(RawData[Mobile])),0,1)),_xlpm.z,SUMPRODUCT(_xlpm.v,--(RawData[Project Name]=AF10)),IF(_xlpm.z=0,NA(),SUMPRODUCT(_xlpm.v,--(RawData[Project Name]=AF10),RawData[Error Flag]))))} -> #N/A
A11: Guru Punvaanii Ernika | B11: 8073016841 | C11: Vinutha M1 | D11: 46253 | E11: Prospect | F11: He said he will call & come for the visit.its raining there.- Aishwarya spoke | G11: 46256.585 | H11: Anekal | I11: -1 | J11: Interested | K11: In Progress | L11: requirement-1200sqft corner plot location -btm layout purpose- investment now and later for construction | M11: Online Portal | N11: 99 Acres | O11: 1 | P11: =IF(RawData[[#This Row],[Mobile]]="","",_xlfn.TEXTJOIN(" | ",TRUE,IF(AND(OR(LOWER(TRIM(RawData[[#This Row],[Lead Status]]))="cold",LOWER(TRIM(RawData[[#This Row],[Lead Status]]))="lost"),OR(ISNUMBER(SEARCH("visit",LOWER(TRIM(RawData[[#This Row],[Comments]])))),ISNUMBER(SEARCH("brochure",LOWER(TRIM(RawData[[#This Row],[Comments]])))),ISNUMBER(SEARCH("pricing",LOWER(TRIM(RawData[[#This Row],[Comments]])))),ISNUMBER(SEARCH("price",LOWER(TRIM(RawData[[#This Row],[Comments]])))),ISNUMBER(SEARCH("budget",LOWER(TRIM(RawData[[#This Row],[Comments]])))))),"Wrong Lead Status",""),IF(AND(LOWER(TRIM(RawData[[#This Row],[Lead Status]]))="cold",OR(LOWER(TRIM(RawData[[#This Row],[Comments]]))="rnr",LOWER(TRIM(RawData[[#This Row],[Comments]]))="busy",LOWER(TRIM(RawData[[#This Row],[Comments]]))="out of network",LOWER(TRIM(RawData[[#This Row],[Comments]]))="outoff network",LOWER(TRIM(RawData[[#This Row],[Comments]]))="voice mail",LOWER(TRIM(RawData[[#This Row],[Comments]]))="voicemail")),"RNR Classification Error",""),IF(AND(LOWER(TRIM(RawData[[#This Row],[Lead Status]]))="warm",OR(LOWER(TRIM(RawData[[#This Row],[Comments]]))="busy",LOWER(TRIM(RawData[[#This Row],[Comments]]))="voice mail",LOWER(TRIM(RawData[[#This Row],[Comments]]))="voicemail",LOWER(TRIM(RawData[[#This Row],[Comments]]))="call back later")),"Warm Status Mismatch",""),IF(AND(LOWER(TRIM(RawData[[#This Row],[Status]]))="rnr",OR(ISNUMBER(SEARCH("requirement",LOWER(RawData[[#This Row],[Comments]]&" "&RawData[[#This Row],[Customer Requirement]]))),ISNUMBER(SEARCH("budget",LOWER(RawData[[#This Row],[Comments]]&" "&RawData[[#This Row],[Customer Requirement]]))),ISNUMBER(SEARCH("location",LOWER(RawData[[#This Row],[Comments]]&" "&RawData[[#This Row],[Customer Requirement]]))),ISNUMBER(SEARCH("purpose",LOWER(RawData[[#This Row],[Comments]]&" "&RawData[[#This Row],[Customer Requirement]]))),ISNUMBER(SEARCH("dimension",LOWER(RawData[[#This Row],[Comments]]&" "&RawData[[#This Row],[Customer Requirement]]))),ISNUMBER(SEARCH("sqft",LOWER(RawData[[#This Row],[Comments]]&" "&RawData[[#This Row],[Customer Requirement]]))))),"CRM Status Mismatch",""),IF(AND(ISNUMBER(RawData[[#This Row],[Next Followup Date]]),RawData[[#This Row],[Next Followup Date]]<NOW(),OR(LOWER(TRIM(RawData[[#This Row],[Lead Status]]))="hot",LOWER(TRIM(RawData[[#This Row],[Lead Status]]))="prospect",LOWER(TRIM(RawData[[#This Row],[Lead Status]]))="warm")),"Follow-up Error",""),IF(AND(LOWER(TRIM(RawData[[#This Row],[Location]]))="anekal",OR(ISNUMBER(SEARCH("ernika",LOWER(RawData[[#This Row],[Project Name]]))),ISNUMBER(SEARCH("enrika",LOWER(RawData[[#This Row],[Project Name]]))),ISNUMBER(SEARCH("exotica",LOWER(RawData[[#This Row],[Project Name]]))),ISNUMBER(SEARCH(" eka",LOWER(RawData[[#This Row],[Project Name]]))))),"Customer Location Not Captured",""))) -> Customer Location Not Captured | Q11: =IF(RawData[[#This Row],[Mobile]]="","",_xlfn.TEXTJOIN(CHAR(10),TRUE,IF(AND(OR(LOWER(TRIM(RawData[[#This Row],[Lead Status]]))="cold",LOWER(TRIM(RawData[[#This Row],[Lead Status]]))="lost"),OR(ISNUMBER(SEARCH("visit",LOWER(TRIM(RawData[[#This Row],[Comments]])))),ISNUMBER(SEARCH("brochure",LOWER(TRIM(RawData[[#This Row],[Comments]])))),ISNUMBER(SEARCH("pricing",LOWER(TRIM(RawData[[#This Row],[Comments]])))),ISNUMBER(SEARCH("price",LOWER(TRIM(RawData[[#This Row],[Comments]])))),ISNUMBER(SEARCH("budget",LOWER(TRIM(RawData[[#This Row],[Comments]])))))),"Engagement intent conflicts with Cold/Lost status",""),IF(AND(LOWER(TRIM(RawData[[#This Row],[Lead Status]]))="cold",OR(LOWER(TRIM(RawData[[#This Row],[Comments]]))="rnr",LOWER(TRIM(RawData[[#This Row],[Comments]]))="busy",LOWER(TRIM(RawData[[#This Row],[Comments]]))="out of network",LOWER(TRIM(RawData[[#This Row],[Comments]]))="outoff network",LOWER(TRIM(RawData[[#This Row],[Comments]]))="voice mail",LOWER(TRIM(RawData[[#This Row],[Comments]]))="voicemail")),"Contact outcome should remain RNR rather than Cold",""),IF(AND(LOWER(TRIM(RawData[[#This Row],[Lead Status]]))="warm",OR(LOWER(TRIM(RawData[[#This Row],[Comments]]))="busy",LOWER(TRIM(RawData[[#This Row],[Comments]]))="voice mail",LOWER(TRIM(RawData[[#This Row],[Comments]]))="voicemail",LOWER(TRIM(RawData[[#This Row],[Comments]]))="call back later")),"Contact-only outcome does not support Warm status",""),IF(AND(LOWER(TRIM(RawData[[#This Row],[Status]]))="rnr",OR(ISNUMBER(SEARCH("requirement",LOWER(RawData[[#This Row],[Comments]]&" "&RawData[[#This Row],[Customer Requirement]]))),ISNUMBER(SEARCH("budget",LOWER(RawData[[#This Row],[Comments]]&" "&RawData[[#This Row],[Customer Requirement]]))),ISNUMBER(SEARCH("location",LOWER(RawData[[#This Row],[Comments]]&" "&RawData[[#This Row],[Customer Requirement]]))),ISNUMBER(SEARCH("purpose",LOWER(RawData[[#This Row],[Comments]]&" "&RawData[[#This Row],[Customer Requirement]]))),ISNUMBER(SEARCH("dimension",LOWER(RawData[[#This Row],[Comments]]&" "&RawData[[#This Row],[Customer Requirement]]))),ISNUMBER(SEARCH("sqft",LOWER(RawData[[#This Row],[Comments]]&" "&RawData[[#This Row],[Customer Requirement]]))))),"Requirements were captured while CRM status remains RNR",""),IF(AND(ISNUMBER(RawData[[#This Row],[Next Followup Date]]),RawData[[#This Row],[Next Followup Date]]<NOW(),OR(LOWER(TRIM(RawData[[#This Row],[Lead Status]]))="hot",LOWER(TRIM(RawData[[#This Row],[Lead Status]]))="prospect",LOWER(TRIM(RawData[[#This Row],[Lead Status]]))="warm")),"Follow-up date/time has passed for an active lead",""),IF(AND(LOWER(TRIM(RawData[[#This Row],[Location]]))="anekal",OR(ISNUMBER(SEARCH("ernika",LOWER(RawData[[#This Row],[Project Name]]))),ISNUMBER(SEARCH("enrika",LOWER(RawData[[#This Row],[Project Name]]))),ISNUMBER(SEARCH("exotica",LOWER(RawData[[#This Row],[Project Name]]))),ISNUMBER(SEARCH(" eka",LOWER(RawData[[#This Row],[Project Name]]))))),"Anekal is the project default; customer location was not captured",""))) -> Anekal is the project default; customer location was not captured | R11: =IF(RawData[[#This Row],[Mobile]]="","",_xlfn.TEXTJOIN(CHAR(10),TRUE,IF(AND(OR(LOWER(TRIM(RawData[[#This Row],[Lead Status]]))="cold",LOWER(TRIM(RawData[[#This Row],[Lead Status]]))="lost"),OR(ISNUMBER(SEARCH("visit",LOWER(TRIM(RawData[[#This Row],[Comments]])))),ISNUMBER(SEARCH("brochure",LOWER(TRIM(RawData[[#This Row],[Comments]])))),ISNUMBER(SEARCH("pricing",LOWER(TRIM(RawData[[#This Row],[Comments]])))),ISNUMBER(SEARCH("price",LOWER(TRIM(RawData[[#This Row],[Comments]])))),ISNUMBER(SEARCH("budget",LOWER(TRIM(RawData[[#This Row],[Comments]])))))),"Reclassify lead and schedule a documented follow-up",""),IF(AND(LOWER(TRIM(RawData[[#This Row],[Lead Status]]))="cold",OR(LOWER(TRIM(RawData[[#This Row],[Comments]]))="rnr",LOWER(TRIM(RawData[[#This Row],[Comments]]))="busy",LOWER(TRIM(RawData[[#This Row],[Comments]]))="out of network",LOWER(TRIM(RawData[[#This Row],[Comments]]))="outoff network",LOWER(TRIM(RawData[[#This Row],[Comments]]))="voice mail",LOWER(TRIM(RawData[[#This Row],[Comments]]))="voicemail")),"Change lead classification to RNR and retry contact",""),IF(AND(LOWER(TRIM(RawData[[#This Row],[Lead Status]]))="warm",OR(LOWER(TRIM(RawData[[#This Row],[Comments]]))="busy",LOWER(TRIM(RawData[[#This Row],[Comments]]))="voice mail",LOWER(TRIM(RawData[[#This Row],[Comments]]))="voicemail",LOWER(TRIM(RawData[[#This Row],[Comments]]))="call back later")),"Validate engagement before retaining Warm status",""),IF(AND(LOWER(TRIM(RawData[[#This Row],[Status]]))="rnr",OR(ISNUMBER(SEARCH("requirement",LOWER(RawData[[#This Row],[Comments]]&" "&RawData[[#This Row],[Customer Requirement]]))),ISNUMBER(SEARCH("budget",LOWER(RawData[[#This Row],[Comments]]&" "&RawData[[#This Row],[Customer Requirement]]))),ISNUMBER(SEARCH("location",LOWER(RawData[[#This Row],[Comments]]&" "&RawData[[#This Row],[Customer Requirement]]))),ISNUMBER(SEARCH("purpose",LOWER(RawData[[#This Row],[Comments]]&" "&RawData[[#This Row],[Customer Requirement]]))),ISNUMBER(SEARCH("dimension",LOWER(RawData[[#This Row],[Comments]]&" "&RawData[[#This Row],[Customer Requirement]]))),ISNUMBER(SEARCH("sqft",LOWER(RawData[[#This Row],[Comments]]&" "&RawData[[#This Row],[Customer Requirement]]))))),"Update CRM status to reflect the collected requirement",""),IF(AND(ISNUMBER(RawData[[#This Row],[Next Followup Date]]),RawData[[#This Row],[Next Followup Date]]<NOW(),OR(LOWER(TRIM(RawData[[#This Row],[Lead Status]]))="hot",LOWER(TRIM(RawData[[#This Row],[Lead Status]]))="prospect",LOWER(TRIM(RawData[[#This Row],[Lead Status]]))="warm")),"Contact immediately and set the next follow-up",""),IF(AND(LOWER(TRIM(RawData[[#This Row],[Location]]))="anekal",OR(ISNUMBER(SEARCH("ernika",LOWER(RawData[[#This Row],[Project Name]]))),ISNUMBER(SEARCH("enrika",LOWER(RawData[[#This Row],[Project Name]]))),ISNUMBER(SEARCH("exotica",LOWER(RawData[[#This Row],[Project Name]]))),ISNUMBER(SEARCH(" eka",LOWER(RawData[[#This Row],[Project Name]]))))),"Contact the customer and record their actual location",""))) -> Contact the customer and record their actual location | S11: =IF(RawData[[#This Row],[Error Flag]]=0,"",IF(OR(ISNUMBER(SEARCH("Wrong Lead Status",RawData[[#This Row],[Error Type]])),ISNUMBER(SEARCH("RNR Classification Error",RawData[[#This Row],[Error Type]])),ISNUMBER(SEARCH("Follow-up Error",RawData[[#This Row],[Error Type]]))),"Critical","Medium")) -> Medium | T11: =IF(RawData[[#This Row],[Error Flag]]=0,"Pass","Action Required ("&RawData[[#This Row],[Error Flag]]&IF(RawData[[#This Row],[Error Flag]]=1," error)"," errors)")) -> Action Required (1 error) | U11: =IF(RawData[[#This Row],[Mobile]]="",0,--(AND(OR(LOWER(TRIM(RawData[[#This Row],[Lead Status]]))="cold",LOWER(TRIM(RawData[[#This Row],[Lead Status]]))="lost"),OR(ISNUMBER(SEARCH("visit",LOWER(TRIM(RawData[[#This Row],[Comments]])))),ISNUMBER(SEARCH("brochure",LOWER(TRIM(RawData[[#This Row],[Comments]])))),ISNUMBER(SEARCH("pricing",LOWER(TRIM(RawData[[#This Row],[Comments]])))),ISNUMBER(SEARCH("price",LOWER(TRIM(RawData[[#This Row],[Comments]])))),ISNUMBER(SEARCH("budget",LOWER(TRIM(RawData[[#This Row],[Comments]])))))))+--(AND(LOWER(TRIM(RawData[[#This Row],[Lead Status]]))="cold",OR(LOWER(TRIM(RawData[[#This Row],[Comments]]))="rnr",LOWER(TRIM(RawData[[#This Row],[Comments]]))="busy",LOWER(TRIM(RawData[[#This Row],[Comments]]))="out of network",LOWER(TRIM(RawData[[#This Row],[Comments]]))="outoff network",LOWER(TRIM(RawData[[#This Row],[Comments]]))="voice mail",LOWER(TRIM(RawData[[#This Row],[Comments]]))="voicemail")))+--(AND(LOWER(TRIM(RawData[[#This Row],[Lead Status]]))="warm",OR(LOWER(TRIM(RawData[[#This Row],[Comments]]))="busy",LOWER(TRIM(RawData[[#This Row],[Comments]]))="voice mail",LOWER(TRIM(RawData[[#This Row],[Comments]]))="voicemail",LOWER(TRIM(RawData[[#This Row],[Comments]]))="call back later")))+--(AND(LOWER(TRIM(RawData[[#This Row],[Status]]))="rnr",OR(ISNUMBER(SEARCH("requirement",LOWER(RawData[[#This Row],[Comments]]&" "&RawData[[#This Row],[Customer Requirement]]))),ISNUMBER(SEARCH("budget",LOWER(RawData[[#This Row],[Comments]]&" "&RawData[[#This Row],[Customer Requirement]]))),ISNUMBER(SEARCH("location",LOWER(RawData[[#This Row],[Comments]]&" "&RawData[[#This Row],[Customer Requirement]]))),ISNUMBER(SEARCH("purpose",LOWER(RawData[[#This Row],[Comments]]&" "&RawData[[#This Row],[Customer Requirement]]))),ISNUMBER(SEARCH("dimension",LOWER(RawData[[#This Row],[Comments]]&" "&RawData[[#This Row],[Customer Requirement]]))),ISNUMBER(SEARCH("sqft",LOWER(RawData[[#This Row],[Comments]]&" "&RawData[[#This Row],[Customer Requirement]]))))))+--(AND(ISNUMBER(RawData[[#This Row],[Next Followup Date]]),RawData[[#This Row],[Next Followup Date]]<NOW(),OR(LOWER(TRIM(RawData[[#This Row],[Lead Status]]))="hot",LOWER(TRIM(RawData[[#This Row],[Lead Status]]))="prospect",LOWER(TRIM(RawData[[#This Row],[Lead Status]]))="warm")))+--(AND(LOWER(TRIM(RawData[[#This Row],[Location]]))="anekal",OR(ISNUMBER(SEARCH("ernika",LOWER(RawData[[#This Row],[Project Name]]))),ISNUMBER(SEARCH("enrika",LOWER(RawData[[#This Row],[Project Name]]))),ISNUMBER(SEARCH("exotica",LOWER(RawData[[#This Row],[Project Name]]))),ISNUMBER(SEARCH(" eka",LOWER(RawData[[#This Row],[Project Name]]))))))) -> 1 | W11: ='Telecaller Performance'!A15 | X11: {=IF(W11="",NA(),_xlfn.LET(_xlpm.v,SUBTOTAL(103,OFFSET(RawData[Mobile],ROW(RawData[Mobile])-MIN(ROW(RawData[Mobile])),0,1)),_xlpm.z,SUMPRODUCT(_xlpm.v,--(RawData[Telecaller Name]=W11)),IF(_xlpm.z=0,NA(),MAX(0,1-SUMPRODUCT(_xlpm.v,--(RawData[Telecaller Name]=W11),RawData[Error Flag])/_xlpm.z))))} -> #N/A | Z11: ='Telecaller Performance'!A15 | AA11: {=IF(Z11="",NA(),_xlfn.LET(_xlpm.v,SUBTOTAL(103,OFFSET(RawData[Mobile],ROW(RawData[Mobile])-MIN(ROW(RawData[Mobile])),0,1)),_xlpm.z,SUMPRODUCT(_xlpm.v,--(RawData[Telecaller Name]=Z11)),IF(_xlpm.z=0,NA(),SUMPRODUCT(_xlpm.v,--(RawData[Telecaller Name]=Z11),RawData[Error Flag]))))} -> #N/A | AF11: {=IFERROR(INDEX(_xlfn._xlws.SORT(_xlfn.UNIQUE(_xlfn._xlws.FILTER(RawData[Project Name],RawData[Project Name]<>""))),ROWS(AF$2:AF11)),"")} | AG11: {=IF(AF11="",NA(),_xlfn.LET(_xlpm.v,SUBTOTAL(103,OFFSET(RawData[Mobile],ROW(RawData[Mobile])-MIN(ROW(RawData[Mobile])),0,1)),_xlpm.z,SUMPRODUCT(_xlpm.v,--(RawData[Project Name]=AF11)),IF(_xlpm.z=0,NA(),SUMPRODUCT(_xlpm.v,--(RawData[Project Name]=AF11),RawData[Error Flag]))))} -> #N/A
A12: Guru Punvaanii Ernika | B12: 8123042533 | C12: Vinutha M1 | D12: 46253 | E12: Cold | F12: Rnr | G12: 46256.465 | H12: Anekal | I12: -1 | J12: Interested | K12: RNR | L12: rnr | M12: Online Portal | N12: 99 Acres | O12: 1 | P12: =IF(RawData[[#This Row],[Mobile]]="","",_xlfn.TEXTJOIN(" | ",TRUE,IF(AND(OR(LOWER(TRIM(RawData[[#This Row],[Lead Status]]))="cold",LOWER(TRIM(RawData[[#This Row],[Lead Status]]))="lost"),OR(ISNUMBER(SEARCH("visit",LOWER(TRIM(RawData[[#This Row],[Comments]])))),ISNUMBER(SEARCH("brochure",LOWER(TRIM(RawData[[#This Row],[Comments]])))),ISNUMBER(SEARCH("pricing",LOWER(TRIM(RawData[[#This Row],[Comments]])))),ISNUMBER(SEARCH("price",LOWER(TRIM(RawData[[#This Row],[Comments]])))),ISNUMBER(SEARCH("budget",LOWER(TRIM(RawData[[#This Row],[Comments]])))))),"Wrong Lead Status",""),IF(AND(LOWER(TRIM(RawData[[#This Row],[Lead Status]]))="cold",OR(LOWER(TRIM(RawData[[#This Row],[Comments]]))="rnr",LOWER(TRIM(RawData[[#This Row],[Comments]]))="busy",LOWER(TRIM(RawData[[#This Row],[Comments]]))="out of network",LOWER(TRIM(RawData[[#This Row],[Comments]]))="outoff network",LOWER(TRIM(RawData[[#This Row],[Comments]]))="voice mail",LOWER(TRIM(RawData[[#This Row],[Comments]]))="voicemail")),"RNR Classification Error",""),IF(AND(LOWER(TRIM(RawData[[#This Row],[Lead Status]]))="warm",OR(LOWER(TRIM(RawData[[#This Row],[Comments]]))="busy",LOWER(TRIM(RawData[[#This Row],[Comments]]))="voice mail",LOWER(TRIM(RawData[[#This Row],[Comments]]))="voicemail",LOWER(TRIM(RawData[[#This Row],[Comments]]))="call back later")),"Warm Status Mismatch",""),IF(AND(LOWER(TRIM(RawData[[#This Row],[Status]]))="rnr",OR(ISNUMBER(SEARCH("requirement",LOWER(RawData[[#This Row],[Comments]]&" "&RawData[[#This Row],[Customer Requirement]]))),ISNUMBER(SEARCH("budget",LOWER(RawData[[#This Row],[Comments]]&" "&RawData[[#This Row],[Customer Requirement]]))),ISNUMBER(SEARCH("location",LOWER(RawData[[#This Row],[Comments]]&" "&RawData[[#This Row],[Customer Requirement]]))),ISNUMBER(SEARCH("purpose",LOWER(RawData[[#This Row],[Comments]]&" "&RawData[[#This Row],[Customer Requirement]]))),ISNUMBER(SEARCH("dimension",LOWER(RawData[[#This Row],[Comments]]&" "&RawData[[#This Row],[Customer Requirement]]))),ISNUMBER(SEARCH("sqft",LOWER(RawData[[#This Row],[Comments]]&" "&RawData[[#This Row],[Customer Requirement]]))))),"CRM Status Mismatch",""),IF(AND(ISNUMBER(RawData[[#This Row],[Next Followup Date]]),RawData[[#This Row],[Next Followup Date]]<NOW(),OR(LOWER(TRIM(RawData[[#This Row],[Lead Status]]))="hot",LOWER(TRIM(RawData[[#This Row],[Lead Status]]))="prospect",LOWER(TRIM(RawData[[#This Row],[Lead Status]]))="warm")),"Follow-up Error",""),IF(AND(LOWER(TRIM(RawData[[#This Row],[Location]]))="anekal",OR(ISNUMBER(SEARCH("ernika",LOWER(RawData[[#This Row],[Project Name]]))),ISNUMBER(SEARCH("enrika",LOWER(RawData[[#This Row],[Project Name]]))),ISNUMBER(SEARCH("exotica",LOWER(RawData[[#This Row],[Project Name]]))),ISNUMBER(SEARCH(" eka",LOWER(RawData[[#This Row],[Project Name]]))))),"Customer Location Not Captured",""))) -> RNR Classification Error | Customer Location Not Captured | Q12: =IF(RawData[[#This Row],[Mobile]]="","",_xlfn.TEXTJOIN(CHAR(10),TRUE,IF(AND(OR(LOWER(TRIM(RawData[[#This Row],[Lead Status]]))="cold",LOWER(TRIM(RawData[[#This Row],[Lead Status]]))="lost"),OR(ISNUMBER(SEARCH("visit",LOWER(TRIM(RawData[[#This Row],[Comments]])))),ISNUMBER(SEARCH("brochure",LOWER(TRIM(RawData[[#This Row],[Comments]])))),ISNUMBER(SEARCH("pricing",LOWER(TRIM(RawData[[#This Row],[Comments]])))),ISNUMBER(SEARCH("price",LOWER(TRIM(RawData[[#This Row],[Comments]])))),ISNUMBER(SEARCH("budget",LOWER(TRIM(RawData[[#This Row],[Comments]])))))),"Engagement intent conflicts with Cold/Lost status",""),IF(AND(LOWER(TRIM(RawData[[#This Row],[Lead Status]]))="cold",OR(LOWER(TRIM(RawData[[#This Row],[Comments]]))="rnr",LOWER(TRIM(RawData[[#This Row],[Comments]]))="busy",LOWER(TRIM(RawData[[#This Row],[Comments]]))="out of network",LOWER(TRIM(RawData[[#This Row],[Comments]]))="outoff network",LOWER(TRIM(RawData[[#This Row],[Comments]]))="voice mail",LOWER(TRIM(RawData[[#This Row],[Comments]]))="voicemail")),"Contact outcome should remain RNR rather than Cold",""),IF(AND(LOWER(TRIM(RawData[[#This Row],[Lead Status]]))="warm",OR(LOWER(TRIM(RawData[[#This Row],[Comments]]))="busy",LOWER(TRIM(RawData[[#This Row],[Comments]]))="voice mail",LOWER(TRIM(RawData[[#This Row],[Comments]]))="voicemail",LOWER(TRIM(RawData[[#This Row],[Comments]]))="call back later")),"Contact-only outcome does not support Warm status",""),IF(AND(LOWER(TRIM(RawData[[#This Row],[Status]]))="rnr",OR(ISNUMBER(SEARCH("requirement",LOWER(RawData[[#This Row],[Comments]]&" "&RawData[[#This Row],[Customer Requirement]]))),ISNUMBER(SEARCH("budget",LOWER(RawData[[#This Row],[Comments]]&" "&RawData[[#This Row],[Customer Requirement]]))),ISNUMBER(SEARCH("location",LOWER(RawData[[#This Row],[Comments]]&" "&RawData[[#This Row],[Customer Requirement]]))),ISNUMBER(SEARCH("purpose",LOWER(RawData[[#This Row],[Comments]]&" "&RawData[[#This Row],[Customer Requirement]]))),ISNUMBER(SEARCH("dimension",LOWER(RawData[[#This Row],[Comments]]&" "&RawData[[#This Row],[Customer Requirement]]))),ISNUMBER(SEARCH("sqft",LOWER(RawData[[#This Row],[Comments]]&" "&RawData[[#This Row],[Customer Requirement]]))))),"Requirements were captured while CRM status remains RNR",""),IF(AND(ISNUMBER(RawData[[#This Row],[Next Followup Date]]),RawData[[#This Row],[Next Followup Date]]<NOW(),OR(LOWER(TRIM(RawData[[#This Row],[Lead Status]]))="hot",LOWER(TRIM(RawData[[#This Row],[Lead Status]]))="prospect",LOWER(TRIM(RawData[[#This Row],[Lead Status]]))="warm")),"Follow-up date/time has passed for an active lead",""),IF(AND(LOWER(TRIM(RawData[[#This Row],[Location]]))="anekal",OR(ISNUMBER(SEARCH("ernika",LOWER(RawData[[#This Row],[Project Name]]))),ISNUMBER(SEARCH("enrika",LOWER(RawData[[#This Row],[Project Name]]))),ISNUMBER(SEARCH("exotica",LOWER(RawData[[#This Row],[Project Name]]))),ISNUMBER(SEARCH(" eka",LOWER(RawData[[#This Row],[Project Name]]))))),"Anekal is the project default; customer location was not captured",""))) -> Contact outcome should remain RNR rather than Cold Anekal is the project default; customer location was not captured | R12: =IF(RawData[[#This Row],[Mobile]]="","",_xlfn.TEXTJOIN(CHAR(10),TRUE,IF(AND(OR(LOWER(TRIM(RawData[[#This Row],[Lead Status]]))="cold",LOWER(TRIM(RawData[[#This Row],[Lead Status]]))="lost"),OR(ISNUMBER(SEARCH("visit",LOWER(TRIM(RawData[[#This Row],[Comments]])))),ISNUMBER(SEARCH("brochure",LOWER(TRIM(RawData[[#This Row],[Comments]])))),ISNUMBER(SEARCH("pricing",LOWER(TRIM(RawData[[#This Row],[Comments]])))),ISNUMBER(SEARCH("price",LOWER(TRIM(RawData[[#This Row],[Comments]])))),ISNUMBER(SEARCH("budget",LOWER(TRIM(RawData[[#This Row],[Comments]])))))),"Reclassify lead and schedule a documented follow-up",""),IF(AND(LOWER(TRIM(RawData[[#This Row],[Lead Status]]))="cold",OR(LOWER(TRIM(RawData[[#This Row],[Comments]]))="rnr",LOWER(TRIM(RawData[[#This Row],[Comments]]))="busy",LOWER(TRIM(RawData[[#This Row],[Comments]]))="out of network",LOWER(TRIM(RawData[[#This Row],[Comments]]))="outoff network",LOWER(TRIM(RawData[[#This Row],[Comments]]))="voice mail",LOWER(TRIM(RawData[[#This Row],[Comments]]))="voicemail")),"Change lead classification to RNR and retry contact",""),IF(AND(LOWER(TRIM(RawData[[#This Row],[Lead Status]]))="warm",OR(LOWER(TRIM(RawData[[#This Row],[Comments]]))="busy",LOWER(TRIM(RawData[[#This Row],[Comments]]))="voice mail",LOWER(TRIM(RawData[[#This Row],[Comments]]))="voicemail",LOWER(TRIM(RawData[[#This Row],[Comments]]))="call back later")),"Validate engagement before retaining Warm status",""),IF(AND(LOWER(TRIM(RawData[[#This Row],[Status]]))="rnr",OR(ISNUMBER(SEARCH("requirement",LOWER(RawData[[#This Row],[Comments]]&" "&RawData[[#This Row],[Customer Requirement]]))),ISNUMBER(SEARCH("budget",LOWER(RawData[[#This Row],[Comments]]&" "&RawData[[#This Row],[Customer Requirement]]))),ISNUMBER(SEARCH("location",LOWER(RawData[[#This Row],[Comments]]&" "&RawData[[#This Row],[Customer Requirement]]))),ISNUMBER(SEARCH("purpose",LOWER(RawData[[#This Row],[Comments]]&" "&RawData[[#This Row],[Customer Requirement]]))),ISNUMBER(SEARCH("dimension",LOWER(RawData[[#This Row],[Comments]]&" "&RawData[[#This Row],[Customer Requirement]]))),ISNUMBER(SEARCH("sqft",LOWER(RawData[[#This Row],[Comments]]&" "&RawData[[#This Row],[Customer Requirement]]))))),"Update CRM status to reflect the collected requirement",""),IF(AND(ISNUMBER(RawData[[#This Row],[Next Followup Date]]),RawData[[#This Row],[Next Followup Date]]<NOW(),OR(LOWER(TRIM(RawData[[#This Row],[Lead Status]]))="hot",LOWER(TRIM(RawData[[#This Row],[Lead Status]]))="prospect",LOWER(TRIM(RawData[[#This Row],[Lead Status]]))="warm")),"Contact immediately and set the next follow-up",""),IF(AND(LOWER(TRIM(RawData[[#This Row],[Location]]))="anekal",OR(ISNUMBER(SEARCH("ernika",LOWER(RawData[[#This Row],[Project Name]]))),ISNUMBER(SEARCH("enrika",LOWER(RawData[[#This Row],[Project Name]]))),ISNUMBER(SEARCH("exotica",LOWER(RawData[[#This Row],[Project Name]]))),ISNUMBER(SEARCH(" eka",LOWER(RawData[[#This Row],[Project Name]]))))),"Contact the customer and record their actual location",""))) -> Change lead classification to RNR and retry contact Contact the customer and record their actual location | S12: =IF(RawData[[#This Row],[Error Flag]]=0,"",IF(OR(ISNUMBER(SEARCH("Wrong Lead Status",RawData[[#This Row],[Error Type]])),ISNUMBER(SEARCH("RNR Classification Error",RawData[[#This Row],[Error Type]])),ISNUMBER(SEARCH("Follow-up Error",RawData[[#This Row],[Error Type]]))),"Critical","Medium")) -> Critical | T12: =IF(RawData[[#This Row],[Error Flag]]=0,"Pass","Action Required ("&RawData[[#This Row],[Error Flag]]&IF(RawData[[#This Row],[Error Flag]]=1," error)"," errors)")) -> Action Required (2 errors) | U12: =IF(RawData[[#This Row],[Mobile]]="",0,--(AND(OR(LOWER(TRIM(RawData[[#This Row],[Lead Status]]))="cold",LOWER(TRIM(RawData[[#This Row],[Lead Status]]))="lost"),OR(ISNUMBER(SEARCH("visit",LOWER(TRIM(RawData[[#This Row],[Comments]])))),ISNUMBER(SEARCH("brochure",LOWER(TRIM(RawData[[#This Row],[Comments]])))),ISNUMBER(SEARCH("pricing",LOWER(TRIM(RawData[[#This Row],[Comments]])))),ISNUMBER(SEARCH("price",LOWER(TRIM(RawData[[#This Row],[Comments]])))),ISNUMBER(SEARCH("budget",LOWER(TRIM(RawData[[#This Row],[Comments]])))))))+--(AND(LOWER(TRIM(RawData[[#This Row],[Lead Status]]))="cold",OR(LOWER(TRIM(RawData[[#This Row],[Comments]]))="rnr",LOWER(TRIM(RawData[[#This Row],[Comments]]))="busy",LOWER(TRIM(RawData[[#This Row],[Comments]]))="out of network",LOWER(TRIM(RawData[[#This Row],[Comments]]))="outoff network",LOWER(TRIM(RawData[[#This Row],[Comments]]))="voice mail",LOWER(TRIM(RawData[[#This Row],[Comments]]))="voicemail")))+--(AND(LOWER(TRIM(RawData[[#This Row],[Lead Status]]))="warm",OR(LOWER(TRIM(RawData[[#This Row],[Comments]]))="busy",LOWER(TRIM(RawData[[#This Row],[Comments]]))="voice mail",LOWER(TRIM(RawData[[#This Row],[Comments]]))="voicemail",LOWER(TRIM(RawData[[#This Row],[Comments]]))="call back later")))+--(AND(LOWER(TRIM(RawData[[#This Row],[Status]]))="rnr",OR(ISNUMBER(SEARCH("requirement",LOWER(RawData[[#This Row],[Comments]]&" "&RawData[[#This Row],[Customer Requirement]]))),ISNUMBER(SEARCH("budget",LOWER(RawData[[#This Row],[Comments]]&" "&RawData[[#This Row],[Customer Requirement]]))),ISNUMBER(SEARCH("location",LOWER(RawData[[#This Row],[Comments]]&" "&RawData[[#This Row],[Customer Requirement]]))),ISNUMBER(SEARCH("purpose",LOWER(RawData[[#This Row],[Comments]]&" "&RawData[[#This Row],[Customer Requirement]]))),ISNUMBER(SEARCH("dimension",LOWER(RawData[[#This Row],[Comments]]&" "&RawData[[#This Row],[Customer Requirement]]))),ISNUMBER(SEARCH("sqft",LOWER(RawData[[#This Row],[Comments]]&" "&RawData[[#This Row],[Customer Requirement]]))))))+--(AND(ISNUMBER(RawData[[#This Row],[Next Followup Date]]),RawData[[#This Row],[Next Followup Date]]<NOW(),OR(LOWER(TRIM(RawData[[#This Row],[Lead Status]]))="hot",LOWER(TRIM(RawData[[#This Row],[Lead Status]]))="prospect",LOWER(TRIM(RawData[[#This Row],[Lead Status]]))="warm")))+--(AND(LOWER(TRIM(RawData[[#This Row],[Location]]))="anekal",OR(ISNUMBER(SEARCH("ernika",LOWER(RawData[[#This Row],[Project Name]]))),ISNUMBER(SEARCH("enrika",LOWER(RawData[[#This Row],[Project Name]]))),ISNUMBER(SEARCH("exotica",LOWER(RawData[[#This Row],[Project Name]]))),ISNUMBER(SEARCH(" eka",LOWER(RawData[[#This Row],[Project Name]]))))))) -> 2 | W12: ='Telecaller Performance'!A16 | X12: {=IF(W12="",NA(),_xlfn.LET(_xlpm.v,SUBTOTAL(103,OFFSET(RawData[Mobile],ROW(RawData[Mobile])-MIN(ROW(RawData[Mobile])),0,1)),_xlpm.z,SUMPRODUCT(_xlpm.v,--(RawData[Telecaller Name]=W12)),IF(_xlpm.z=0,NA(),MAX(0,1-SUMPRODUCT(_xlpm.v,--(RawData[Telecaller Name]=W12),RawData[Error Flag])/_xlpm.z))))} -> #N/A | Z12: ='Telecaller Performance'!A16 | AA12: {=IF(Z12="",NA(),_xlfn.LET(_xlpm.v,SUBTOTAL(103,OFFSET(RawData[Mobile],ROW(RawData[Mobile])-MIN(ROW(RawData[Mobile])),0,1)),_xlpm.z,SUMPRODUCT(_xlpm.v,--(RawData[Telecaller Name]=Z12)),IF(_xlpm.z=0,NA(),SUMPRODUCT(_xlpm.v,--(RawData[Telecaller Name]=Z12),RawData[Error Flag]))))} -> #N/A | AF12: {=IFERROR(INDEX(_xlfn._xlws.SORT(_xlfn.UNIQUE(_xlfn._xlws.FILTER(RawData[Project Name],RawData[Project Name]<>""))),ROWS(AF$2:AF12)),"")} | AG12: {=IF(AF12="",NA(),_xlfn.LET(_xlpm.v,SUBTOTAL(103,OFFSET(RawData[Mobile],ROW(RawData[Mobile])-MIN(ROW(RawData[Mobile])),0,1)),_xlpm.z,SUMPRODUCT(_xlpm.v,--(RawData[Project Name]=AF12)),IF(_xlpm.z=0,NA(),SUMPRODUCT(_xlpm.v,--(RawData[Project Name]=AF12),RawData[Error Flag]))))} -> #N/A
A13: Guru Punvaanii Ernika | B13: 8660592160 | C13: Vinutha M1 | D13: 46253 | E13: Prospect | F13: Visited | G13: 46256.676 | H13: Anekal | I13: -1 | J13: Interested | K13: In Progress | L13: details shared in whatsapp he is Looking for 30*40 dimension for investment purpose and end use both located in KR puram budget is uptp 1cr including construction hr is looking he have plan to construct g+2 building asked about permission and he needs some builder reference too he will visit on wednesday with his wife | M13: MCube | N13: Google Ads | O13: 1 | P13: =IF(RawData[[#This Row],[Mobile]]="","",_xlfn.TEXTJOIN(" | ",TRUE,IF(AND(OR(LOWER(TRIM(RawData[[#This Row],[Lead Status]]))="cold",LOWER(TRIM(RawData[[#This Row],[Lead Status]]))="lost"),OR(ISNUMBER(SEARCH("visit",LOWER(TRIM(RawData[[#This Row],[Comments]])))),ISNUMBER(SEARCH("brochure",LOWER(TRIM(RawData[[#This Row],[Comments]])))),ISNUMBER(SEARCH("pricing",LOWER(TRIM(RawData[[#This Row],[Comments]])))),ISNUMBER(SEARCH("price",LOWER(TRIM(RawData[[#This Row],[Comments]])))),ISNUMBER(SEARCH("budget",LOWER(TRIM(RawData[[#This Row],[Comments]])))))),"Wrong Lead Status",""),IF(AND(LOWER(TRIM(RawData[[#This Row],[Lead Status]]))="cold",OR(LOWER(TRIM(RawData[[#This Row],[Comments]]))="rnr",LOWER(TRIM(RawData[[#This Row],[Comments]]))="busy",LOWER(TRIM(RawData[[#This Row],[Comments]]))="out of network",LOWER(TRIM(RawData[[#This Row],[Comments]]))="outoff network",LOWER(TRIM(RawData[[#This Row],[Comments]]))="voice mail",LOWER(TRIM(RawData[[#This Row],[Comments]]))="voicemail")),"RNR Classification Error",""),IF(AND(LOWER(TRIM(RawData[[#This Row],[Lead Status]]))="warm",OR(LOWER(TRIM(RawData[[#This Row],[Comments]]))="busy",LOWER(TRIM(RawData[[#This Row],[Comments]]))="voice mail",LOWER(TRIM(RawData[[#This Row],[Comments]]))="voicemail",LOWER(TRIM(RawData[[#This Row],[Comments]]))="call back later")),"Warm Status Mismatch",""),IF(AND(LOWER(TRIM(RawData[[#This Row],[Status]]))="rnr",OR(ISNUMBER(SEARCH("requirement",LOWER(RawData[[#This Row],[Comments]]&" "&RawData[[#This Row],[Customer Requirement]]))),ISNUMBER(SEARCH("budget",LOWER(RawData[[#This Row],[Comments]]&" "&RawData[[#This Row],[Customer Requirement]]))),ISNUMBER(SEARCH("location",LOWER(RawData[[#This Row],[Comments]]&" "&RawData[[#This Row],[Customer Requirement]]))),ISNUMBER(SEARCH("purpose",LOWER(RawData[[#This Row],[Comments]]&" "&RawData[[#This Row],[Customer Requirement]]))),ISNUMBER(SEARCH("dimension",LOWER(RawData[[#This Row],[Comments]]&" "&RawData[[#This Row],[Customer Requirement]]))),ISNUMBER(SEARCH("sqft",LOWER(RawData[[#This Row],[Comments]]&" "&RawData[[#This Row],[Customer Requirement]]))))),"CRM Status Mismatch",""),IF(AND(ISNUMBER(RawData[[#This Row],[Next Followup Date]]),RawData[[#This Row],[Next Followup Date]]<NOW(),OR(LOWER(TRIM(RawData[[#This Row],[Lead Status]]))="hot",LOWER(TRIM(RawData[[#This Row],[Lead Status]]))="prospect",LOWER(TRIM(RawData[[#This Row],[Lead Status]]))="warm")),"Follow-up Error",""),IF(AND(LOWER(TRIM(RawData[[#This Row],[Location]]))="anekal",OR(ISNUMBER(SEARCH("ernika",LOWER(RawData[[#This Row],[Project Name]]))),ISNUMBER(SEARCH("enrika",LOWER(RawData[[#This Row],[Project Name]]))),ISNUMBER(SEARCH("exotica",LOWER(RawData[[#This Row],[Project Name]]))),ISNUMBER(SEARCH(" eka",LOWER(RawData[[#This Row],[Project Name]]))))),"Customer Location Not Captured",""))) -> Customer Location Not Captured | Q13: =IF(RawData[[#This Row],[Mobile]]="","",_xlfn.TEXTJOIN(CHAR(10),TRUE,IF(AND(OR(LOWER(TRIM(RawData[[#This Row],[Lead Status]]))="cold",LOWER(TRIM(RawData[[#This Row],[Lead Status]]))="lost"),OR(ISNUMBER(SEARCH("visit",LOWER(TRIM(RawData[[#This Row],[Comments]])))),ISNUMBER(SEARCH("brochure",LOWER(TRIM(RawData[[#This Row],[Comments]])))),ISNUMBER(SEARCH("pricing",LOWER(TRIM(RawData[[#This Row],[Comments]])))),ISNUMBER(SEARCH("price",LOWER(TRIM(RawData[[#This Row],[Comments]])))),ISNUMBER(SEARCH("budget",LOWER(TRIM(RawData[[#This Row],[Comments]])))))),"Engagement intent conflicts with Cold/Lost status",""),IF(AND(LOWER(TRIM(RawData[[#This Row],[Lead Status]]))="cold",OR(LOWER(TRIM(RawData[[#This Row],[Comments]]))="rnr",LOWER(TRIM(RawData[[#This Row],[Comments]]))="busy",LOWER(TRIM(RawData[[#This Row],[Comments]]))="out of network",LOWER(TRIM(RawData[[#This Row],[Comments]]))="outoff network",LOWER(TRIM(RawData[[#This Row],[Comments]]))="voice mail",LOWER(TRIM(RawData[[#This Row],[Comments]]))="voicemail")),"Contact outcome should remain RNR rather than Cold",""),IF(AND(LOWER(TRIM(RawData[[#This Row],[Lead Status]]))="warm",OR(LOWER(TRIM(RawData[[#This Row],[Comments]]))="busy",LOWER(TRIM(RawData[[#This Row],[Comments]]))="voice mail",LOWER(TRIM(RawData[[#This Row],[Comments]]))="voicemail",LOWER(TRIM(RawData[[#This Row],[Comments]]))="call back later")),"Contact-only outcome does not support Warm status",""),IF(AND(LOWER(TRIM(RawData[[#This Row],[Status]]))="rnr",OR(ISNUMBER(SEARCH("requirement",LOWER(RawData[[#This Row],[Comments]]&" "&RawData[[#This Row],[Customer Requirement]]))),ISNUMBER(SEARCH("budget",LOWER(RawData[[#This Row],[Comments]]&" "&RawData[[#This Row],[Customer Requirement]]))),ISNUMBER(SEARCH("location",LOWER(RawData[[#This Row],[Comments]]&" "&RawData[[#This Row],[Customer Requirement]]))),ISNUMBER(SEARCH("purpose",LOWER(RawData[[#This Row],[Comments]]&" "&RawData[[#This Row],[Customer Requirement]]))),ISNUMBER(SEARCH("dimension",LOWER(RawData[[#This Row],[Comments]]&" "&RawData[[#This Row],[Customer Requirement]]))),ISNUMBER(SEARCH("sqft",LOWER(RawData[[#This Row],[Comments]]&" "&RawData[[#This Row],[Customer Requirement]]))))),"Requirements were captured while CRM status remains RNR",""),IF(AND(ISNUMBER(RawData[[#This Row],[Next Followup Date]]),RawData[[#This Row],[Next Followup Date]]<NOW(),OR(LOWER(TRIM(RawData[[#This Row],[Lead Status]]))="hot",LOWER(TRIM(RawData[[#This Row],[Lead Status]]))="prospect",LOWER(TRIM(RawData[[#This Row],[Lead Status]]))="warm")),"Follow-up date/time has passed for an active lead",""),IF(AND(LOWER(TRIM(RawData[[#This Row],[Location]]))="anekal",OR(ISNUMBER(SEARCH("ernika",LOWER(RawData[[#This Row],[Project Name]]))),ISNUMBER(SEARCH("enrika",LOWER(RawData[[#This Row],[Project Name]]))),ISNUMBER(SEARCH("exotica",LOWER(RawData[[#This Row],[Project Name]]))),ISNUMBER(SEARCH(" eka",LOWER(RawData[[#This Row],[Project Name]]))))),"Anekal is the project default; customer location was not captured",""))) -> Anekal is the project default; customer location was not captured | R13: =IF(RawData[[#This Row],[Mobile]]="","",_xlfn.TEXTJOIN(CHAR(10),TRUE,IF(AND(OR(LOWER(TRIM(RawData[[#This Row],[Lead Status]]))="cold",LOWER(TRIM(RawData[[#This Row],[Lead Status]]))="lost"),OR(ISNUMBER(SEARCH("visit",LOWER(TRIM(RawData[[#This Row],[Comments]])))),ISNUMBER(SEARCH("brochure",LOWER(TRIM(RawData[[#This Row],[Comments]])))),ISNUMBER(SEARCH("pricing",LOWER(TRIM(RawData[[#This Row],[Comments]])))),ISNUMBER(SEARCH("price",LOWER(TRIM(RawData[[#This Row],[Comments]])))),ISNUMBER(SEARCH("budget",LOWER(TRIM(RawData[[#This Row],[Comments]])))))),"Reclassify lead and schedule a documented follow-up",""),IF(AND(LOWER(TRIM(RawData[[#This Row],[Lead Status]]))="cold",OR(LOWER(TRIM(RawData[[#This Row],[Comments]]))="rnr",LOWER(TRIM(RawData[[#This Row],[Comments]]))="busy",LOWER(TRIM(RawData[[#This Row],[Comments]]))="out of network",LOWER(TRIM(RawData[[#This Row],[Comments]]))="outoff network",LOWER(TRIM(RawData[[#This Row],[Comments]]))="voice mail",LOWER(TRIM(RawData[[#This Row],[Comments]]))="voicemail")),"Change lead classification to RNR and retry contact",""),IF(AND(LOWER(TRIM(RawData[[#This Row],[Lead Status]]))="warm",OR(LOWER(TRIM(RawData[[#This Row],[Comments]]))="busy",LOWER(TRIM(RawData[[#This Row],[Comments]]))="voice mail",LOWER(TRIM(RawData[[#This Row],[Comments]]))="voicemail",LOWER(TRIM(RawData[[#This Row],[Comments]]))="call back later")),"Validate engagement before retaining Warm status",""),IF(AND(LOWER(TRIM(RawData[[#This Row],[Status]]))="rnr",OR(ISNUMBER(SEARCH("requirement",LOWER(RawData[[#This Row],[Comments]]&" "&RawData[[#This Row],[Customer Requirement]]))),ISNUMBER(SEARCH("budget",LOWER(RawData[[#This Row],[Comments]]&" "&RawData[[#This Row],[Customer Requirement]]))),ISNUMBER(SEARCH("location",LOWER(RawData[[#This Row],[Comments]]&" "&RawData[[#This Row],[Customer Requirement]]))),ISNUMBER(SEARCH("purpose",LOWER(RawData[[#This Row],[Comments]]&" "&RawData[[#This Row],[Customer Requirement]]))),ISNUMBER(SEARCH("dimension",LOWER(RawData[[#This Row],[Comments]]&" "&RawData[[#This Row],[Customer Requirement]]))),ISNUMBER(SEARCH("sqft",LOWER(RawData[[#This Row],[Comments]]&" "&RawData[[#This Row],[Customer Requirement]]))))),"Update CRM status to reflect the collected requirement",""),IF(AND(ISNUMBER(RawData[[#This Row],[Next Followup Date]]),RawData[[#This Row],[Next Followup Date]]<NOW(),OR(LOWER(TRIM(RawData[[#This Row],[Lead Status]]))="hot",LOWER(TRIM(RawData[[#This Row],[Lead Status]]))="prospect",LOWER(TRIM(RawData[[#This Row],[Lead Status]]))="warm")),"Contact immediately and set the next follow-up",""),IF(AND(LOWER(TRIM(RawData[[#This Row],[Location]]))="anekal",OR(ISNUMBER(SEARCH("ernika",LOWER(RawData[[#This Row],[Project Name]]))),ISNUMBER(SEARCH("enrika",LOWER(RawData[[#This Row],[Project Name]]))),ISNUMBER(SEARCH("exotica",LOWER(RawData[[#This Row],[Project Name]]))),ISNUMBER(SEARCH(" eka",LOWER(RawData[[#This Row],[Project Name]]))))),"Contact the customer and record their actual location",""))) -> Contact the customer and record their actual location | S13: =IF(RawData[[#This Row],[Error Flag]]=0,"",IF(OR(ISNUMBER(SEARCH("Wrong Lead Status",RawData[[#This Row],[Error Type]])),ISNUMBER(SEARCH("RNR Classification Error",RawData[[#This Row],[Error Type]])),ISNUMBER(SEARCH("Follow-up Error",RawData[[#This Row],[Error Type]]))),"Critical","Medium")) -> Medium | T13: =IF(RawData[[#This Row],[Error Flag]]=0,"Pass","Action Required ("&RawData[[#This Row],[Error Flag]]&IF(RawData[[#This Row],[Error Flag]]=1," error)"," errors)")) -> Action Required (1 error) | U13: =IF(RawData[[#This Row],[Mobile]]="",0,--(AND(OR(LOWER(TRIM(RawData[[#This Row],[Lead Status]]))="cold",LOWER(TRIM(RawData[[#This Row],[Lead Status]]))="lost"),OR(ISNUMBER(SEARCH("visit",LOWER(TRIM(RawData[[#This Row],[Comments]])))),ISNUMBER(SEARCH("brochure",LOWER(TRIM(RawData[[#This Row],[Comments]])))),ISNUMBER(SEARCH("pricing",LOWER(TRIM(RawData[[#This Row],[Comments]])))),ISNUMBER(SEARCH("price",LOWER(TRIM(RawData[[#This Row],[Comments]])))),ISNUMBER(SEARCH("budget",LOWER(TRIM(RawData[[#This Row],[Comments]])))))))+--(AND(LOWER(TRIM(RawData[[#This Row],[Lead Status]]))="cold",OR(LOWER(TRIM(RawData[[#This Row],[Comments]]))="rnr",LOWER(TRIM(RawData[[#This Row],[Comments]]))="busy",LOWER(TRIM(RawData[[#This Row],[Comments]]))="out of network",LOWER(TRIM(RawData[[#This Row],[Comments]]))="outoff network",LOWER(TRIM(RawData[[#This Row],[Comments]]))="voice mail",LOWER(TRIM(RawData[[#This Row],[Comments]]))="voicemail")))+--(AND(LOWER(TRIM(RawData[[#This Row],[Lead Status]]))="warm",OR(LOWER(TRIM(RawData[[#This Row],[Comments]]))="busy",LOWER(TRIM(RawData[[#This Row],[Comments]]))="voice mail",LOWER(TRIM(RawData[[#This Row],[Comments]]))="voicemail",LOWER(TRIM(RawData[[#This Row],[Comments]]))="call back later")))+--(AND(LOWER(TRIM(RawData[[#This Row],[Status]]))="rnr",OR(ISNUMBER(SEARCH("requirement",LOWER(RawData[[#This Row],[Comments]]&" "&RawData[[#This Row],[Customer Requirement]]))),ISNUMBER(SEARCH("budget",LOWER(RawData[[#This Row],[Comments]]&" "&RawData[[#This Row],[Customer Requirement]]))),ISNUMBER(SEARCH("location",LOWER(RawData[[#This Row],[Comments]]&" "&RawData[[#This Row],[Customer Requirement]]))),ISNUMBER(SEARCH("purpose",LOWER(RawData[[#This Row],[Comments]]&" "&RawData[[#This Row],[Customer Requirement]]))),ISNUMBER(SEARCH("dimension",LOWER(RawData[[#This Row],[Comments]]&" "&RawData[[#This Row],[Customer Requirement]]))),ISNUMBER(SEARCH("sqft",LOWER(RawData[[#This Row],[Comments]]&" "&RawData[[#This Row],[Customer Requirement]]))))))+--(AND(ISNUMBER(RawData[[#This Row],[Next Followup Date]]),RawData[[#This Row],[Next Followup Date]]<NOW(),OR(LOWER(TRIM(RawData[[#This Row],[Lead Status]]))="hot",LOWER(TRIM(RawData[[#This Row],[Lead Status]]))="prospect",LOWER(TRIM(RawData[[#This Row],[Lead Status]]))="warm")))+--(AND(LOWER(TRIM(RawData[[#This Row],[Location]]))="anekal",OR(ISNUMBER(SEARCH("ernika",LOWER(RawData[[#This Row],[Project Name]]))),ISNUMBER(SEARCH("enrika",LOWER(RawData[[#This Row],[Project Name]]))),ISNUMBER(SEARCH("exotica",LOWER(RawData[[#This Row],[Project Name]]))),ISNUMBER(SEARCH(" eka",LOWER(RawData[[#This Row],[Project Name]]))))))) -> 1 | W13: ='Telecaller Performance'!A17 | X13: {=IF(W13="",NA(),_xlfn.LET(_xlpm.v,SUBTOTAL(103,OFFSET(RawData[Mobile],ROW(RawData[Mobile])-MIN(ROW(RawData[Mobile])),0,1)),_xlpm.z,SUMPRODUCT(_xlpm.v,--(RawData[Telecaller Name]=W13)),IF(_xlpm.z=0,NA(),MAX(0,1-SUMPRODUCT(_xlpm.v,--(RawData[Telecaller Name]=W13),RawData[Error Flag])/_xlpm.z))))} -> #N/A | Z13: ='Telecaller Performance'!A17 | AA13: {=IF(Z13="",NA(),_xlfn.LET(_xlpm.v,SUBTOTAL(103,OFFSET(RawData[Mobile],ROW(RawData[Mobile])-MIN(ROW(RawData[Mobile])),0,1)),_xlpm.z,SUMPRODUCT(_xlpm.v,--(RawData[Telecaller Name]=Z13)),IF(_xlpm.z=0,NA(),SUMPRODUCT(_xlpm.v,--(RawData[Telecaller Name]=Z13),RawData[Error Flag]))))} -> #N/A | AF13: {=IFERROR(INDEX(_xlfn._xlws.SORT(_xlfn.UNIQUE(_xlfn._xlws.FILTER(RawData[Project Name],RawData[Project Name]<>""))),ROWS(AF$2:AF13)),"")} | AG13: {=IF(AF13="",NA(),_xlfn.LET(_xlpm.v,SUBTOTAL(103,OFFSET(RawData[Mobile],ROW(RawData[Mobile])-MIN(ROW(RawData[Mobile])),0,1)),_xlpm.z,SUMPRODUCT(_xlpm.v,--(RawData[Project Name]=AF13)),IF(_xlpm.z=0,NA(),SUMPRODUCT(_xlpm.v,--(RawData[Project Name]=AF13),RawData[Error Flag]))))} -> #N/A
A14: Guru Punvaanii Ernika | B14: 8870745937 | C14: Vinutha M1 | D14: 46254 | E14: warm | F14: Seeing for 1200sqft , located at electronic city , seeing for self asked me to share details they will check and get back | G14: 46256.431 | H14: Anekal | I14: -1 | J14: Interested | K14: In Progress | L14: Seeing for 1200sqft , located at electronic city, seeing for self | M14: Online Portal | N14: 99 Acres | O14: 1 | P14: =IF(RawData[[#This Row],[Mobile]]="","",_xlfn.TEXTJOIN(" | ",TRUE,IF(AND(OR(LOWER(TRIM(RawData[[#This Row],[Lead Status]]))="cold",LOWER(TRIM(RawData[[#This Row],[Lead Status]]))="lost"),OR(ISNUMBER(SEARCH("visit",LOWER(TRIM(RawData[[#This Row],[Comments]])))),ISNUMBER(SEARCH("brochure",LOWER(TRIM(RawData[[#This Row],[Comments]])))),ISNUMBER(SEARCH("pricing",LOWER(TRIM(RawData[[#This Row],[Comments]])))),ISNUMBER(SEARCH("price",LOWER(TRIM(RawData[[#This Row],[Comments]])))),ISNUMBER(SEARCH("budget",LOWER(TRIM(RawData[[#This Row],[Comments]])))))),"Wrong Lead Status",""),IF(AND(LOWER(TRIM(RawData[[#This Row],[Lead Status]]))="cold",OR(LOWER(TRIM(RawData[[#This Row],[Comments]]))="rnr",LOWER(TRIM(RawData[[#This Row],[Comments]]))="busy",LOWER(TRIM(RawData[[#This Row],[Comments]]))="out of network",LOWER(TRIM(RawData[[#This Row],[Comments]]))="outoff network",LOWER(TRIM(RawData[[#This Row],[Comments]]))="voice mail",LOWER(TRIM(RawData[[#This Row],[Comments]]))="voicemail")),"RNR Classification Error",""),IF(AND(LOWER(TRIM(RawData[[#This Row],[Lead Status]]))="warm",OR(LOWER(TRIM(RawData[[#This Row],[Comments]]))="busy",LOWER(TRIM(RawData[[#This Row],[Comments]]))="voice mail",LOWER(TRIM(RawData[[#This Row],[Comments]]))="voicemail",LOWER(TRIM(RawData[[#This Row],[Comments]]))="call back later")),"Warm Status Mismatch",""),IF(AND(LOWER(TRIM(RawData[[#This Row],[Status]]))="rnr",OR(ISNUMBER(SEARCH("requirement",LOWER(RawData[[#This Row],[Comments]]&" "&RawData[[#This Row],[Customer Requirement]]))),ISNUMBER(SEARCH("budget",LOWER(RawData[[#This Row],[Comments]]&" "&RawData[[#This Row],[Customer Requirement]]))),ISNUMBER(SEARCH("location",LOWER(RawData[[#This Row],[Comments]]&" "&RawData[[#This Row],[Customer Requirement]]))),ISNUMBER(SEARCH("purpose",LOWER(RawData[[#This Row],[Comments]]&" "&RawData[[#This Row],[Customer Requirement]]))),ISNUMBER(SEARCH("dimension",LOWER(RawData[[#This Row],[Comments]]&" "&RawData[[#This Row],[Customer Requirement]]))),ISNUMBER(SEARCH("sqft",LOWER(RawData[[#This Row],[Comments]]&" "&RawData[[#This Row],[Customer Requirement]]))))),"CRM Status Mismatch",""),IF(AND(ISNUMBER(RawData[[#This Row],[Next Followup Date]]),RawData[[#This Row],[Next Followup Date]]<NOW(),OR(LOWER(TRIM(RawData[[#This Row],[Lead Status]]))="hot",LOWER(TRIM(RawData[[#This Row],[Lead Status]]))="prospect",LOWER(TRIM(RawData[[#This Row],[Lead Status]]))="warm")),"Follow-up Error",""),IF(AND(LOWER(TRIM(RawData[[#This Row],[Location]]))="anekal",OR(ISNUMBER(SEARCH("ernika",LOWER(RawData[[#This Row],[Project Name]]))),ISNUMBER(SEARCH("enrika",LOWER(RawData[[#This Row],[Project Name]]))),ISNUMBER(SEARCH("exotica",LOWER(RawData[[#This Row],[Project Name]]))),ISNUMBER(SEARCH(" eka",LOWER(RawData[[#This Row],[Project Name]]))))),"Customer Location Not Captured",""))) -> Customer Location Not Captured | Q14: =IF(RawData[[#This Row],[Mobile]]="","",_xlfn.TEXTJOIN(CHAR(10),TRUE,IF(AND(OR(LOWER(TRIM(RawData[[#This Row],[Lead Status]]))="cold",LOWER(TRIM(RawData[[#This Row],[Lead Status]]))="lost"),OR(ISNUMBER(SEARCH("visit",LOWER(TRIM(RawData[[#This Row],[Comments]])))),ISNUMBER(SEARCH("brochure",LOWER(TRIM(RawData[[#This Row],[Comments]])))),ISNUMBER(SEARCH("pricing",LOWER(TRIM(RawData[[#This Row],[Comments]])))),ISNUMBER(SEARCH("price",LOWER(TRIM(RawData[[#This Row],[Comments]])))),ISNUMBER(SEARCH("budget",LOWER(TRIM(RawData[[#This Row],[Comments]])))))),"Engagement intent conflicts with Cold/Lost status",""),IF(AND(LOWER(TRIM(RawData[[#This Row],[Lead Status]]))="cold",OR(LOWER(TRIM(RawData[[#This Row],[Comments]]))="rnr",LOWER(TRIM(RawData[[#This Row],[Comments]]))="busy",LOWER(TRIM(RawData[[#This Row],[Comments]]))="out of network",LOWER(TRIM(RawData[[#This Row],[Comments]]))="outoff network",LOWER(TRIM(RawData[[#This Row],[Comments]]))="voice mail",LOWER(TRIM(RawData[[#This Row],[Comments]]))="voicemail")),"Contact outcome should remain RNR rather than Cold",""),IF(AND(LOWER(TRIM(RawData[[#This Row],[Lead Status]]))="warm",OR(LOWER(TRIM(RawData[[#This Row],[Comments]]))="busy",LOWER(TRIM(RawData[[#This Row],[Comments]]))="voice mail",LOWER(TRIM(RawData[[#This Row],[Comments]]))="voicemail",LOWER(TRIM(RawData[[#This Row],[Comments]]))="call back later")),"Contact-only outcome does not support Warm status",""),IF(AND(LOWER(TRIM(RawData[[#This Row],[Status]]))="rnr",OR(ISNUMBER(SEARCH("requirement",LOWER(RawData[[#This Row],[Comments]]&" "&RawData[[#This Row],[Customer Requirement]]))),ISNUMBER(SEARCH("budget",LOWER(RawData[[#This Row],[Comments]]&" "&RawData[[#This Row],[Customer Requirement]]))),ISNUMBER(SEARCH("location",LOWER(RawData[[#This Row],[Comments]]&" "&RawData[[#This Row],[Customer Requirement]]))),ISNUMBER(SEARCH("purpose",LOWER(RawData[[#This Row],[Comments]]&" "&RawData[[#This Row],[Customer Requirement]]))),ISNUMBER(SEARCH("dimension",LOWER(RawData[[#This Row],[Comments]]&" "&RawData[[#This Row],[Customer Requirement]]))),ISNUMBER(SEARCH("sqft",LOWER(RawData[[#This Row],[Comments]]&" "&RawData[[#This Row],[Customer Requirement]]))))),"Requirements were captured while CRM status remains RNR",""),IF(AND(ISNUMBER(RawData[[#This Row],[Next Followup Date]]),RawData[[#This Row],[Next Followup Date]]<NOW(),OR(LOWER(TRIM(RawData[[#This Row],[Lead Status]]))="hot",LOWER(TRIM(RawData[[#This Row],[Lead Status]]))="prospect",LOWER(TRIM(RawData[[#This Row],[Lead Status]]))="warm")),"Follow-up date/time has passed for an active lead",""),IF(AND(LOWER(TRIM(RawData[[#This Row],[Location]]))="anekal",OR(ISNUMBER(SEARCH("ernika",LOWER(RawData[[#This Row],[Project Name]]))),ISNUMBER(SEARCH("enrika",LOWER(RawData[[#This Row],[Project Name]]))),ISNUMBER(SEARCH("exotica",LOWER(RawData[[#This Row],[Project Name]]))),ISNUMBER(SEARCH(" eka",LOWER(RawData[[#This Row],[Project Name]]))))),"Anekal is the project default; customer location was not captured",""))) -> Anekal is the project default; customer location was not captured | R14: =IF(RawData[[#This Row],[Mobile]]="","",_xlfn.TEXTJOIN(CHAR(10),TRUE,IF(AND(OR(LOWER(TRIM(RawData[[#This Row],[Lead Status]]))="cold",LOWER(TRIM(RawData[[#This Row],[Lead Status]]))="lost"),OR(ISNUMBER(SEARCH("visit",LOWER(TRIM(RawData[[#This Row],[Comments]])))),ISNUMBER(SEARCH("brochure",LOWER(TRIM(RawData[[#This Row],[Comments]])))),ISNUMBER(SEARCH("pricing",LOWER(TRIM(RawData[[#This Row],[Comments]])))),ISNUMBER(SEARCH("price",LOWER(TRIM(RawData[[#This Row],[Comments]])))),ISNUMBER(SEARCH("budget",LOWER(TRIM(RawData[[#This Row],[Comments]])))))),"Reclassify lead and schedule a documented follow-up",""),IF(AND(LOWER(TRIM(RawData[[#This Row],[Lead Status]]))="cold",OR(LOWER(TRIM(RawData[[#This Row],[Comments]]))="rnr",LOWER(TRIM(RawData[[#This Row],[Comments]]))="busy",LOWER(TRIM(RawData[[#This Row],[Comments]]))="out of network",LOWER(TRIM(RawData[[#This Row],[Comments]]))="outoff network",LOWER(TRIM(RawData[[#This Row],[Comments]]))="voice mail",LOWER(TRIM(RawData[[#This Row],[Comments]]))="voicemail")),"Change lead classification to RNR and retry contact",""),IF(AND(LOWER(TRIM(RawData[[#This Row],[Lead Status]]))="warm",OR(LOWER(TRIM(RawData[[#This Row],[Comments]]))="busy",LOWER(TRIM(RawData[[#This Row],[Comments]]))="voice mail",LOWER(TRIM(RawData[[#This Row],[Comments]]))="voicemail",LOWER(TRIM(RawData[[#This Row],[Comments]]))="call back later")),"Validate engagement before retaining Warm status",""),IF(AND(LOWER(TRIM(RawData[[#This Row],[Status]]))="rnr",OR(ISNUMBER(SEARCH("requirement",LOWER(RawData[[#This Row],[Comments]]&" "&RawData[[#This Row],[Customer Requirement]]))),ISNUMBER(SEARCH("budget",LOWER(RawData[[#This Row],[Comments]]&" "&RawData[[#This Row],[Customer Requirement]]))),ISNUMBER(SEARCH("location",LOWER(RawData[[#This Row],[Comments]]&" "&RawData[[#This Row],[Customer Requirement]]))),ISNUMBER(SEARCH("purpose",LOWER(RawData[[#This Row],[Comments]]&" "&RawData[[#This Row],[Customer Requirement]]))),ISNUMBER(SEARCH("dimension",LOWER(RawData[[#This Row],[Comments]]&" "&RawData[[#This Row],[Customer Requirement]]))),ISNUMBER(SEARCH("sqft",LOWER(RawData[[#This Row],[Comments]]&" "&RawData[[#This Row],[Customer Requirement]]))))),"Update CRM status to reflect the collected requirement",""),IF(AND(ISNUMBER(RawData[[#This Row],[Next Followup Date]]),RawData[[#This Row],[Next Followup Date]]<NOW(),OR(LOWER(TRIM(RawData[[#This Row],[Lead Status]]))="hot",LOWER(TRIM(RawData[[#This Row],[Lead Status]]))="prospect",LOWER(TRIM(RawData[[#This Row],[Lead Status]]))="warm")),"Contact immediately and set the next follow-up",""),IF(AND(LOWER(TRIM(RawData[[#This Row],[Location]]))="anekal",OR(ISNUMBER(SEARCH("ernika",LOWER(RawData[[#This Row],[Project Name]]))),ISNUMBER(SEARCH("enrika",LOWER(RawData[[#This Row],[Project Name]]))),ISNUMBER(SEARCH("exotica",LOWER(RawData[[#This Row],[Project Name]]))),ISNUMBER(SEARCH(" eka",LOWER(RawData[[#This Row],[Project Name]]))))),"Contact the customer and record their actual location",""))) -> Contact the customer and record their actual location | S14: =IF(RawData[[#This Row],[Error Flag]]=0,"",IF(OR(ISNUMBER(SEARCH("Wrong Lead Status",RawData[[#This Row],[Error Type]])),ISNUMBER(SEARCH("RNR Classification Error",RawData[[#This Row],[Error Type]])),ISNUMBER(SEARCH("Follow-up Error",RawData[[#This Row],[Error Type]]))),"Critical","Medium")) -> Medium | T14: =IF(RawData[[#This Row],[Error Flag]]=0,"Pass","Action Required ("&RawData[[#This Row],[Error Flag]]&IF(RawData[[#This Row],[Error Flag]]=1," error)"," errors)")) -> Action Required (1 error) | U14: =IF(RawData[[#This Row],[Mobile]]="",0,--(AND(OR(LOWER(TRIM(RawData[[#This Row],[Lead Status]]))="cold",LOWER(TRIM(RawData[[#This Row],[Lead Status]]))="lost"),OR(ISNUMBER(SEARCH("visit",LOWER(TRIM(RawData[[#This Row],[Comments]])))),ISNUMBER(SEARCH("brochure",LOWER(TRIM(RawData[[#This Row],[Comments]])))),ISNUMBER(SEARCH("pricing",LOWER(TRIM(RawData[[#This Row],[Comments]])))),ISNUMBER(SEARCH("price",LOWER(TRIM(RawData[[#This Row],[Comments]])))),ISNUMBER(SEARCH("budget",LOWER(TRIM(RawData[[#This Row],[Comments]])))))))+--(AND(LOWER(TRIM(RawData[[#This Row],[Lead Status]]))="cold",OR(LOWER(TRIM(RawData[[#This Row],[Comments]]))="rnr",LOWER(TRIM(RawData[[#This Row],[Comments]]))="busy",LOWER(TRIM(RawData[[#This Row],[Comments]]))="out of network",LOWER(TRIM(RawData[[#This Row],[Comments]]))="outoff network",LOWER(TRIM(RawData[[#This Row],[Comments]]))="voice mail",LOWER(TRIM(RawData[[#This Row],[Comments]]))="voicemail")))+--(AND(LOWER(TRIM(RawData[[#This Row],[Lead Status]]))="warm",OR(LOWER(TRIM(RawData[[#This Row],[Comments]]))="busy",LOWER(TRIM(RawData[[#This Row],[Comments]]))="voice mail",LOWER(TRIM(RawData[[#This Row],[Comments]]))="voicemail",LOWER(TRIM(RawData[[#This Row],[Comments]]))="call back later")))+--(AND(LOWER(TRIM(RawData[[#This Row],[Status]]))="rnr",OR(ISNUMBER(SEARCH("requirement",LOWER(RawData[[#This Row],[Comments]]&" "&RawData[[#This Row],[Customer Requirement]]))),ISNUMBER(SEARCH("budget",LOWER(RawData[[#This Row],[Comments]]&" "&RawData[[#This Row],[Customer Requirement]]))),ISNUMBER(SEARCH("location",LOWER(RawData[[#This Row],[Comments]]&" "&RawData[[#This Row],[Customer Requirement]]))),ISNUMBER(SEARCH("purpose",LOWER(RawData[[#This Row],[Comments]]&" "&RawData[[#This Row],[Customer Requirement]]))),ISNUMBER(SEARCH("dimension",LOWER(RawData[[#This Row],[Comments]]&" "&RawData[[#This Row],[Customer Requirement]]))),ISNUMBER(SEARCH("sqft",LOWER(RawData[[#This Row],[Comments]]&" "&RawData[[#This Row],[Customer Requirement]]))))))+--(AND(ISNUMBER(RawData[[#This Row],[Next Followup Date]]),RawData[[#This Row],[Next Followup Date]]<NOW(),OR(LOWER(TRIM(RawData[[#This Row],[Lead Status]]))="hot",LOWER(TRIM(RawData[[#This Row],[Lead Status]]))="prospect",LOWER(TRIM(RawData[[#This Row],[Lead Status]]))="warm")))+--(AND(LOWER(TRIM(RawData[[#This Row],[Location]]))="anekal",OR(ISNUMBER(SEARCH("ernika",LOWER(RawData[[#This Row],[Project Name]]))),ISNUMBER(SEARCH("enrika",LOWER(RawData[[#This Row],[Project Name]]))),ISNUMBER(SEARCH("exotica",LOWER(RawData[[#This Row],[Project Name]]))),ISNUMBER(SEARCH(" eka",LOWER(RawData[[#This Row],[Project Name]]))))))) -> 1 | W14: ='Telecaller Performance'!A18 | X14: {=IF(W14="",NA(),_xlfn.LET(_xlpm.v,SUBTOTAL(103,OFFSET(RawData[Mobile],ROW(RawData[Mobile])-MIN(ROW(RawData[Mobile])),0,1)),_xlpm.z,SUMPRODUCT(_xlpm.v,--(RawData[Telecaller Name]=W14)),IF(_xlpm.z=0,NA(),MAX(0,1-SUMPRODUCT(_xlpm.v,--(RawData[Telecaller Name]=W14),RawData[Error Flag])/_xlpm.z))))} -> #N/A | Z14: ='Telecaller Performance'!A18 | AA14: {=IF(Z14="",NA(),_xlfn.LET(_xlpm.v,SUBTOTAL(103,OFFSET(RawData[Mobile],ROW(RawData[Mobile])-MIN(ROW(RawData[Mobile])),0,1)),_xlpm.z,SUMPRODUCT(_xlpm.v,--(RawData[Telecaller Name]=Z14)),IF(_xlpm.z=0,NA(),SUMPRODUCT(_xlpm.v,--(RawData[Telecaller Name]=Z14),RawData[Error Flag]))))} -> #N/A | AF14: {=IFERROR(INDEX(_xlfn._xlws.SORT(_xlfn.UNIQUE(_xlfn._xlws.FILTER(RawData[Project Name],RawData[Project Name]<>""))),ROWS(AF$2:AF14)),"")} | AG14: {=IF(AF14="",NA(),_xlfn.LET(_xlpm.v,SUBTOTAL(103,OFFSET(RawData[Mobile],ROW(RawData[Mobile])-MIN(ROW(RawData[Mobile])),0,1)),_xlpm.z,SUMPRODUCT(_xlpm.v,--(RawData[Project Name]=AF14)),IF(_xlpm.z=0,NA(),SUMPRODUCT(_xlpm.v,--(RawData[Project Name]=AF14),RawData[Error Flag]))))} -> #N/A
A15: Guru Punvaanii Ernika | B15: 9113651947 | C15: Vinutha M1 | D15: 46254 | E15: warm | F15: Rnr | G15: 46256.47 | I15: -1 | J15: Interested | K15: RNR | L15: .. | M15: Digital Marketing | N15: WhatsApp | O15: 1 | P15: =IF(RawData[[#This Row],[Mobile]]="","",_xlfn.TEXTJOIN(" | ",TRUE,IF(AND(OR(LOWER(TRIM(RawData[[#This Row],[Lead Status]]))="cold",LOWER(TRIM(RawData[[#This Row],[Lead Status]]))="lost"),OR(ISNUMBER(SEARCH("visit",LOWER(TRIM(RawData[[#This Row],[Comments]])))),ISNUMBER(SEARCH("brochure",LOWER(TRIM(RawData[[#This Row],[Comments]])))),ISNUMBER(SEARCH("pricing",LOWER(TRIM(RawData[[#This Row],[Comments]])))),ISNUMBER(SEARCH("price",LOWER(TRIM(RawData[[#This Row],[Comments]])))),ISNUMBER(SEARCH("budget",LOWER(TRIM(RawData[[#This Row],[Comments]])))))),"Wrong Lead Status",""),IF(AND(LOWER(TRIM(RawData[[#This Row],[Lead Status]]))="cold",OR(LOWER(TRIM(RawData[[#This Row],[Comments]]))="rnr",LOWER(TRIM(RawData[[#This Row],[Comments]]))="busy",LOWER(TRIM(RawData[[#This Row],[Comments]]))="out of network",LOWER(TRIM(RawData[[#This Row],[Comments]]))="outoff network",LOWER(TRIM(RawData[[#This Row],[Comments]]))="voice mail",LOWER(TRIM(RawData[[#This Row],[Comments]]))="voicemail")),"RNR Classification Error",""),IF(AND(LOWER(TRIM(RawData[[#This Row],[Lead Status]]))="warm",OR(LOWER(TRIM(RawData[[#This Row],[Comments]]))="busy",LOWER(TRIM(RawData[[#This Row],[Comments]]))="voice mail",LOWER(TRIM(RawData[[#This Row],[Comments]]))="voicemail",LOWER(TRIM(RawData[[#This Row],[Comments]]))="call back later")),"Warm Status Mismatch",""),IF(AND(LOWER(TRIM(RawData[[#This Row],[Status]]))="rnr",OR(ISNUMBER(SEARCH("requirement",LOWER(RawData[[#This Row],[Comments]]&" "&RawData[[#This Row],[Customer Requirement]]))),ISNUMBER(SEARCH("budget",LOWER(RawData[[#This Row],[Comments]]&" "&RawData[[#This Row],[Customer Requirement]]))),ISNUMBER(SEARCH("location",LOWER(RawData[[#This Row],[Comments]]&" "&RawData[[#This Row],[Customer Requirement]]))),ISNUMBER(SEARCH("purpose",LOWER(RawData[[#This Row],[Comments]]&" "&RawData[[#This Row],[Customer Requirement]]))),ISNUMBER(SEARCH("dimension",LOWER(RawData[[#This Row],[Comments]]&" "&RawData[[#This Row],[Customer Requirement]]))),ISNUMBER(SEARCH("sqft",LOWER(RawData[[#This Row],[Comments]]&" "&RawData[[#This Row],[Customer Requirement]]))))),"CRM Status Mismatch",""),IF(AND(ISNUMBER(RawData[[#This Row],[Next Followup Date]]),RawData[[#This Row],[Next Followup Date]]<NOW(),OR(LOWER(TRIM(RawData[[#This Row],[Lead Status]]))="hot",LOWER(TRIM(RawData[[#This Row],[Lead Status]]))="prospect",LOWER(TRIM(RawData[[#This Row],[Lead Status]]))="warm")),"Follow-up Error",""),IF(AND(LOWER(TRIM(RawData[[#This Row],[Location]]))="anekal",OR(ISNUMBER(SEARCH("ernika",LOWER(RawData[[#This Row],[Project Name]]))),ISNUMBER(SEARCH("enrika",LOWER(RawData[[#This Row],[Project Name]]))),ISNUMBER(SEARCH("exotica",LOWER(RawData[[#This Row],[Project Name]]))),ISNUMBER(SEARCH(" eka",LOWER(RawData[[#This Row],[Project Name]]))))),"Customer Location Not Captured",""))) | Q15: =IF(RawData[[#This Row],[Mobile]]="","",_xlfn.TEXTJOIN(CHAR(10),TRUE,IF(AND(OR(LOWER(TRIM(RawData[[#This Row],[Lead Status]]))="cold",LOWER(TRIM(RawData[[#This Row],[Lead Status]]))="lost"),OR(ISNUMBER(SEARCH("visit",LOWER(TRIM(RawData[[#This Row],[Comments]])))),ISNUMBER(SEARCH("brochure",LOWER(TRIM(RawData[[#This Row],[Comments]])))),ISNUMBER(SEARCH("pricing",LOWER(TRIM(RawData[[#This Row],[Comments]])))),ISNUMBER(SEARCH("price",LOWER(TRIM(RawData[[#This Row],[Comments]])))),ISNUMBER(SEARCH("budget",LOWER(TRIM(RawData[[#This Row],[Comments]])))))),"Engagement intent conflicts with Cold/Lost status",""),IF(AND(LOWER(TRIM(RawData[[#This Row],[Lead Status]]))="cold",OR(LOWER(TRIM(RawData[[#This Row],[Comments]]))="rnr",LOWER(TRIM(RawData[[#This Row],[Comments]]))="busy",LOWER(TRIM(RawData[[#This Row],[Comments]]))="out of network",LOWER(TRIM(RawData[[#This Row],[Comments]]))="outoff network",LOWER(TRIM(RawData[[#This Row],[Comments]]))="voice mail",LOWER(TRIM(RawData[[#This Row],[Comments]]))="voicemail")),"Contact outcome should remain RNR rather than Cold",""),IF(AND(LOWER(TRIM(RawData[[#This Row],[Lead Status]]))="warm",OR(LOWER(TRIM(RawData[[#This Row],[Comments]]))="busy",LOWER(TRIM(RawData[[#This Row],[Comments]]))="voice mail",LOWER(TRIM(RawData[[#This Row],[Comments]]))="voicemail",LOWER(TRIM(RawData[[#This Row],[Comments]]))="call back later")),"Contact-only outcome does not support Warm status",""),IF(AND(LOWER(TRIM(RawData[[#This Row],[Status]]))="rnr",OR(ISNUMBER(SEARCH("requirement",LOWER(RawData[[#This Row],[Comments]]&" "&RawData[[#This Row],[Customer Requirement]]))),ISNUMBER(SEARCH("budget",LOWER(RawData[[#This Row],[Comments]]&" "&RawData[[#This Row],[Customer Requirement]]))),ISNUMBER(SEARCH("location",LOWER(RawData[[#This Row],[Comments]]&" "&RawData[[#This Row],[Customer Requirement]]))),ISNUMBER(SEARCH("purpose",LOWER(RawData[[#This Row],[Comments]]&" "&RawData[[#This Row],[Customer Requirement]]))),ISNUMBER(SEARCH("dimension",LOWER(RawData[[#This Row],[Comments]]&" "&RawData[[#This Row],[Customer Requirement]]))),ISNUMBER(SEARCH("sqft",LOWER(RawData[[#This Row],[Comments]]&" "&RawData[[#This Row],[Customer Requirement]]))))),"Requirements were captured while CRM status remains RNR",""),IF(AND(ISNUMBER(RawData[[#This Row],[Next Followup Date]]),RawData[[#This Row],[Next Followup Date]]<NOW(),OR(LOWER(TRIM(RawData[[#This Row],[Lead Status]]))="hot",LOWER(TRIM(RawData[[#This Row],[Lead Status]]))="prospect",LOWER(TRIM(RawData[[#This Row],[Lead Status]]))="warm")),"Follow-up date/time has passed for an active lead",""),IF(AND(LOWER(TRIM(RawData[[#This Row],[Location]]))="anekal",OR(ISNUMBER(SEARCH("ernika",LOWER(RawData[[#This Row],[Project Name]]))),ISNUMBER(SEARCH("enrika",LOWER(RawData[[#This Row],[Project Name]]))),ISNUMBER(SEARCH("exotica",LOWER(RawData[[#This Row],[Project Name]]))),ISNUMBER(SEARCH(" eka",LOWER(RawData[[#This Row],[Project Name]]))))),"Anekal is the project default; customer location was not captured",""))) | R15: =IF(RawData[[#This Row],[Mobile]]="","",_xlfn.TEXTJOIN(CHAR(10),TRUE,IF(AND(OR(LOWER(TRIM(RawData[[#This Row],[Lead Status]]))="cold",LOWER(TRIM(RawData[[#This Row],[Lead Status]]))="lost"),OR(ISNUMBER(SEARCH("visit",LOWER(TRIM(RawData[[#This Row],[Comments]])))),ISNUMBER(SEARCH("brochure",LOWER(TRIM(RawData[[#This Row],[Comments]])))),ISNUMBER(SEARCH("pricing",LOWER(TRIM(RawData[[#This Row],[Comments]])))),ISNUMBER(SEARCH("price",LOWER(TRIM(RawData[[#This Row],[Comments]])))),ISNUMBER(SEARCH("budget",LOWER(TRIM(RawData[[#This Row],[Comments]])))))),"Reclassify lead and schedule a documented follow-up",""),IF(AND(LOWER(TRIM(RawData[[#This Row],[Lead Status]]))="cold",OR(LOWER(TRIM(RawData[[#This Row],[Comments]]))="rnr",LOWER(TRIM(RawData[[#This Row],[Comments]]))="busy",LOWER(TRIM(RawData[[#This Row],[Comments]]))="out of network",LOWER(TRIM(RawData[[#This Row],[Comments]]))="outoff network",LOWER(TRIM(RawData[[#This Row],[Comments]]))="voice mail",LOWER(TRIM(RawData[[#This Row],[Comments]]))="voicemail")),"Change lead classification to RNR and retry contact",""),IF(AND(LOWER(TRIM(RawData[[#This Row],[Lead Status]]))="warm",OR(LOWER(TRIM(RawData[[#This Row],[Comments]]))="busy",LOWER(TRIM(RawData[[#This Row],[Comments]]))="voice mail",LOWER(TRIM(RawData[[#This Row],[Comments]]))="voicemail",LOWER(TRIM(RawData[[#This Row],[Comments]]))="call back later")),"Validate engagement before retaining Warm status",""),IF(AND(LOWER(TRIM(RawData[[#This Row],[Status]]))="rnr",OR(ISNUMBER(SEARCH("requirement",LOWER(RawData[[#This Row],[Comments]]&" "&RawData[[#This Row],[Customer Requirement]]))),ISNUMBER(SEARCH("budget",LOWER(RawData[[#This Row],[Comments]]&" "&RawData[[#This Row],[Customer Requirement]]))),ISNUMBER(SEARCH("location",LOWER(RawData[[#This Row],[Comments]]&" "&RawData[[#This Row],[Customer Requirement]]))),ISNUMBER(SEARCH("purpose",LOWER(RawData[[#This Row],[Comments]]&" "&RawData[[#This Row],[Customer Requirement]]))),ISNUMBER(SEARCH("dimension",LOWER(RawData[[#This Row],[Comments]]&" "&RawData[[#This Row],[Customer Requirement]]))),ISNUMBER(SEARCH("sqft",LOWER(RawData[[#This Row],[Comments]]&" "&RawData[[#This Row],[Customer Requirement]]))))),"Update CRM status to reflect the collected requirement",""),IF(AND(ISNUMBER(RawData[[#This Row],[Next Followup Date]]),RawData[[#This Row],[Next Followup Date]]<NOW(),OR(LOWER(TRIM(RawData[[#This Row],[Lead Status]]))="hot",LOWER(TRIM(RawData[[#This Row],[Lead Status]]))="prospect",LOWER(TRIM(RawData[[#This Row],[Lead Status]]))="warm")),"Contact immediately and set the next follow-up",""),IF(AND(LOWER(TRIM(RawData[[#This Row],[Location]]))="anekal",OR(ISNUMBER(SEARCH("ernika",LOWER(RawData[[#This Row],[Project Name]]))),ISNUMBER(SEARCH("enrika",LOWER(RawData[[#This Row],[Project Name]]))),ISNUMBER(SEARCH("exotica",LOWER(RawData[[#This Row],[Project Name]]))),ISNUMBER(SEARCH(" eka",LOWER(RawData[[#This Row],[Project Name]]))))),"Contact the customer and record their actual location",""))) | S15: =IF(RawData[[#This Row],[Error Flag]]=0,"",IF(OR(ISNUMBER(SEARCH("Wrong Lead Status",RawData[[#This Row],[Error Type]])),ISNUMBER(SEARCH("RNR Classification Error",RawData[[#This Row],[Error Type]])),ISNUMBER(SEARCH("Follow-up Error",RawData[[#This Row],[Error Type]]))),"Critical","Medium")) | T15: =IF(RawData[[#This Row],[Error Flag]]=0,"Pass","Action Required ("&RawData[[#This Row],[Error Flag]]&IF(RawData[[#This Row],[Error Flag]]=1," error)"," errors)")) -> Pass | U15: =IF(RawData[[#This Row],[Mobile]]="",0,--(AND(OR(LOWER(TRIM(RawData[[#This Row],[Lead Status]]))="cold",LOWER(TRIM(RawData[[#This Row],[Lead Status]]))="lost"),OR(ISNUMBER(SEARCH("visit",LOWER(TRIM(RawData[[#This Row],[Comments]])))),ISNUMBER(SEARCH("brochure",LOWER(TRIM(RawData[[#This Row],[Comments]])))),ISNUMBER(SEARCH("pricing",LOWER(TRIM(RawData[[#This Row],[Comments]])))),ISNUMBER(SEARCH("price",LOWER(TRIM(RawData[[#This Row],[Comments]])))),ISNUMBER(SEARCH("budget",LOWER(TRIM(RawData[[#This Row],[Comments]])))))))+--(AND(LOWER(TRIM(RawData[[#This Row],[Lead Status]]))="cold",OR(LOWER(TRIM(RawData[[#This Row],[Comments]]))="rnr",LOWER(TRIM(RawData[[#This Row],[Comments]]))="busy",LOWER(TRIM(RawData[[#This Row],[Comments]]))="out of network",LOWER(TRIM(RawData[[#This Row],[Comments]]))="outoff network",LOWER(TRIM(RawData[[#This Row],[Comments]]))="voice mail",LOWER(TRIM(RawData[[#This Row],[Comments]]))="voicemail")))+--(AND(LOWER(TRIM(RawData[[#This Row],[Lead Status]]))="warm",OR(LOWER(TRIM(RawData[[#This Row],[Comments]]))="busy",LOWER(TRIM(RawData[[#This Row],[Comments]]))="voice mail",LOWER(TRIM(RawData[[#This Row],[Comments]]))="voicemail",LOWER(TRIM(RawData[[#This Row],[Comments]]))="call back later")))+--(AND(LOWER(TRIM(RawData[[#This Row],[Status]]))="rnr",OR(ISNUMBER(SEARCH("requirement",LOWER(RawData[[#This Row],[Comments]]&" "&RawData[[#This Row],[Customer Requirement]]))),ISNUMBER(SEARCH("budget",LOWER(RawData[[#This Row],[Comments]]&" "&RawData[[#This Row],[Customer Requirement]]))),ISNUMBER(SEARCH("location",LOWER(RawData[[#This Row],[Comments]]&" "&RawData[[#This Row],[Customer Requirement]]))),ISNUMBER(SEARCH("purpose",LOWER(RawData[[#This Row],[Comments]]&" "&RawData[[#This Row],[Customer Requirement]]))),ISNUMBER(SEARCH("dimension",LOWER(RawData[[#This Row],[Comments]]&" "&RawData[[#This Row],[Customer Requirement]]))),ISNUMBER(SEARCH("sqft",LOWER(RawData[[#This Row],[Comments]]&" "&RawData[[#This Row],[Customer Requirement]]))))))+--(AND(ISNUMBER(RawData[[#This Row],[Next Followup Date]]),RawData[[#This Row],[Next Followup Date]]<NOW(),OR(LOWER(TRIM(RawData[[#This Row],[Lead Status]]))="hot",LOWER(TRIM(RawData[[#This Row],[Lead Status]]))="prospect",LOWER(TRIM(RawData[[#This Row],[Lead Status]]))="warm")))+--(AND(LOWER(TRIM(RawData[[#This Row],[Location]]))="anekal",OR(ISNUMBER(SEARCH("ernika",LOWER(RawData[[#This Row],[Project Name]]))),ISNUMBER(SEARCH("enrika",LOWER(RawData[[#This Row],[Project Name]]))),ISNUMBER(SEARCH("exotica",LOWER(RawData[[#This Row],[Project Name]]))),ISNUMBER(SEARCH(" eka",LOWER(RawData[[#This Row],[Project Name]]))))))) -> 0 | W15: ='Telecaller Performance'!A19 | X15: {=IF(W15="",NA(),_xlfn.LET(_xlpm.v,SUBTOTAL(103,OFFSET(RawData[Mobile],ROW(RawData[Mobile])-MIN(ROW(RawData[Mobile])),0,1)),_xlpm.z,SUMPRODUCT(_xlpm.v,--(RawData[Telecaller Name]=W15)),IF(_xlpm.z=0,NA(),MAX(0,1-SUMPRODUCT(_xlpm.v,--(RawData[Telecaller Name]=W15),RawData[Error Flag])/_xlpm.z))))} -> #N/A | Z15: ='Telecaller Performance'!A19 | AA15: {=IF(Z15="",NA(),_xlfn.LET(_xlpm.v,SUBTOTAL(103,OFFSET(RawData[Mobile],ROW(RawData[Mobile])-MIN(ROW(RawData[Mobile])),0,1)),_xlpm.z,SUMPRODUCT(_xlpm.v,--(RawData[Telecaller Name]=Z15)),IF(_xlpm.z=0,NA(),SUMPRODUCT(_xlpm.v,--(RawData[Telecaller Name]=Z15),RawData[Error Flag]))))} -> #N/A | AF15: {=IFERROR(INDEX(_xlfn._xlws.SORT(_xlfn.UNIQUE(_xlfn._xlws.FILTER(RawData[Project Name],RawData[Project Name]<>""))),ROWS(AF$2:AF15)),"")} | AG15: {=IF(AF15="",NA(),_xlfn.LET(_xlpm.v,SUBTOTAL(103,OFFSET(RawData[Mobile],ROW(RawData[Mobile])-MIN(ROW(RawData[Mobile])),0,1)),_xlpm.z,SUMPRODUCT(_xlpm.v,--(RawData[Project Name]=AF15)),IF(_xlpm.z=0,NA(),SUMPRODUCT(_xlpm.v,--(RawData[Project Name]=AF15),RawData[Error Flag]))))} -> #N/A
